Workbook
Name Key: リスト!$B$3:$B$4
Name フォーマット: リスト!$K$3:$K$8
Name プロトコル: リスト!$J$3:$J$11
Name 改行コード: リスト!$Q$3:$Q$6
Name 括り文字: リスト!$R$3:$R$7
Name 起動契機: リスト!$M$3:$M$10
Name 空ファイル生成: リスト!$S$3:$S$6
Name 桁数表記: リスト!$V$3:$V$5
Name 項目属性: リスト!$U$3:$U$11
Name 再処理単位: リスト!$O$3:$O$6
Name 小数部: リスト!$F$3:$F$5
Name 操作内容: リスト!$L$3:$L$8
Name 属性: リスト!$C$3:$C$8
Name 必須: リスト!$G$3:$G$4
Name 符号: リスト!$I$3:$I$6
Name 文字コード: リスト!$P$3:$P$7
Name 文字種別: リスト!$D$3:$D$6
Name 文字埋: リスト!$H$3:$H$7
Name 有り無し: リスト!$E$3:$E$5
Name 有無: リスト!$T$3:$T$5
Name 連携区分: リスト!$N$3:$N$5
Name 連携方式: リスト!$A$3:$A$8

Sheet 表紙
E11: KAPS2再構築PJ
E12: インターフェース項目定義書
C16: IFID | D16: IFZ9000018
C17: IF名称 | D17: K-WINC2連携用インボイスデータファイル
C18: 連携方式 | D18: ファイル連携

Sheet IFレイアウト
A1: IFID | D1: インターフェース名称
A2: =IF(表紙!D16<>"",表紙!D16,"") -> IFZ9000018 | D2: =IF(表紙!D17<>"",表紙!D17,"") -> K-WINC2連携用インボイスデータファイル
A4: No | B4: Key | C4: 項目名称 | D4: 技術名称 | E4: 属性 | F4: 文字種別 | G4: 文字数 | H4: Byte数 | I4: 小数桁 | J4: 小数点 | K4: 小数部 | L4: 桁区切り | M4: 必須 | N4: 文字埋 | O4: 符号 | P4: 階層構造 | Q4: 繰り返し数 | R4: 書式設定 | S4: 備考
A5: =ROW()-4 -> 1
A6: =ROW()-4 -> 2
A7: =ROW()-4 -> 3
A8: =ROW()-4 -> 4
A9: =ROW()-4 -> 5
A10: =ROW()-4 -> 6
A11: =ROW()-4 -> 7
A12: =ROW()-4 -> 8
A13: =ROW()-4 -> 9
A14: =ROW()-4 -> 10
A15: =ROW()-4 -> 11
A16: =ROW()-4 -> 12
... A59: =ROW()-4 -> 55

Sheet 項目マッピング (01)
A1: IFID | C1: インターフェース名称 | P1: →印刷範囲外（対向先とのセッション時に利用）
A2: =IF(表紙!D16<>"",表紙!D16,"") -> IFZ9000018 | C2: =IF(表紙!D17<>"",表紙!D17,"") -> K-WINC2連携用インボイスデータファイル
A4: 連携元 | G4: 連携元№ | H4: 変換 | J4: 連携先 | Q4: (補足）対向先調整メモ
A5: 部品SAP | H5: 変換仕様 | I5: 現行編集仕様（参考情報） | J5: KWINC2 | Q5: 現行からの変更内容 | T5: 部品SAP再現不可情報 | V5: 備考
A6: № | B6: 項目名称 | C6: 構造 | D6: 技術名称 | E6: 文字数 | F6: 属性 | J6: № | K6: 項目名称 | L6: 構造 | M6: 技術名称 | N6: 文字数 | O6: 属性 | Q6: 桁数 | R6: コード体系 | S6: 補足・その他 | T6: No. | U6: 分類
A7: S010 | G7: S010 | H7: 固定値01 | I7: 01'(固定値) | J7: S010 | K7: データ種別 | M7: DATAID | N7: 2 | O7: 文字(半角のみ)
A8: S020 | B8: シップメント伝票番号 | C8: VTTK | D8: TKNUM | E8: 10 | F8: CHAR | G8: S020 | H8: インボイスNo | I8: インボイス台帳ヘッド：同名項目 | J8: S020 | K8: インボイス№ | M8: BINV | N8: 10 | O8: 文字(半角のみ)
A9: S030 | B9: 受注先 | C9: LIKP | D9: KUNAG | E9: 10 | F9: CHAR | G9: S030 | I9: インボイス台帳ヘッド：同名項目 | J9: S030 | K9: 得意先コード | M9: BTKU | N9: 6 | O9: 文字(半角のみ)
A10: S040 | B10: 取引先機能：請求先の得意先コード | C10: VBPA | D10: KUNNR | E10: 10 | F10: CHAR | G10: S040 | H10: 出荷伝票→受注伝票と辿り受注伝票取引先から取得 | I10: インボイス台帳ヘッド：同名項目 | J10: S040 | K10: 請求得意先コード | M10: BSEKTKU | N10: 6 | O10: 文字(半角のみ)
A11: S050 | B11: 出荷条件 | C11: LIKP | D11: VSBED | E11: 2 | F11: CHAR | G11: S050 | I11: インボイス台帳ヘッド：同名項目 | J11: S050 | K11: 輸送便区分 | M11: CYUS | N11: 1 | O11: 文字(半角のみ)
A12: S060 | B12: 名称1＋名称2 | C12: ADRC ADRC | D12: NAME1 NAME2 | E12: 40 40 | F12: CHAR CHAR | G12: S060 | H12: 受注先のBPマスタから取得、名称1と名称2の結合 | I12: インボイス台帳ヘッド：同名項目 | J12: S060 | K12: 得意先名略称（漢字） | M12: NTKURAKKJ | N12: 20 | O12: 文字(全角のみ)
A13: S070 | B13: レコード登録日付 | C13: VTTK | D13: ERDAT | E13: 8 | F13: DATS | G13: S070 | I13: インボイス台帳ヘッド：同名項目 (YYYYMMDD編集) | J13: S070 | K13: インボイス作成日付 | M13: DINVSSI | N13: 8 | O13: 文字(半角のみ)
A14: S080 | G14: S080 | H14: 非標準 | I14: インボイス台帳ヘッド：同名項目 | J14: S080 | K14: 船積担当者コード | M14: BFZMTTS | N14: 3 | O14: 文字(半角のみ)
A15: S090 | B15: 出荷先 | C15: LIKP | D15: KUNNR | E15: 10 | F15: CHAR | G15: S090 | H15: 出荷先コードの下３桁 | I15: インボイス台帳ヘッド：同名項目 | J15: S090 | K15: 納所コード | M15: BNOS | N15: 3 | O15: 文字(半角のみ)
A16: S0100 | B16: 名称1＋名称2 (国際バージョン：カナ) | C16: ADRC ADRC | D16: NAME1 NAME2 | E16: 40 40 | F16: CHAR CHAR | G16: S0100 | H16: 出荷先のBPマスタから取得、名称1と名称2の結合 | I16: インボイス台帳ヘッド：同名項目 | J16: S0100 | K16: 納所名 | M16: NNOS | N16: 40 | O16: 文字(半角のみ)
A17: S0110 | B17: 市区町村＋地名 (国際バージョン：カナ) | C17: ADRC ADRC | D17: CITY1 STREET | E17: 40 60 | F17: CHAR CHAR | G17: S0110 | H17: 出荷先のBPマスタから取得 | I17: インボイス台帳ヘッド：同名項目 | J17: S0110 | K17: 納所住所 | M17: JNOS | N17: 40 | O17: 文字(半角のみ)
A18: S0120 | B18: 出荷タイプ | C18: VTTK | D18: VSART | E18: 2 | F18: CHAR | G18: S0120 | H18: 手配方法 | I18: インボイス台帳ヘッド：同名項目 | J18: S0120 | K18: 手配方法 | M18: CTHO | N18: 3 | O18: 文字(半角のみ)
A19: S0130 | G19: S0130 | H19: 非標準 S0350請求用建値とは違う？ | I19: インボイス台帳ヘッド：同名項目 | J19: S0130 | K19: 建値 | M19: TTTE | N19: 20 | O19: 文字(半角のみ)
A20: S0140 | G20: S0140 | H20: 非標準 ■業務Ｔ検討中 | I20: インボイス台帳ヘッド：同名項目 | J20: S0140 | K20: ケースマーク№ | M20: BCAM | N20: 3 | O20: 文字(半角のみ)
A21: S0150 | B21: 販売伝票通貨 | C21: VBAK | D21: WAERK | E21: 3 | F21: CUKY | G21: S0150 | H21: 出荷伝票→受注伝票と辿り受注伝票から取得 | I21: インボイス台帳ヘッド：同名項目 | J21: S0150 | K21: 通貨単位 | M21: CTUKTNI | N21: 3 | O21: 文字(半角のみ)
A22: S0160 | G22: S0160 | H22: 非標準 | I22: インボイス台帳ヘッド：同名項目 | J22: S0160 | K22: 得意先受取日付 | M22: DTKUUKT | N22: 8 | O22: 文字(半角のみ)
A23: S0170 | G23: S0170 | H23: ブランク | I23: - | J23: S0170 | K23: ピース数（合計） | M23: SPCETTL | N23: 6 | O23: 文字(半角のみ)
A24: S0180 | G24: S0180 | H24: ブランク | I24: - | J24: S0180 | K24: セット数（合計） | M24: SSETTTL | N24: 6 | O24: 文字(半角のみ)
A25: S0190 | G25: S0190 | H25: ブランク | I25: - | J25: S0190 | K25: 正味重量（合計） | M25: SSYMGYUTTL | N25: 11 | O25: 文字(半角のみ)
A26: S0200 | B26: 荷役単位の総重量 | C26: VEKP | D26: BRGEW | E26: 15,3 | F26: QUAN | G26: S0200 | H26: 紐つく梱包情報の総重量の合計値 | I26: インボイス台帳ヘッド：同名項目×100 (99999999編集) | J26: S0200 | K26: 梱包重量（合計） | M26: SKOPGYUTTL | N26: 8 | O26: 文字(半角のみ)
A27: S0210 | B27: 荷役単位の総数量 | C27: VEKP | D27: BTVOL | E27: 15,3 | F27: QUAN | G27: S0210 | H27: 紐つく梱包情報の総数量の合計値 | I27: インボイス台帳ヘッド：同名項目×1000 (9999999編集) | J27: S0210 | K27: 容量（合計） | M27: SYROTTL | N27: 7 | O27: 文字(半角のみ)
A28: S0220 | B28: VEKPの件数 | C28: VEKP | G28: S0220 | H28: 紐つく梱包情報の件数 ※外装のみ？内装含む？要確認 | I28: インボイス台帳ヘッド：同名項目 (99999編集) | J28: S0220 | K28: ケース数 | M28: SCAS | N28: 5 | O28: 文字(半角のみ)
A29: S0230 | G29: S0230 | H29: 非標準 インボイス金額合計（日本製）／（米国製）とは？ 紐つく出荷伝票→受注伝票と辿り受注伝票価格情報から外貨の金額を取得し合計？ | I29: インボイス台帳ヘッド：｛インボイス金額合計（日本製)＋インボイス金額合計（米国製)｝×100 (9999999999999編集) | J29: S0230 | K29: インボイス金額合計（外貨） | M29: KINVTTLABT | N29: 13 | O29: 文字(半角のみ)
A30: S0240 | G30: S0240 | H30: 紐つく出荷伝票→受注伝票と辿り受注伝票価格情報から邦貨の金額を取得し合計、でよいか？ | I30: インボイス台帳ヘッド：同名項目 (99999999999編集) | J30: S0240 | K30: インボイス金額合計（円貨） | M30: KINVTTLYEN | N30: 11 | O30: 文字(半角のみ)
A31: S0250 | G31: S0250 | H31: 非標準 インボイス金額合計（日本製）とは？ | I31: インボイス台帳ヘッド：同名項目×100 (9999999999999編集) | J31: S0250 | K31: インボイス金額合計（日本製） | M31: KINVTTLMJP | N31: 13 | O31: 文字(半角のみ)
A32: S0260 | G32: S0260 | H32: 非標準 インボイス金額合計（米国製）とは？ | I32: インボイス台帳ヘッド：同名項目×100 (9999999999999編集) | J32: S0260 | K32: インボイス金額合計（米国製） | M32: KINVTTLMUS | N32: 13 | O32: 文字(半角のみ)
A33: S0270 | B33: 出荷単位内容のテキスト | C33: VEKP | D33: INHALT | E33: 40 | F33: CHAR | G33: S0270 | H33: 紐つく梱包情報のカートン数(出荷単位内容のテキスト)の合計値 | I33: インボイス台帳ヘッド：同名項目 (999編集) | J33: S0270 | K33: カートン数 | M33: SCTN | N33: 3 | O33: 文字(半角のみ)
A34: S0280 | G34: S0280 | H34: 非標準 | I34: インボイス台帳ヘッド：同名項目 (999編集) | J34: S0280 | K34: パレット数 | M34: SPAL | N34: 3 | O34: 文字(半角のみ)
A35: S0290 | G35: S0290 | H35: 非標準 | I35: インボイス台帳ヘッド：同名項目 (99999編集) | J35: S0290 | K35: パレット内カートン数 | M35: SPALINSCTN | N35: 5 | O35: 文字(半角のみ)
A36: S0300 | G36: S0300 | H36: 非標準 | I36: インボイス台帳ヘッド：同名項目 (999編集) | J36: S0300 | K36: クレート数 | M36: SCRA | N36: 3 | O36: 文字(半角のみ)
A37: S0310 | G37: S0310 | H37: 非標準 S0220ケース数とは違う？ | I37: インボイス台帳ヘッド：同名項目 (999編集) | J37: S0310 | K37: ケース数（荷姿） | M37: SCASNSG | N37: 3 | O37: 文字(半角のみ)
A38: S0320 | G38: S0320 | H38: 非標準 | I38: インボイス台帳ヘッド：同名項目 (999編集) | J38: S0320 | K38: スチール数 | M38: SSTE | N38: 3 | O38: 文字(半角のみ)
A39: S0330 | G39: S0330 | H39: 非標準 | I39: インボイス台帳ヘッド：同名項目 (999編集) | J39: S0330 | K39: バンドル数 | M39: SBUN | N39: 3 | O39: 文字(半角のみ)
A40: S0340 | G40: S0340 | H40: 非標準 | I40: インボイス台帳ヘッド：同名項目 (999編集) | J40: S0340 | K40: エンベロップ数 | M40: SENV | N40: 3 | O40: 文字(半角のみ)
A41: S0350 | B41: インコタームズ: 印刷 | C41: VTTS | D41: INCO1 | E41: 3 | F41: CHAR | G41: S0350 | H41: 請求用建値 | I41: インボイス台帳ヘッド：同名項目 | J41: S0350 | K41: 請求用建値 | M41: SSEKTTE | N41: 3 | O41: 文字(半角のみ)
A42: S0360 | B42: 仕向地: 追加情報 (例: 荷渡ポイント) | C42: VTTS | D42: ABLAD | E42: 25 | F42: CHAR | G42: S0360 | H42: 揚げ地 | I42: インボイス台帳ヘッド：同名項目 | J42: S0360 | K42: 請求用揚げ地 | M42: NSEKAGE | N42: 17 | O42: 文字(半角のみ)
A43: S0370 | G43: S0370 | H43: 非標準 | I43: インボイス台帳ヘッド：｛インボイス金額合計（日本製)＋インボイス金額合計（米国製)｝×100 (9999999999999編集) | J43: S0370 | K43: 請求用インボイス金額 | M43: KSEKINV | N43: 13 | O43: 文字(半角のみ)
A44: S0380 | G44: S0380 | H44: 非標準 | I44: インボイス台帳ヘッド：インボイスNo上1桁＝'N'(無償インボイス)の場合、ブランク編集、以外は、(i2)輸送費負担区分 | J44: S0380 | K44: 輸送費負担区分 | M44: CYUHHYF | N44: 1 | O44: 文字(半角のみ)
A45: S0390 | G45: S0390 | H45: 非標準 | I45: インボイス台帳ヘッド：同名項目 | J45: S0390 | K45: 保険料負担区分 | M45: CKHOHYF | N45: 1 | O45: 文字(半角のみ)
A46: S0400 | G46: S0400 | H46: 非標準 | I46: インボイス台帳ヘッド：同名項目×100 (9999999999999編集) | J46: S0400 | K46: 通関用参考表示運送費（外貨） | M46: KTKSAHJYUHAB | N46: 13 | O46: 文字(半角のみ)
A47: S0410 | G47: S0410 | H47: 非標準 | I47: インボイス台帳ヘッド：同名項目×100 (9999999999999編集) | J47: S0410 | K47: 通関用参考表示保険料（外貨） | M47: KTKSAHJKHOAB | N47: 13 | O47: 文字(半角のみ)
A48: S0420 | G48: S0420 | H48: 非標準 | I48: インボイス台帳ヘッド：同名項目×100 (9999999999999編集) | J48: S0420 | K48: 請求用運送費（外貨） | M48: KSEKJUHAB | N48: 13 | O48: 文字(半角のみ)
A49: S0430 | G49: S0430 | H49: 非標準 | I49: インボイス台帳ヘッド：同名項目 (99999999999編集) | J49: S0430 | K49: 請求用運送費（円貨） | M49: KSEKJUHYE | N49: 11 | O49: 文字(半角のみ)
A50: S0440 | G50: S0440 | H50: 非標準 | I50: インボイス台帳ヘッド：同名項目×100 (9999999999999編集) | J50: S0440 | K50: 請求用保険料（外貨） | M50: KSEKKHOAB | N50: 13 | O50: 文字(半角のみ)
A51: S0450 | G51: S0450 | H51: 非標準 | I51: インボイス台帳ヘッド：同名項目 (99999999999編集) | J51: S0450 | K51: 請求用保険料（円貨） | M51: KSEKKHOYE | N51: 11 | O51: 文字(半角のみ)
A52: S0460 | G52: S0460 | H52: 非標準 | I52: インボイス台帳ヘッド：同名項目×100 (9999999999999編集) | J52: S0460 | K52: 請求用参考表示運送費（外貨） | M52: KSESAHJYUHAB | N52: 13 | O52: 文字(半角のみ)
A53: S0470 | G53: S0470 | H53: 非標準 | I53: インボイス台帳ヘッド：同名項目×100 (9999999999999編集) | J53: S0470 | K53: 請求用参考表示保険料（外貨） | M53: KSESAHJKHOAB | N53: 13 | O53: 文字(半角のみ)
A54: S0480 | G54: S0480 | H54: 非標準 | I54: インボイス台帳ヘッド：同名項目 (YYYYMMDD編集) | J54: S0480 | K54: 出港予定日付 | M54: DSYY | N54: 8 | O54: 文字(半角のみ)
... A56: S0500 | G56: S0500 | H56: 非標準 | I56: インボイス台帳ヘッド：同名項目 (YYYYMMDD編集) | J56: S0500 | K56: 到着予定日付２ | M56: DTOCYOT2 | N56: 8 | O56: 文字(半角のみ)
A57: S0510 | B57: 船積地点 | C57: VTTS | D57: KNOTA | E57: 10 | F57: CHAR | G57: S0510 | H57: FROM/VIA/TO(1)の港コード ※段階1はかならずFROM ※移送順序の段階(VTTS-TSRFO)との関連は要確認 | I57: インボイス台帳ヘッド：同名項目 | J57: S0510 | K57: 出港地 | M57: NSUT | N57: 10 | O57: 文字(半角のみ)
A58: S0520 | B58: 納入ポイント | C58: VTTS | D58: KNOTZ | E58: 10 | F58: CHAR | G58: S0520 | H58: VIA/TO(1)/TO(2)の港コード ※移送順序の段階(VTTS-TSRFO)との関連は要確認 | I58: インボイス台帳ヘッド：同名項目 | J58: S0520 | K58: 経由地 | M58: NKYT | N58: 40 | O58: 文字(半角のみ)
A59: S0530 | B59: 納入ポイント | C59: VTTS | D59: KNOTZ | E59: 10 | F59: CHAR | G59: S0530 | H59: VIA/TO(1)/TO(2)の港コード ※移送順序の段階(VTTS-TSRFO)との関連は要確認 | I59: インボイス台帳ヘッド：同名項目 | J59: S0530 | K59: 到着地１ | M59: NTCT1 | N59: 40 | O59: 文字(半角のみ)
A60: S0540 | B60: 納入ポイント | C60: VTTS | D60: KNOTZ | E60: 10 | F60: CHAR | G60: S0540 | H60: VIA/TO(1)/TO(2)の港コード ※移送順序の段階(VTTS-TSRFO)との関連は要確認 | I60: インボイス台帳ヘッド：同名項目 | J60: S0540 | K60: 到着地２ | M60: NTCT2 | N60: 40 | O60: 文字(半角のみ)
A61: S0550 | G61: S0550 | H61: 非標準 | I61: インボイス台帳ヘッド：同名項目 (YYYYMMDD編集) | J61: S0550 | K61: 船荷証券発行日付 | M61: DFUSHAK | N61: 8 | O61: 文字(半角のみ)
A62: S0560 | G62: S0560 | H62: 非標準 | I62: インボイス台帳ヘッド：同名項目 | J62: S0560 | K62: 航空貨物運送状（ハウス） | M62: BKUKUSJHOE | N62: 15 | O62: 文字(半角のみ)
A63: S0570 | G63: S0570 | H63: 非標準 | I63: インボイス台帳ヘッド：同名項目 | J63: S0570 | K63: 航空貨物運送状（マスター） | M63: BKUKUSJMAS | N63: 15 | O63: 文字(半角のみ)
A64: S0580 | B64: 外部 ID 1 | C64: VTTK | D64: EXTI1 | E64: 20 | F64: CHAR | G64: S0580 | H64: OCEAN B/L No. | I64: インボイス台帳ヘッド：同名項目 | J64: S0580 | K64: 船荷証券№ | M64: BFUS | N64: 20 | O64: 文字(半角のみ)
A65: S0590 | G65: S0590 | H65: 非標準 | I65: インボイス台帳ヘッド：同名項目 | J65: S0590 | K65: 便名 | M65: NBIN | N65: 20 | O65: 文字(半角のみ)
A66: S0600 | G66: S0600 | H66: 非標準 | I66: インボイス台帳ヘッド：同名項目 | J66: S0600 | K66: 船名 | M66: NSHP | N66: 30 | O66: 文字(半角のみ)
A67: S0610 | B67: 追加テキスト 1 | C67: VTTK | D67: TEXT1 | E67: 40 | F67: CHAR | G67: S0610 | H67: CONTAINER NO.(1) | I67: インボイス台帳ヘッド：同名項目 | J67: S0610 | K67: コンテナ№１ | M67: BCTN1 | N67: 15 | O67: 文字(半角のみ)
A68: S0620 | B68: 補足 1 | C68: VTTK | D68: ADD01 | E68: 10 | F68: CHAR | G68: S0620 | H68: SIZE(1) | I68: インボイス台帳ヘッド：同名項目 | J68: S0620 | K68: コンテナサイズ１ | M68: CCTNSIZ1 | N68: 1 | O68: 文字(半角のみ)
A69: S0630 | B69: 追加テキスト 2 | C69: VTTK | D69: TEXT2 | E69: 40 | F69: CHAR | G69: S0630 | H69: CONTAINER NO.(2) | I69: インボイス台帳ヘッド：同名項目 | J69: S0630 | K69: コンテナ№２ | M69: BCTN2 | N69: 15 | O69: 文字(半角のみ)
A70: S0640 | B70: 補足 2 | C70: VTTK | D70: ADD02 | E70: 10 | F70: CHAR | G70: S0640 | H70: SIZE(2) | I70: インボイス台帳ヘッド：同名項目 | J70: S0640 | K70: コンテナサイズ２ | M70: CCTNSIZ2 | N70: 1 | O70: 文字(半角のみ)
A71: S0650 | B71: 追加テキスト 3 | C71: VTTK | D71: TEXT3 | E71: 40 | F71: CHAR | G71: S0650 | H71: CONTAINER NO.(3) | I71: インボイス台帳ヘッド：同名項目 | J71: S0650 | K71: コンテナ№３ | M71: BCTN3 | N71: 15 | O71: 文字(半角のみ)
A72: S0660 | B72: 補足 3 | C72: VTTK | D72: ADD03 | E72: 10 | F72: CHAR | G72: S0660 | H72: SIZE(3) | I72: インボイス台帳ヘッド：同名項目 | J72: S0660 | K72: コンテナサイズ３ | M72: CCTNSIZ3 | N72: 1 | O72: 文字(半角のみ)
A73: S0670 | B73: 追加テキスト 4 | C73: VTTK | D73: TEXT4 | E73: 40 | F73: CHAR | G73: S0670 | H73: CONTAINER NO.(4) | I73: インボイス台帳ヘッド：同名項目 | J73: S0670 | K73: コンテナ№４ | M73: BCTN4 | N73: 15 | O73: 文字(半角のみ)
A74: S0680 | B74: 補足 4 | C74: VTTK | D74: ADD04 | E74: 10 | F74: CHAR | G74: S0680 | H74: SIZE(4) | I74: インボイス台帳ヘッド：同名項目 | J74: S0680 | K74: コンテナサイズ４ | M74: CCTNSIZ4 | N74: 1 | O74: 文字(半角のみ)
A75: S0690 | G75: S0690 | H75: 非標準 | I75: インボイス台帳ヘッド：同名項目 | J75: S0690 | K75: 国際宅急便運送状№ | M75: BITBUSJ | N75: 20 | O75: 文字(半角のみ)
A76: S0700 | G76: S0700 | H76: 非標準 | I76: インボイス台帳ヘッド：同名項目 | J76: S0700 | K76: インボイスヘッド備考１ | M76: XINVHEDBKO1 | N76: 40 | O76: 文字(半角のみ)
A77: S0710 | G77: S0710 | H77: 非標準 | I77: インボイス台帳ヘッド：同名項目 | J77: S0710 | K77: インボイスヘッド備考２ | M77: XINVHEDBKO2 | N77: 40 | O77: 文字(半角のみ)
A78: S0720 | G78: S0720 | H78: 非標準 | I78: インボイス台帳ヘッド：同名項目 | J78: S0720 | K78: インボイスヘッド備考３ | M78: XINVHEDBKO3 | N78: 40 | O78: 文字(半角のみ)
A79: S0730 | G79: S0730 | H79: 非標準 | I79: インボイス台帳ヘッド：同名項目 | J79: S0730 | K79: インボイスヘッド備考４ | M79: XINVHEDBKO4 | N79: 40 | O79: 文字(半角のみ)
A80: S0740 | G80: S0740 | H80: 非標準 | I80: インボイス台帳ヘッド：同名項目 (YYYYMMDD編集) | J80: S0740 | K80: 船積完了日付 | M80: DFZMKRO | N80: 8 | O80: 文字(半角のみ)
A81: S0750 | G81: S0750 | H81: 非標準 | I81: インボイス台帳ヘッド：同名項目 (YYYYMMDD編集) | J81: S0750 | K81: 船積完了報告書作成指示日付 | M81: DFZMKROHOSSJI | N81: 8 | O81: 文字(半角のみ)
A82: S0760 | G82: S0760 | H82: 非標準 | I82: インボイス台帳ヘッド：同名項目 (YYYYMMDD編集) | J82: S0760 | K82: ＰＩＫＯ送信指示日付 | M82: DPIKSEDSZZ | N82: 8 | O82: 文字(半角のみ)
A83: S0770 | G83: S0770 | H83: 非標準 | I83: インボイス台帳ヘッド：同名項目 (YYYYMMDD編集) | J83: S0770 | K83: シッピングアドバイス送信指示日付 | M83: DSPASEDSZZ | N83: 8 | O83: 文字(半角のみ)
A84: S0780 | G84: S0780 | H84: 非標準 | I84: インボイス台帳ヘッド：同名項目 | J84: S0780 | K84: シッピングアドバイス備考１ | M84: XSPABKO1 | N84: 40 | O84: 文字(半角のみ)
A85: S0790 | G85: S0790 | H85: 非標準 | I85: インボイス台帳ヘッド：同名項目 | J85: S0790 | K85: シッピングアドバイス備考２ | M85: XSPABKO2 | N85: 40 | O85: 文字(半角のみ)
A86: S0800 | G86: S0800 | H86: 非標準 | I86: インボイス台帳ヘッド：同名項目 | J86: S0800 | K86: デビットノート№ | M86: BDBT | N86: 10 | O86: 文字(半角のみ)
A87: S0810 | B87: 計画終了日付 | C87: VTTK | D87: DTDIS | E87: 8 | F87: DATS | G87: S0810 | H87: INVOICE DATE | I87: インボイス台帳ヘッド：同名項目 (YYYYMMDD編集) | J87: S0810 | K87: 請求日付 | M87: DSEK | N87: 8 | O87: 文字(半角のみ)
A88: S0820 | G88: S0820 | H88: 非標準 | I88: インボイス台帳ヘッド：同名項目 (YYYYMMDD編集) | J88: S0820 | K88: 入金日付 | M88: DNYU | N88: 8 | O88: 文字(半角のみ)
A89: S0830 | B89: 出荷ポイント: 得意先 | C89: VTTS | D89: KUNNA | E89: 10 | F89: CHAR | G89: S0830 | H89: FROM/VIA/TO(1)の港コードに対するBPコード | I89: インボイス台帳ヘッド：同名項目 | J89: S0830 | K89: 船積用得意先コード | M89: BFZMTKU | N89: 6 | O89: 文字(半角のみ)
A90: S0840 | G90: S0840 | H90: S0150通貨単位の名称 ※SAPカスタマイズと同じか要確認 | I90: インボイス台帳ヘッド：同名項目 | J90: S0840 | K90: 通貨単位名称 | M90: NTUKTMI | N90: 3 | O90: 文字(半角のみ)
A91: S0850 | G91: S0850 | H91: どの国？受注先、出荷先、船積地、仕向地 | I91: インボイス台帳ヘッド：同名項目 | J91: S0850 | K91: 国コード | M91: BCOT | N91: 3 | O91: 文字(半角のみ)
A92: S0860 | G92: S0860 | H92: S0850国コードの名称 ※SAPカスタマイズと同じか要確認 | I92: インボイス台帳ヘッド：同名項目 | J92: S0860 | K92: 国名 | M92: NKNM | N92: 15 | O92: 文字(半角のみ)
A93: S0870 | G93: S0870 | H93: 非標準 | I93: インボイス台帳ヘッド：同名項目 | J93: S0870 | K93: 代表得意先コード | M93: BDAITKU | N93: 6 | O93: 文字(半角のみ)
A94: S0880 | G94: S0880 | H94: 非標準 | I94: インボイス台帳ヘッド：同名項目 (99999編集) | J94: S0880 | K94: カートン内カートン数 | M94: SCTNINSCTN | N94: 5 | O94: 文字(半角のみ)
A95: S0890 | G95: S0890 | H95: 非標準 | I95: インボイス台帳ヘッド：同名項目 (99999編集) | J95: S0890 | K95: クレート内カートン数 | M95: SCRAINSCTN | N95: 5 | O95: 文字(半角のみ)
A96: S0900 | G96: S0900 | H96: 非標準 | I96: インボイス台帳ヘッド：同名項目 (99999編集) | J96: S0900 | K96: ケース内カートン数 | M96: SCASINSCTN | N96: 5 | O96: 文字(半角のみ)
A97: S0910 | G97: S0910 | H97: 非標準 | I97: インボイス台帳ヘッド：同名項目 (99999編集) | J97: S0910 | K97: スチール内カートン数 | M97: SSTEINSCTN | N97: 5 | O97: 文字(半角のみ)
A98: S0920 | G98: S0920 | H98: 非標準 | I98: インボイス台帳ヘッド：同名項目 (99999編集) | J98: S0920 | K98: バンドル内カートン数 | M98: SBUNINSCTN | N98: 5 | O98: 文字(半角のみ)
A99: S0930 | G99: S0930 | H99: 非標準 | I99: インボイス台帳ヘッド：同名項目 (99999編集) | J99: S0930 | K99: エンベロップ内カートン数 | M99: SENVINSCTN | N99: 5 | O99: 文字(半角のみ)
A100: S0940 | G100: S0940 | H100: 非標準 | I100: インボイス台帳ヘッド：同名項目 | J100: S0940 | K100: 許可書NO1 | M100: BKYS1 | N100: 15 | O100: 文字(半角のみ)
A101: S0950 | G101: S0950 | H101: 非標準 | I101: インボイス台帳ヘッド：同名項目 | J101: S0950 | K101: 許可書NO2 | M101: BKYS2 | N101: 15 | O101: 文字(半角のみ)
... A121: S1150 | G121: S1150 | H121: 非標準 | I121: システム日付(YYYYMMDD編集)||システム時刻(HHMMSS編集) | J121: S1150 | K121: KWIN2送信指示日 | M121: DKWN2SND | N121: 14 | O121: 文字(半角のみ)

Sheet 対象IF一覧(IDOC→FTP)
A1: IFID | M1: インターフェース名称
A2: =IF(表紙!D16<>"",表紙!D16,"") -> IFZ9000018 | M2: =IF(表紙!D17<>"",表紙!D17,"") -> K-WINC2連携用インボイスデータファイル
A4: 1 | B4: 代表IF基本情報
B5: ① | C5: 連携元
C6: プロトコル | H6: ALE/IDOC
C7: メッセージタイプ | N7: 基本タイプ.拡張タイプ | X7: 備考・特記事項
B10: ② | C10: 連携先
C11: プロトコル | H11: FTP
C12: ファイルフォーマット | R12: レコード長 | X12: 備考・特記事項
C13: 可変長(タブ区切り) | R13: - | X13: [フォーマットに "XML" を選択する場合] XSD File： XXXXXXXXXXXXXXXXXXXXXXXXXX.xsd （または同等の情報が得られる資料へのリンクを明記）
A15: 2 | B15: 代表IF単位での共通処理
B16: ① | C16: 実行タイミング
C17: 実行場所 | J17: 処理名 | Q17: 起動契機 | X17: 連携区分 | AE17: 再処理単位 | AL17: 備考・特記事項
C18: 連携元(部品SAP) | J18: IDOC生成 | Q18: 時間指定 | X18: 差分 | AE18: トランザクション
C19: 連携元(部品SAP) | J19: IDOC送信 | Q19: ジョブ連携 | X19: 全件 | AE19: トランザクション
C20: データ連携基盤 | J20: ETL(抽出) | Q20: 随時 | X20: 全件 | AE20: トランザクション
C21: データ連携基盤 | J21: ETL(変換) | Q21: ファイル検知 | X21: 全件 | AE21: ALL
C22: データ連携基盤 | J22: ETL(投入) | Q22: ジョブ連携 | X22: 全件 | AE22: ALL
C23: 連携先 | J23: ファイル読込 | Q23: 任意 | X23: 全件 | AE23: ALL
B26: ② | C26: ファイル操作
C27: パターン：IDOC→FTP
C28: ファイル種別 | L28: 説明 | AE28: 有無 | AG28: 複数世代 | AI28: 入出力 | AQ28: バックアップ | BC28: 削除 | BK28: リネーム：世代番号付与 | BS28: リネーム：FTP送達保証
AI29: 出力 | AM29: 入力 | AQ29: 事前(前回分) | AU29: 成功時 | AY29: 失敗時 | BC29: 成功時 | BG29: 失敗時 | BK29: 成功時 | BO29: 失敗時 | BS29: 成功時 | BW29: 失敗時
C30: 変換前ファイル | L30: 共通処理の出力、変換処理の入力ファイル。IDOC形式。 | AE30: 有 | AG30: 有 | AI30: 共通処理 | AM30: ETL(変換) | AQ30: - | AU30: ETL(変換) | AY30: - | BC30: ETL(変換) | BG30: - | BK30: 共通処理 | BO30: - | BS30: - | BW30: -
C31: 変換後ファイル | L31: 変換処理の出力、投入処理の入力ファイル。 | AE31: 有 | AG31: 有 | AI31: ETL(変換) | AM31: ETL(投入) | AQ31: - | AU31: ETL(投入) | AY31: - | BC31: ETL(投入) | BG31: - | BK31: ETL(変換) | BO31: - | BS31: - | BW31: -
C32: IFファイル(連携先) | L32: FTP連携で、データ連携基盤が連携先システムにPUTするファイル。 | AE32: 有 | AG32: 無 | AI32: ETL(投入) | AM32: 連携先 | AQ32: - | AU32: - | AY32: - | BC32: - | BG32: - | BK32: - | BO32: - | BS32: ETL(投入) | BW32: -
C33: ※ 標準と異なるファイル操作を指定したい場合のみ、AE～BZ列の内容を変更してください。標準のファイル操作については、インターフェース開発方針「4.2. 連携方式概要」を参照。
B35: ③ | C35: 順序制御
C36: ・ | D36: FIFO（受信した順番に連携する） | O36: ※FIFOではない個別の並び替え要件がある場合には、ソートのキーとなる項目および昇順/降順、複数ある場合には優先順序を明記すること。
B38: ④ | C38: トランザクション制御
C39: ・ | D39: 処理の開始時に対象となる全データを１つのトランザクションとして処理する。
A43: 3 | B43: 総IF毎の個別処理
B44: ① | C44: 連携元
C45: プロトコル | H45: ALE/IDOC
C46: No | E46: マージ版No | L46: 送信元情報 | T46: 送信先情報 | AA46: 抽出条件 | AL46: 備考・特記事項
C48: 1 | E48: 1111 | L48: ERP(S/4) | S48: ⇒ | T48: データ連携基盤 | AA48: なし
C49: 2 | E49: 2222 | L49: ERP(S/4) | S49: ⇒ | T49: データ連携基盤 | AA49: なし
C50: 3
C51: 4
C52: 5
B54: ② | C54: 連携先
C55: プロトコル | H55: FTP
C56: No | E56: マージ版No | L56: 送信元情報 | T56: 送信先情報 | AA56: 抽出条件 | AL56: ファイル名 | AV56: 保管先パス | BD56: 文字コード | BI56: 改行コード | BN56: 括り文字 | BW56: 空ファイル生成 | BZ56: ヘッダ | CC56: 備考・特記事項
C58: 1 | E58: 1111 | L58: XXXX工場 | S58: ⇒ | T58: データ連携基盤 | AA58: なし | AL58: xxx.dat | AV58: \\xxx\xxx | BD58: Shift-JIS | BI58: CR+LF | BN58: なし | BW58: 無 | BZ58: 無
C59: 2 | E59: 2222 | L59: XXXX工場 | S59: ⇒ | T59: データ連携基盤 | AA59: なし | AL59: xxx.dat | AV59: \\xxx\xxx | BD59: Shift-JIS | BI59: CR+LF | BN59: なし | BW59: 無 | BZ59: 無
C60: 3
C61: 4
C62: 5
A64: 4 | B64: システムフロー（任意記載）

Sheet 対象IF一覧(IDOC→SFTP)
A1: IFID | M1: インターフェース名称
A2: =IF(表紙!D16<>"",表紙!D16,"") -> IFZ9000018 | M2: =IF(表紙!D17<>"",表紙!D17,"") -> K-WINC2連携用インボイスデータファイル
A4: 1 | B4: 代表IF基本情報
B5: ① | C5: 連携元
C6: プロトコル | H6: ALE/IDOC
C7: メッセージタイプ | N7: 基本タイプ.拡張タイプ | X7: 備考・特記事項
B10: ② | C10: 連携先
C11: プロトコル | H11: SFTP
C12: ファイルフォーマット | R12: レコード長 | X12: 備考・特記事項
C13: 可変長(タブ区切り) | R13: -
A15: 2 | B15: 代表IF単位での共通処理
B16: ① | C16: 実行タイミング
C17: 実行場所 | J17: 処理名 | Q17: 起動契機 | X17: 連携区分 | AE17: 再処理単位 | AL17: 備考・特記事項
C18: 連携元(KIC) | J18: IDOC生成 | Q18: 時間指定 | X18: 差分 | AE18: トランザクション
C19: 連携元(KIC) | J19: IDOC送信 | Q19: ジョブ連携 | X19: 全件 | AE19: トランザクション
C20: データ連携基盤 | J20: ETL(抽出) | Q20: 随時 | X20: 全件 | AE20: トランザクション
C21: データ連携基盤 | J21: ETL(変換) | Q21: 時間指定 | X21: 全件 | AE21: ALL | AL21: ジョブネットは生販システムデータソースのリージョン単位で作成する。 ジョブネットは複数の変換処理を含む場合がある。
C22: データ連携基盤 | J22: ETL(投入) | Q22: ジョブ連携 | X22: 全件 | AE22: ALL | AL22: 生販システムデータソースのリージョン毎に１つだけ作成する。
C23: 連携先 | J23: ファイル読込 | Q23: 任意 | X23: 全件 | AE23: ALL
B26: ② | C26: ファイル操作
C27: パターン：IDOC→SFTP
C28: ファイル種別 | L28: 説明 | AE28: 有無 | AG28: 複数世代 | AI28: 入出力 | AQ28: バックアップ | BC28: 削除 | BK28: リネーム：世代番号付与 | BS28: リネーム：FTP送達保証
AI29: 出力 | AM29: 入力 | AQ29: 事前(前回分) | AU29: 成功時 | AY29: 失敗時 | BC29: 成功時 | BG29: 失敗時 | BK29: 成功時 | BO29: 失敗時 | BS29: 成功時 | BW29: 失敗時
C30: 変換前ファイル | L30: 共通処理の出力、変換処理の入力ファイル。IDOC形式。 | AE30: 有 | AG30: 有 | AI30: 共通処理 | AM30: ETL(変換) | AQ30: - | AU30: ETL(変換) | AY30: - | BC30: ETL(変換) | BG30: - | BK30: 共通処理 | BO30: - | BS30: - | BW30: -
C31: 変換後ファイル | L31: 変換処理の出力、投入処理の入力ファイル。 | AE31: 有 | AG31: 有 | AI31: ETL(変換) | AM31: ETL(投入) | AQ31: - | AU31: ETL(投入) | AY31: - | BC31: ETL(投入) | BG31: - | BK31: ETL(変換) | BO31: - | BS31: - | BW31: -
C32: IFファイル(連携先) | L32: データ連携基盤が連携先システムにPUTするファイル。 | AE32: 有 | AG32: 無 | AI32: ETL(投入) | AM32: 連携先 | AQ32: - | AU32: - | AY32: - | BC32: - | BG32: - | BK32: - | BO32: - | BS32: ETL(投入) | BW32: -
C33: ※ 標準と異なるファイル操作を指定したい場合のみ、AE～BZ列の内容を変更してください。標準のファイル操作については、インターフェース開発方針「4.2. 連携方式概要」を参照。
B35: ③ | C35: 順序制御
C36: ・ | D36: FIFO（受信した順番に連携する） | O36: ※FIFOではない個別の並び替え要件がある場合には、ソートのキーとなる項目および昇順/降順、複数ある場合には優先順序を明記すること。
B38: ④ | C38: トランザクション制御
C39: ・ | D39: 処理の開始時に対象となる全データを１つのトランザクションとして処理する。
A43: 3 | B43: 総IF毎の個別処理
B44: ① | C44: 連携元
C45: プロトコル | H45: ALE/IDOC
C46: No | E46: マージ版No | L46: 送信元情報 | T46: 送信先情報 | AA46: 抽出条件 | AL46: 備考・特記事項
C48: 1 | E48: 1111 | L48: ERP(S/4) | S48: ⇒ | T48: データ連携基盤 | AA48: なし
C49: 2
C50: 3
C51: 4
C52: 5
B54: ② | C54: 連携先
C55: プロトコル | H55: SFTP
C56: No | E56: マージ版No | L56: 送信元情報 | T56: 送信先情報 | AA56: 抽出条件 | AL56: ファイル名 | AV56: 生販システムリージョン | BD56: 文字コード | BI56: 改行コード | BN56: 括り文字 | BW56: 空ファイル生成 | BZ56: ヘッダ | CC56: 備考・特記事項
C58: 1 | E58: 1111 | L58: データ連携基盤 | S58: ⇒ | T58: 生販システム | AA58: なし | AL58: xxx.dat | BD58: Shift-JIS | BI58: CR+LF | BN58: なし | BW58: 無 | BZ58: 無
C59: 2
C60: 3
C61: 4
C62: 5
A64: 4 | B64: システムフロー（任意記載）

Sheet 対象IF一覧(FTP→IDOC)
A1: IFID | M1: インターフェース名称
A2: =IF(表紙!D16<>"",表紙!D16,"") -> IFZ9000018 | M2: =IF(表紙!D17<>"",表紙!D17,"") -> K-WINC2連携用インボイスデータファイル
A4: 1 | B4: 代表IF基本情報
B5: ① | C5: 連携元
C6: プロトコル | H6: FTP
C7: ファイルフォーマット | R7: レコード長 | X7: 備考・特記事項
C8: 可変長(タブ区切り) | R8: - | X8: [フォーマットに "XML" を選択する場合] XSD File： XXXXXXXXXXXXXXXXXXXXXXXXXX.xsd （または同等の情報が得られる資料へのリンクを明記）
B10: ② | C10: 連携先
C11: プロトコル | H11: ALE/IDOC
C12: メッセージタイプ | N12: 基本タイプ.拡張タイプ | X12: 備考・特記事項
A15: 2 | B15: 代表IF単位での共通処理
B16: ① | C16: 実行タイミング
C17: 実行場所 | J17: 処理名 | Q17: 起動契機 | X17: 連携区分 | AE17: 再処理単位 | AL17: 備考・特記事項
C18: 連携元 | J18: ファイル送信 | Q18: 任意 | X18: 差分 | AE18: トランザクション
C19: データ連携基盤 | J19: ETL(抽出) | Q19: ファイル検知 | X19: 全件 | AE19: トランザクション
C20: データ連携基盤 | J20: ETL(変換) | Q20: ジョブ連携 | X20: 全件 | AE20: トランザクション
C21: データ連携基盤 | J21: ETL(投入) | Q21: ジョブ連携 | X21: 全件 | AE21: トランザクション
C22: 連携先(KIC) | J22: IDOC解析 | Q22: 時間指定 | X22: 全件 | AE22: トランザクション
C23: 連携先(KIC) | J23: データ格納 | Q23: 随時 | X23: 全件 | AE23: トランザクション
B26: ② | C26: ファイル操作
C27: パターン：FTP → IDOC
C28: ファイル種別 | L28: 説明 | AE28: 有無 | AG28: 複数世代 | AI28: 入出力 | AQ28: バックアップ | BC28: 削除 | BK28: リネーム：世代番号付与 | BS28: リネーム：FTP送達保証
AI29: 出力 | AM29: 入力 | AQ29: 事前(前回分) | AU29: 成功時 | AY29: 失敗時 | BC29: 成功時 | BG29: 失敗時 | BK29: 成功時 | BO29: 失敗時 | BS29: 成功時 | BW29: 失敗時
C30: IFファイル(連携元) | L30: FTP連携で、連携元システムがデータ連携基盤にPUTしたファイル。 | AE30: 有 | AG30: 無 | AI30: 連携元 | AM30: ETL(抽出) | AQ30: - | AU30: - | AY30: - | BC30: ETL(抽出) | BG30: - | BK30: - | BO30: - | BS30: - | BW30: -
C31: 変換前ファイル | L31: 抽出処理の出力、変換処理の入力ファイル。 | AE31: 有 | AG31: 有 | AI31: ETL(抽出) | AM31: ETL(変換) | AQ31: - | AU31: ETL(変換) | AY31: - | BC31: ETL(変換) | BG31: - | BK31: ETL(抽出) | BO31: - | BS31: - | BW31: -
C32: 変換後ファイル | L32: 変換処理の出力、投入処理の入力ファイル。IDOC形式。 | AE32: 有 | AG32: 有 | AI32: ETL(変換) | AM32: ETL(投入) | AQ32: - | AU32: ETL(投入) | AY32: - | BC32: ETL(投入) | BG32: - | BK32: ETL(変換) | BO32: - | BS32: - | BW32: -
C33: ※ 標準と異なるファイル操作を指定したい場合のみ、AE～BZ列の内容を変更してください。標準のファイル操作については、インターフェース開発方針「4.2. 連携方式概要」を参照。
B35: ③ | C35: 順序制御
C36: ・ | D36: FIFO（受信した順番に連携する） | O36: ※FIFOではない個別の並び替え要件がある場合には、ソートのキーとなる項目および昇順/降順、複数ある場合には優先順序を明記すること。
B38: ④ | C38: トランザクション制御
C39: ・ | D39: IDOCの文書番号は、インタフェース対象となるファイル１件につき１つのユニークな番号を割り当てて連携を行う。
D40: ※ ERP(S/4)側の取り込み処理でコミットを発行する単位で文書番号を分けること。
A43: 3 | B43: 総IF毎の個別処理
B44: ① | C44: 連携元
C45: プロトコル | H45: FTP
C46: No | E46: マージ版No | L46: 送信元情報 | T46: 送信先情報 | AA46: 抽出条件 | AL46: ファイル名 | AV46: 保管先パス | BD46: 文字コード | BI46: 改行コード | BN46: 括り文字 | BW46: 空ファイル生成 | BZ46: ヘッダ | CC46: 備考・特記事項
C48: 1 | E48: 1111 | L48: XXXX工場 | S48: ⇒ | T48: データ連携基盤 | AA48: なし | AL48: xxx.dat | AV48: \\xxx\xxx | BD48: Shift-JIS | BI48: CR+LF | BN48: なし | BW48: 無 | BZ48: 無
C49: 2 | E49: 2222 | L49: XXXX工場 | S49: ⇒ | T49: データ連携基盤 | AA49: なし | AL49: xxx.dat | AV49: \\xxx\xxx | BD49: Shift-JIS | BI49: CR+LF | BN49: なし | BW49: 無 | BZ49: 無
C50: 3
C51: 4
C52: 5
B54: ② | C54: 連携先
C55: プロトコル | H55: ALE/IDOC
C56: No | E56: マージ版No | L56: 送信元情報 | T56: 送信先情報 | AA56: 抽出条件 | AL56: 備考・特記事項
C58: 1 | E58: 1111 | L58: データ連携基盤 | S58: ⇒ | T58: ERP(S/4) | AA58: なし
C59: 2 | E59: 2222 | L59: データ連携基盤 | S59: ⇒ | T59: ERP(S/4) | AA59: なし
C60: 3
C61: 4
C62: 5
A64: 4 | B64: システムフロー（任意記載）

Sheet 対象IF一覧(SFTP→IDOC)
A1: IFID | M1: インターフェース名称
A2: =IF(表紙!D16<>"",表紙!D16,"") -> IFZ9000018 | M2: =IF(表紙!D17<>"",表紙!D17,"") -> K-WINC2連携用インボイスデータファイル
A4: 1 | B4: 代表IF基本情報
B5: ① | C5: 連携元
C6: プロトコル | H6: SFTP
C7: ファイルフォーマット | R7: レコード長 | X7: 備考・特記事項
C8: 可変長(タブ区切り) | R8: -
B10: ② | C10: 連携先
C11: プロトコル | H11: ALE/IDOC
C12: メッセージタイプ | N12: 基本タイプ.拡張タイプ | X12: 備考・特記事項
A15: 2 | B15: 代表IF単位での共通処理
B16: ① | C16: 実行タイミング
C17: 実行場所 | J17: 処理名 | Q17: 起動契機 | X17: 連携区分 | AE17: 再処理単位 | AL17: 備考・特記事項
C18: 連携元 | J18: ファイル送信 | Q18: 任意 | X18: 差分 | AE18: トランザクション
C19: データ連携基盤 | J19: ETL(抽出) | Q19: 時間指定 | X19: 全件 | AE19: トランザクション
C20: データ連携基盤 | J20: ETL(変換) | Q20: ジョブ連携 | X20: 全件 | AE20: トランザクション
C21: データ連携基盤 | J21: ETL(投入) | Q21: ジョブ連携 | X21: 全件 | AE21: トランザクション
C22: 連携先(KIC) | J22: IDOC解析 | Q22: 時間指定 | X22: 全件 | AE22: トランザクション
C23: 連携先(KIC) | J23: データ格納 | Q23: 随時 | X23: 全件 | AE23: トランザクション
B26: ② | C26: ファイル操作
C27: パターン：SFTP → IDOC
C28: ファイル種別 | L28: 説明 | AE28: 有無 | AG28: 複数世代 | AI28: 入出力 | AQ28: バックアップ | BC28: 削除 | BK28: リネーム：世代番号付与 | BS28: リネーム：FTP送達保証
AI29: 出力 | AM29: 入力 | AQ29: 事前(前回分) | AU29: 成功時 | AY29: 失敗時 | BC29: 成功時 | BG29: 失敗時 | BK29: 成功時 | BO29: 失敗時 | BS29: 成功時 | BW29: 失敗時
C30: IFファイル(連携元) | L30: データ連携基盤が連携元システムからGETするファイル。 | AE30: 有 | AG30: 無 | AI30: 連携元 | AM30: ETL(抽出) | AQ30: - | AU30: - | AY30: - | BC30: ETL(抽出) | BG30: - | BK30: - | BO30: - | BS30: - | BW30: -
C31: 変換前ファイル | L31: 抽出処理の出力、変換処理の入力ファイル。 | AE31: 有 | AG31: 有 | AI31: ETL(抽出) | AM31: ETL(変換) | AQ31: - | AU31: ETL(変換) | AY31: - | BC31: ETL(変換) | BG31: - | BK31: ETL(抽出) | BO31: - | BS31: - | BW31: -
C32: 変換後ファイル | L32: 変換処理の出力、投入処理の入力ファイル。IDOC形式。 | AE32: 有 | AG32: 有 | AI32: ETL(変換) | AM32: ETL(投入) | AQ32: - | AU32: ETL(投入) | AY32: - | BC32: ETL(投入) | BG32: - | BK32: ETL(変換) | BO32: - | BS32: - | BW32: -
C33: ※ 標準と異なるファイル操作を指定したい場合のみ、AE～BZ列の内容を変更してください。標準のファイル操作については、インターフェース開発方針「4.2. 連携方式概要」を参照。
B35: ③ | C35: 順序制御
C36: ・ | D36: FIFO（受信した順番に連携する） | O36: ※FIFOではない個別の並び替え要件がある場合には、ソートのキーとなる項目および昇順/降順、複数ある場合には優先順序を明記すること。
B38: ④ | C38: トランザクション制御
C39: ・ | D39: IDOCの文書番号は、インタフェース対象となるファイル１件につき１つのユニークな番号を割り当てて連携を行う。
D40: ※ ERP(S/4)側の取り込み処理でコミットを発行する単位で文書番号を分けること。
A43: 3 | B43: 総IF毎の個別処理
B44: ① | C44: 連携元
C45: プロトコル | H45: SFTP
C46: No | E46: マージ版No | L46: 送信元情報 | T46: 送信先情報 | AA46: 抽出条件 | AL46: ファイル名 | AV46: 保管先パス | BD46: 文字コード | BI46: 改行コード | BN46: 括り文字 | BW46: 空ファイル生成 | BZ46: ヘッダ | CC46: 備考・特記事項
C48: 1 | E48: 1111 | L48: 生販システム | S48: ⇒ | T48: データ連携基盤 | AA48: なし | AL48: xxx.dat | AV48: Outbound/ | BD48: UTF-8 | BI48: CR+LF | BN48: なし | BW48: 無 | BZ48: 無
C49: 2
B51: ② | C51: 連携先
C52: プロトコル | H52: ALE/IDOC
C53: No | E53: マージ版No | L53: 送信元情報 | T53: 送信先情報 | AA53: 抽出条件 | AL53: 備考・特記事項
C55: 1 | E55: 1111 | L55: データ連携基盤 | S55: ⇒ | T55: ERP(S/4) | AA55: なし
C56: 2
A58: 4 | B58: システムフロー（任意記載）

Sheet 対象IF一覧(MQ→FTP)
A1: IFID | M1: インターフェース名称
A2: =IF(表紙!D16<>"",表紙!D16,"") -> IFZ9000018 | M2: =IF(表紙!D17<>"",表紙!D17,"") -> K-WINC2連携用インボイスデータファイル
A4: 1 | B4: 代表IF基本情報
B5: ① | C5: 連携元
C6: プロトコル | H6: MSMQ
C7: メッセージフォーマット | R7: レコード長 | X7: 備考・特記事項
C8: XML | R8: ー | X8: [フォーマットに "XML" を選択する場合] XSD File： XXXXXXXXXXXXXXXXXXXXXXXXXX.xsd （または同等の情報が得られる資料へのリンクを明記）
B10: ② | C10: 連携先
C11: プロトコル | H11: FTP
C12: ファイルフォーマット | R12: レコード長 | X12: 備考・特記事項
C13: 可変長(タブ区切り) | R13: - | X13: [フォーマットに "XML" を選択する場合] XSD File： XXXXXXXXXXXXXXXXXXXXXXXXXX.xsd （または同等の情報が得られる資料へのリンクを明記）
A15: 2 | B15: 代表IF単位での共通処理
B16: ① | C16: 実行タイミング
C17: 実行場所 | J17: 処理名 | Q17: 起動契機 | X17: 連携区分 | AE17: 再処理単位 | AL17: 備考・特記事項
C18: 連携元 | J18: メッセージ送信 | Q18: 任意 | X18: 差分 | AE18: トランザクション
C19: データ連携基盤 | J19: ETL(抽出) | Q19: 随時 | X19: 全件 | AE19: トランザクション
C20: データ連携基盤 | J20: ETL(変換) | Q20: 時間指定 | X20: 全件 | AE20: ALL
C21: データ連携基盤 | J21: ETL(投入) | Q21: ジョブ連携 | X21: 全件 | AE21: ALL
C22: 連携先 | J22: ファイル読込 | Q22: 任意 | X22: 全件 | AE22: ALL
B26: ② | C26: ファイル操作
C27: パターン：MQ → FTP
C28: ファイル種別 | L28: 説明 | AE28: 有無 | AG28: 複数世代 | AI28: 入出力 | AQ28: バックアップ | BC28: 削除 | BK28: リネーム：世代番号付与 | BS28: リネーム：FTP送達保証
AI29: 出力 | AM29: 入力 | AQ29: 事前(前回分) | AU29: 成功時 | AY29: 失敗時 | BC29: 成功時 | BG29: 失敗時 | BK29: 成功時 | BO29: 失敗時 | BS29: 成功時 | BW29: 失敗時
C30: MQメッセージ(連携元) | L30: 連携元がデータ連携基盤向けのリモートキューにPUTしたメッセージ。 | AE30: 有 | AG30: 有 | AI30: 連携元 | AM30: ETL(抽出) | AQ30: - | AU30: - | AY30: - | BC30: ETL(抽出) | BG30: - | BK30: - | BO30: - | BS30: - | BW30: -
C31: 変換前ファイル | L31: 抽出処理の出力、変換処理の入力ファイル。 | AE31: 有 | AG31: 有 | AI31: ETL(抽出) | AM31: ETL(変換) | AQ31: - | AU31: ETL(変換) | AY31: - | BC31: ETL(変換) | BG31: - | BK31: ETL(抽出) | BO31: - | BS31: - | BW31: -
C32: 変換後ファイル | L32: 変換処理の出力、投入処理の入力ファイル。IDOC形式。 | AE32: 有 | AG32: 有 | AI32: ETL(変換) | AM32: ETL(投入) | AQ32: - | AU32: ETL(投入) | AY32: - | BC32: ETL(投入) | BG32: - | BK32: ETL(変換) | BO32: - | BS32: - | BW32: -
C33: ※ 標準と異なるファイル操作を指定したい場合のみ、AE～BZ列の内容を変更してください。標準のファイル操作については、インターフェース開発方針「4.2. 連携方式概要」を参照。
B35: ③ | C35: 順序制御
C36: ・ | D36: FIFO（受信した順番に連携する） | O36: ※FIFOではない個別の並び替え要件がある場合には、ソートのキーとなる項目および昇順/降順、複数ある場合には優先順序を明記すること。
B38: ④ | C38: トランザクション制御
C39: ・ | D39: 処理の開始時に対象となる全データを１つのトランザクション(ファイル)として処理する。
A43: 3 | B43: 総IF毎の個別処理
B44: ① | C44: 連携元
C45: プロトコル | H45: MSMQ
C46: No | E46: マージ版No | L46: 送信元情報 | T46: 送信先情報 | AA46: キュー名 | AG46: ラベル | AM46: 抽出条件 | AX46: 文字コード | BC46: トランザクション | BH46: ジャーナル | BM46: 記憶域の最大サイズ | BU46: 認証 | BW46: 0件時 送信 | BZ46: 備考・特記事項
BM47: メッセージ | BQ47: ジャーナル
C48: 1 | E48: 1000 | L48: Apriso MES(堺) | S48: ⇒ | T48: データ連携基盤 | AA48: KIC.MES.Queue.01 | AM48: なし | AX48: UTF-8 | BC48: 無効 | BH48: 無効 | BM48: 初期値 | BQ48: 初期値 | BU48: 無 | BW48: 無
C49: 2 | E49: 2000 | L49: Apriso MES(臨海) | S49: ⇒ | T49: データ連携基盤 | AA49: KIC.MES.Queue.02 | AM49: なし | AX49: UTF-8 | BC49: 無効 | BH49: 無効 | BM49: 初期値 | BQ49: 初期値 | BU49: 無 | BW49: 無
C50: 3 | E50: 3000 | L50: Apriso MES(筑波) | S50: ⇒ | T50: データ連携基盤 | AA50: KIC.MES.Queue.03 | AM50: なし | AX50: UTF-8 | BC50: 無効 | BH50: 無効 | BM50: 初期値 | BQ50: 初期値 | BU50: 無 | BW50: 無
C51: 4 | E51: 4000 | L51: Apriso MES(宇都宮) | S51: ⇒ | T51: データ連携基盤 | AA51: KIC.MES.Queue.04 | AM51: なし | AX51: UTF-8 | BC51: 無効 | BH51: 無効 | BM51: 初期値 | BQ51: 初期値 | BU51: 無 | BW51: 無
C52: 5 | E52: 5000 | L52: Apriso MES(枚方) | S52: ⇒ | T52: データ連携基盤 | AA52: KIC.MES.Queue.05 | AM52: なし | AX52: UTF-8 | BC52: 無効 | BH52: 無効 | BM52: 初期値 | BQ52: 初期値 | BU52: 無 | BW52: 無
C53: 6 | E53: 6000 | L53: Apriso MES(クボ精) | S53: ⇒ | T53: データ連携基盤 | AA53: KIC.MES.Queue.06 | AM53: なし | AX53: UTF-8 | BC53: 無効 | BH53: 無効 | BM53: 初期値 | BQ53: 初期値 | BU53: 無 | BW53: 無
B55: ② | C55: 連携先
C56: プロトコル | H56: FTP
C57: No | E57: マージ版No | L57: 送信元情報 | T57: 送信先情報 | AA57: 抽出条件 | AL57: ファイル名 | AV57: 保管先パス | BD57: 文字コード | BI57: 改行コード | BN57: 括り文字 | BW57: 空ファイル生成 | BZ57: ヘッダ | CC57: 備考・特記事項
C59: 1 | E59: 1000 | L59: データ連携基盤 | S59: ⇒ | T59: 堺工場 | AA59: プラントコード = 'xxxx' (堺) | AL59: xxx.dat | AV59: \\xxx\xxx | BD59: Shift-JIS | BI59: CR+LF | BN59: なし | BW59: 無 | BZ59: 無
C60: 2 | E60: 2000 | L60: データ連携基盤 | S60: ⇒ | T60: 臨海工場 | AA60: プラントコード = 'xxxx' (臨海) | AL60: xxx.dat | AV60: \\xxx\xxx | BD60: Shift-JIS | BI60: CR+LF | BN60: なし | BW60: 無 | BZ60: 無
C61: 3 | E61: 3000 | L61: データ連携基盤 | S61: ⇒ | T61: 筑波工場 | AA61: プラントコード = 'xxxx' (筑波) | AL61: xxx.dat | AV61: \\xxx\xxx | BD61: Shift-JIS | BI61: CR+LF | BN61: なし | BW61: 無 | BZ61: 無
C62: 4 | E62: 4000 | L62: データ連携基盤 | S62: ⇒ | T62: 宇都宮工場 | AA62: プラントコード = 'xxxx' (宇都宮) | AL62: xxx.dat | AV62: \\xxx\xxx | BD62: Shift-JIS | BI62: CR+LF | BN62: なし | BW62: 無 | BZ62: 無
C63: 5 | E63: 5000 | L63: データ連携基盤 | S63: ⇒ | T63: 枚方工場 | AA63: プラントコード = 'xxxx' (枚方) | AL63: xxx.dat | AV63: \\xxx\xxx | BD63: Shift-JIS | BI63: CR+LF | BN63: なし | BW63: 無 | BZ63: 無
C64: 6 | E64: 6000 | L64: データ連携基盤 | S64: ⇒ | T64: クボ精工場 | AA64: プラントコード = 'xxxx' (クボ精) | AL64: xxx.dat | AV64: \\xxx\xxx | BD64: Shift-JIS | BI64: CR+LF | BN64: なし | BW64: 無 | BZ64: 無
A66: 4 | B66: システムフロー（任意記載）
C68: Apriso MES(堺) | O68: データ連携基盤 | AG68: 堺工場
L69: 《MSMQ》 | AD69: 《FTP》
C72: Apriso MES(臨海) | AG72: 臨海工場
AD73: 《FTP》
C76: Apriso MES(XXX) | AG76: XXX工場
AD77: 《FTP》

Sheet 対象IF一覧(FTP→MQ)
A1: IFID | M1: インターフェース名称
A2: =IF(表紙!D16<>"",表紙!D16,"") -> IFZ9000018 | M2: =IF(表紙!D17<>"",表紙!D17,"") -> K-WINC2連携用インボイスデータファイル
A4: 1 | B4: 代表IF基本情報
B5: ① | C5: 連携元
C6: プロトコル | H6: FTP
C7: ファイルフォーマット | R7: レコード長 | X7: 備考・特記事項
C8: 可変長(タブ区切り) | R8: - | X8: [フォーマットに "XML" を選択する場合] XSD File： XXXXXXXXXXXXXXXXXXXXXXXXXX.xsd （または同等の情報が得られる資料へのリンクを明記）
B10: ② | C10: 連携先
C11: プロトコル | H11: MSMQ
C12: メッセージフォーマット | R12: レコード長 | X12: 備考・特記事項
C13: XML | R13: ー | X13: [フォーマットに "XML" を選択する場合] XSD File： XXXXXXXXXXXXXXXXXXXXXXXXXX.xsd （または同等の情報が得られる資料へのリンクを明記）
A15: 2 | B15: 代表IF単位での共通処理
B16: ① | C16: 実行タイミング
C17: 実行場所 | J17: 処理名 | Q17: 起動契機 | X17: 連携区分 | AE17: 再処理単位 | AL17: 備考・特記事項
C18: 連携元 | J18: ファイル送信 | Q18: 任意 | X18: 差分 | AE18: トランザクション
C19: データ連携基盤 | J19: ETL(抽出) | Q19: 時間指定 | X19: 全件 | AE19: トランザクション
C20: データ連携基盤 | J20: ETL(変換) | Q20: ジョブ連携 | X20: 全件 | AE20: トランザクション
C21: データ連携基盤 | J21: ETL(投入) | Q21: ジョブ連携 | X21: 全件 | AE21: トランザクション
C22: 連携先 | J22: メッセージ取得 | Q22: 任意 | X22: 全件 | AE22: トランザクション
B26: ② | C26: ファイル操作
C27: パターン：FTP → MQ
C28: ファイル種別 | L28: 説明 | AE28: 有無 | AG28: 複数世代 | AI28: 入出力 | AQ28: バックアップ | BC28: 削除 | BK28: リネーム：世代番号付与 | BS28: リネーム：FTP送達保証
AI29: 出力 | AM29: 入力 | AQ29: 事前(前回分) | AU29: 成功時 | AY29: 失敗時 | BC29: 成功時 | BG29: 失敗時 | BK29: 成功時 | BO29: 失敗時 | BS29: 成功時 | BW29: 失敗時
C30: 変換前ファイル | L30: 共通処理の出力、変換処理の入力ファイル。IDOC形式。 | AE30: 有 | AG30: 有 | AI30: 共通処理 | AM30: ETL(変換) | AQ30: - | AU30: ETL(変換) | AY30: - | BC30: ETL(変換) | BG30: - | BK30: 共通処理 | BO30: - | BS30: - | BW30: -
C31: 変換後ファイル | L31: 変換処理の出力、投入処理の入力ファイル。 | AE31: 有 | AG31: 有 | AI31: ETL(変換) | AM31: ETL(投入) | AQ31: - | AU31: ETL(投入) | AY31: - | BC31: ETL(投入) | BG31: - | BK31: ETL(変換) | BO31: - | BS31: - | BW31: -
C32: MQメッセージ(連携先) | L32: データ連携基盤が連携先向けのリモートキューにPUTしたメッセージ。 | AE32: 有 | AG32: 有 | AI32: ETL(投入) | AM32: 連携先 | AQ32: - | AU32: - | AY32: - | BC32: - | BG32: - | BK32: - | BO32: - | BS32: - | BW32: -
C33: ※ 標準と異なるファイル操作を指定したい場合のみ、AE～BZ列の内容を変更してください。標準のファイル操作については、インターフェース開発方針「4.2. 連携方式概要」を参照。
B35: ③ | C35: 順序制御
C36: ・ | D36: FIFO（受信した順番に連携する） | O36: ※FIFOではない個別の並び替え要件がある場合には、ソートのキーとなる項目および昇順/降順、複数ある場合には優先順序を明記すること。
B38: ④ | C38: トランザクション制御
C39: ・ | D39: 処理の開始時に対象となる全データを１つのトランザクションとして処理する。
A43: 3 | B43: 総IF毎の個別処理
B44: ① | C44: 連携元
C45: プロトコル | H45: FTP
C46: No | E46: マージ版No | L46: 送信元情報 | T46: 送信先情報 | AA46: 抽出条件 | AL46: ファイル名 | AV46: 保管先パス | BD46: 文字コード | BI46: 改行コード | BN46: 括り文字 | BW46: 空ファイル生成 | BZ46: ヘッダ | CC46: 備考・特記事項
C48: 1 | E48: 1000 | L48: 堺工場 | S48: ⇒ | T48: データ連携基盤 | AA48: なし | AL48: xxx.dat | AV48: \\xxx\xxx | BD48: Shift-JIS | BI48: CR+LF | BN48: なし | BW48: 無 | BZ48: 無
C49: 2 | E49: 2000 | L49: 臨海工場 | S49: ⇒ | T49: データ連携基盤 | AA49: なし | AL49: xxx.dat | AV49: \\xxx\xxx | BD49: Shift-JIS | BI49: CR+LF | BN49: なし | BW49: 無 | BZ49: 無
C50: 3 | E50: 3000 | L50: 筑波工場 | S50: ⇒ | T50: データ連携基盤 | AA50: なし | AL50: xxx.dat | AV50: \\xxx\xxx | BD50: Shift-JIS | BI50: CR+LF | BN50: なし | BW50: 無 | BZ50: 無
C51: 4 | E51: 4000 | L51: 宇都宮工場 | S51: ⇒ | T51: データ連携基盤 | AA51: なし | AL51: xxx.dat | AV51: \\xxx\xxx | BD51: Shift-JIS | BI51: CR+LF | BN51: なし | BW51: 無 | BZ51: 無
C52: 5 | E52: 5000 | L52: 枚方工場 | S52: ⇒ | T52: データ連携基盤 | AA52: なし | AL52: xxx.dat | AV52: \\xxx\xxx | BD52: Shift-JIS | BI52: CR+LF | BN52: なし | BW52: 無 | BZ52: 無
C53: 6 | E53: 6000 | L53: クボ精工場 | S53: ⇒ | T53: データ連携基盤 | AA53: なし | AL53: xxx.dat | AV53: \\xxx\xxx | BD53: Shift-JIS | BI53: CR+LF | BN53: なし | BW53: 無 | BZ53: 無
B55: ② | C55: 連携先
C56: プロトコル | H56: MSMQ
C57: No | E57: マージ版No | L57: 送信元情報 | T57: 送信先情報 | AA57: キュー名 | AG57: ラベル | AM57: 抽出条件 | AX57: 文字コード | BC57: トランザクション | BH57: ジャーナル | BM57: 記憶域の最大サイズ | BU57: 認証 | BW57: 0件時 送信 | BZ57: 備考・特記事項
BM58: メッセージ | BQ58: ジャーナル
C59: 1 | E59: 1000 | L59: データ連携基盤 | S59: ⇒ | T59: Apriso MES(堺) | AA59: KIC.PWC.Queue | AM59: なし | AX59: UTF-8 | BC59: 無効 | BH59: 無効 | BM59: 初期値 | BQ59: 初期値 | BU59: 無 | BW59: 無
C60: 2 | E60: 2000 | L60: データ連携基盤 | S60: ⇒ | T60: Apriso MES(臨海) | AA60: KIC.PWC.Queue | AM60: なし | AX60: UTF-8 | BC60: 無効 | BH60: 無効 | BM60: 初期値 | BQ60: 初期値 | BU60: 無 | BW60: 無
C61: 3 | E61: 3000 | L61: データ連携基盤 | S61: ⇒ | T61: Apriso MES(筑波) | AA61: KIC.PWC.Queue | AM61: なし | AX61: UTF-8 | BC61: 無効 | BH61: 無効 | BM61: 初期値 | BQ61: 初期値 | BU61: 無 | BW61: 無
C62: 4 | E62: 4000 | L62: データ連携基盤 | S62: ⇒ | T62: Apriso MES(宇都宮) | AA62: KIC.PWC.Queue | AM62: なし | AX62: UTF-8 | BC62: 無効 | BH62: 無効 | BM62: 初期値 | BQ62: 初期値 | BU62: 無 | BW62: 無
C63: 5 | E63: 5000 | L63: データ連携基盤 | S63: ⇒ | T63: Apriso MES(枚方) | AA63: KIC.PWC.Queue | AM63: なし | AX63: UTF-8 | BC63: 無効 | BH63: 無効 | BM63: 初期値 | BQ63: 初期値 | BU63: 無 | BW63: 無
C64: 6 | E64: 6000 | L64: データ連携基盤 | S64: ⇒ | T64: Apriso MES(クボ精) | AA64: KIC.PWC.Queue | AM64: なし | AX64: UTF-8 | BC64: 無効 | BH64: 無効 | BM64: 初期値 | BQ64: 初期値 | BU64: 無 | BW64: 無
A66: 4 | B66: システムフロー（任意記載）
C68: 堺工場 | Z68: データ連携基盤 | AE68: Apriso MES(堺)
L69: 《FTP》 | AB69: 《MSMQ》
C72: 臨海工場 | AE72: Apriso MES(臨海)
L73: 《FTP》 | AB73: 《MSMQ》
C76: XXX工場 | AE76: Apriso MES(XXX)
L77: 《FTP》 | AB77: 《MSMQ》

Sheet 対象IF一覧(SFTP→FTP)
A1: IFID | M1: インターフェース名称
A2: =IF(表紙!D16<>"",表紙!D16,"") -> IFZ9000018 | M2: =IF(表紙!D17<>"",表紙!D17,"") -> K-WINC2連携用インボイスデータファイル
A4: 1 | B4: 代表IF基本情報
B5: ① | C5: 連携元
C6: プロトコル | H6: SFTP
C7: ファイルフォーマット | R7: レコード長 | X7: 備考・特記事項
C8: 可変長(タブ区切り) | R8: -
B10: ② | C10: 連携先
C11: プロトコル | H11: FTP
C12: ファイルフォーマット | R12: レコード長 | X12: 備考・特記事項
C13: 可変長(タブ区切り) | R13: - | X13: [フォーマットに "XML" を選択する場合] XSD File： XXXXXXXXXXXXXXXXXXXXXXXXXX.xsd （または同等の情報が得られる資料へのリンクを明記）
A15: 2 | B15: 代表IF単位での共通処理
B16: ① | C16: 実行タイミング
C17: 実行場所 | J17: 処理名 | Q17: 起動契機 | X17: 連携区分 | AE17: 再処理単位 | AL17: 備考・特記事項
C18: 連携元 | J18: ファイル送信 | Q18: 任意 | X18: 差分 | AE18: トランザクション
C19: データ連携基盤 | J19: ETL(抽出) | Q19: 時間指定 | X19: 全件 | AE19: トランザクション
C20: データ連携基盤 | J20: ETL(変換) | Q20: ジョブ連携 | X20: 全件 | AE20: ALL
C21: データ連携基盤 | J21: ETL(投入) | Q21: ジョブ連携 | X21: 全件 | AE21: ALL
C22: 連携先 | J22: ファイル読込 | Q22: 任意 | X22: 全件 | AE22: ALL
B26: ② | C26: ファイル操作
C27: パターン：SFTP → IDOC
C28: ファイル種別 | L28: 説明 | AE28: 有無 | AG28: 複数世代 | AI28: 入出力 | AQ28: バックアップ | BC28: 削除 | BK28: リネーム：世代番号付与 | BS28: リネーム：FTP送達保証
AI29: 出力 | AM29: 入力 | AQ29: 事前(前回分) | AU29: 成功時 | AY29: 失敗時 | BC29: 成功時 | BG29: 失敗時 | BK29: 成功時 | BO29: 失敗時 | BS29: 成功時 | BW29: 失敗時
C30: IFファイル(連携元) | L30: データ連携基盤が連携元システムからGETするファイル。 | AE30: 有 | AG30: 無 | AI30: 連携元 | AM30: ETL(抽出) | AQ30: - | AU30: - | AY30: - | BC30: ETL(抽出) | BG30: - | BK30: - | BO30: - | BS30: - | BW30: -
C31: 変換前ファイル | L31: 抽出処理の出力、変換処理の入力ファイル。 | AE31: 有 | AG31: 有 | AI31: ETL(抽出) | AM31: ETL(変換) | AQ31: - | AU31: ETL(変換) | AY31: - | BC31: ETL(変換) | BG31: - | BK31: ETL(抽出) | BO31: - | BS31: - | BW31: -
C32: 変換後ファイル | L32: 変換処理の出力、投入処理の入力ファイル。 | AE32: 有 | AG32: 有 | AI32: ETL(変換) | AM32: ETL(投入) | AQ32: - | AU32: ETL(投入) | AY32: - | BC32: ETL(投入) | BG32: - | BK32: ETL(変換) | BO32: - | BS32: - | BW32: -
C33: IFファイル(連携先) | L33: FTP連携で、データ連携基盤が連携先システムにPUTするファイル。 | AE33: 有 | AG33: 無 | AI33: ETL(投入) | AM33: 連携先 | AQ33: - | AU33: - | AY33: - | BC33: - | BG33: - | BK33: - | BO33: - | BS33: ETL(投入) | BW33: -
C34: ※ 標準と異なるファイル操作を指定したい場合のみ、AE～BZ列の内容を変更してください。標準のファイル操作については、インターフェース開発方針「4.2. 連携方式概要」を参照。
B36: ③ | C36: 順序制御
C37: ・ | D37: FIFO（受信した順番に連携する） | O37: ※FIFOではない個別の並び替え要件がある場合には、ソートのキーとなる項目および昇順/降順、複数ある場合には優先順序を明記すること。
B39: ④ | C39: トランザクション制御
C40: ・ | D40: 処理の開始時に対象となる全データを１つのトランザクションとして処理する。
A44: 3 | B44: 総IF毎の個別処理
B45: ① | C45: 連携元
C46: プロトコル | H46: SFTP
C47: No | E47: マージ版No | L47: 送信元情報 | T47: 送信先情報 | AA47: 抽出条件 | AL47: ファイル名 | AV47: 保管先パス | BD47: 文字コード | BI47: 改行コード | BN47: 括り文字 | BW47: 空ファイル生成 | BZ47: ヘッダ | CC47: 備考・特記事項
C49: 1 | E49: 9999 | L49: 生販システム | S49: ⇒ | T49: データ連携基盤 | AA49: なし | AL49: xxx.dat | AV49: Outbound/ | BD49: UTF-8 | BI49: CR+LF | BN49: なし | BW49: 無 | BZ49: 無
C50: 2
C51: 3
C52: 4
C53: 5
B55: ② | C55: 連携先
C56: プロトコル | H56: FTP
C57: No | E57: マージ版No | L57: 送信元情報 | T57: 送信先情報 | AA57: 抽出条件 | AL57: ファイル名 | AV57: 保管先パス | BD57: 文字コード | BI57: 改行コード | BN57: 括り文字 | BW57: 空ファイル生成 | BZ57: ヘッダ | CC57: 備考・特記事項
C59: 1 | E59: 9999 | L59: データ連携基盤 | S59: ⇒ | T59: XXXX工場 | AA59: なし | AL59: xxx.dat | AV59: \\xxx\xxx | BD59: Shift-JIS | BI59: CR+LF | BN59: なし | BW59: 無 | BZ59: 無
C60: 2
C61: 3
C62: 4
C63: 5
A65: 4 | B65: システムフロー（任意記載）

Sheet 対象IF一覧(FTP→SFTP)
A1: IFID | M1: インターフェース名称
A2: =IF(表紙!D16<>"",表紙!D16,"") -> IFZ9000018 | M2: =IF(表紙!D17<>"",表紙!D17,"") -> K-WINC2連携用インボイスデータファイル
A4: 1 | B4: 代表IF基本情報
B5: ① | C5: 連携元
C6: プロトコル | H6: FTP
C7: ファイルフォーマット | R7: レコード長 | X7: 備考・特記事項
C8: 可変長(タブ区切り) | R8: - | X8: [フォーマットに "XML" を選択する場合] XSD File： XXXXXXXXXXXXXXXXXXXXXXXXXX.xsd （または同等の情報が得られる資料へのリンクを明記）
B10: ② | C10: 連携先
C11: プロトコル | H11: SFTP
C12: ファイルフォーマット | R12: レコード長 | X12: 備考・特記事項
C13: 可変長(タブ区切り) | R13: -
A15: 2 | B15: 代表IF単位での共通処理
B16: ① | C16: 実行タイミング
C17: 実行場所 | J17: 処理名 | Q17: 起動契機 | X17: 連携区分 | AE17: 再処理単位 | AL17: 備考・特記事項
C18: 連携元 | J18: ファイル送信 | Q18: 任意 | X18: 差分 | AE18: トランザクション
C19: データ連携基盤 | J19: ETL(抽出) | Q19: 時間指定 | X19: 全件 | AE19: トランザクション | AL19: 対象ファイルの到着を待つ。
C20: データ連携基盤 | J20: ETL(変換) | Q20: ジョブ連携 | X20: 全件 | AE20: ALL | AL20: ジョブネットは生販システムデータソースのリージョン単位で作成する。 ジョブネットは複数の変換処理を含む場合がある。
C21: データ連携基盤 | J21: ETL(投入) | Q21: ジョブ連携 | X21: 全件 | AE21: ALL | AL21: 生販システムデータソースのリージョン毎に１つだけ作成する。
C22: 連携先 | J22: ファイル読込 | Q22: 任意 | X22: 全件 | AE22: ALL
B26: ② | C26: ファイル操作
C27: パターン：FTP → SFTP
C28: ファイル種別 | L28: 説明 | AE28: 有無 | AG28: 複数世代 | AI28: 入出力 | AQ28: バックアップ | BC28: 削除 | BK28: リネーム：世代番号付与 | BS28: リネーム：FTP送達保証
AI29: 出力 | AM29: 入力 | AQ29: 事前(前回分) | AU29: 成功時 | AY29: 失敗時 | BC29: 成功時 | BG29: 失敗時 | BK29: 成功時 | BO29: 失敗時 | BS29: 成功時 | BW29: 失敗時
C30: IFファイル(連携元) | L30: FTP連携で、連携元システムがデータ連携基盤にPUTしたファイル。 | AE30: 有 | AG30: 無 | AI30: 連携元 | AM30: ETL(抽出) | AQ30: - | AU30: - | AY30: - | BC30: ETL(抽出) | BG30: - | BK30: - | BO30: - | BS30: - | BW30: -
C31: 変換前ファイル | L31: 抽出処理の出力、変換処理の入力ファイル。 | AE31: 有 | AG31: 有 | AI31: ETL(抽出) | AM31: ETL(変換) | AQ31: - | AU31: ETL(変換) | AY31: - | BC31: ETL(変換) | BG31: - | BK31: ETL(抽出) | BO31: - | BS31: - | BW31: -
C32: 変換後ファイル | L32: 変換処理の出力、投入処理の入力ファイル。 | AE32: 有 | AG32: 有 | AI32: ETL(変換) | AM32: ETL(投入) | AQ32: - | AU32: ETL(投入) | AY32: - | BC32: ETL(投入) | BG32: - | BK32: ETL(変換) | BO32: - | BS32: - | BW32: -
C33: IFファイル(連携先) | L33: データ連携基盤が連携先システムにPUTするファイル。 | AE33: 有 | AG33: 無 | AI33: ETL(投入) | AM33: 連携先 | AQ33: - | AU33: - | AY33: - | BC33: - | BG33: - | BK33: - | BO33: - | BS33: ETL(投入) | BW33: -
C34: ※ 標準と異なるファイル操作を指定したい場合のみ、AE～BZ列の内容を変更してください。標準のファイル操作については、インターフェース開発方針「4.2. 連携方式概要」を参照。
B36: ③ | C36: 順序制御
C37: ・ | D37: FIFO（受信した順番に連携する） | O37: ※FIFOではない個別の並び替え要件がある場合には、ソートのキーとなる項目および昇順/降順、複数ある場合には優先順序を明記すること。
B39: ④ | C39: トランザクション制御
C40: ・ | D40: 処理の開始時に対象となる全データを１つのトランザクションとして処理する。
A44: 3 | B44: 総IF毎の個別処理
B45: ① | C45: 連携元
C46: プロトコル | H46: FTP
C47: No | E47: マージ版No | L47: 送信元情報 | T47: 送信先情報 | AA47: 抽出条件 | AL47: ファイル名 | AV47: 保管先パス | BD47: 文字コード | BI47: 改行コード | BN47: 括り文字 | BW47: 空ファイル生成 | BZ47: ヘッダ | CC47: 備考・特記事項
C49: 1 | E49: 1111 | L49: XXXX工場 | S49: ⇒ | T49: データ連携基盤 | AA49: なし | AL49: xxx.dat | AV49: \\xxx\xxx | BD49: Shift-JIS | BI49: CR+LF | BN49: なし | BW49: 無 | BZ49: 無
C50: 2
C51: 3
C52: 4
C53: 5
B55: ② | C55: 連携先
C56: プロトコル | H56: SFTP
C57: No | E57: マージ版No | L57: 送信元情報 | T57: 送信先情報 | AA57: 抽出条件 | AL57: ファイル名 | AV57: 生販システムリージョン | BD57: 文字コード | BI57: 改行コード | BN57: 括り文字 | BW57: 空ファイル生成 | BZ57: ヘッダ | CC57: 備考・特記事項
C59: 1 | E59: 1111 | L59: データ連携基盤 | S59: ⇒ | T59: 生販システム | AA59: なし | AL59: xxx.dat | BD59: Shift-JIS | BI59: CR+LF | BN59: なし | BW59: 無 | BZ59: 無
C60: 2
C61: 3
C62: 4
C63: 5
A65: 4 | B65: システムフロー（任意記載）

Sheet 対象IF一覧(FTP→FTP)
A1: IFID | M1: インターフェース名称
A2: =IF(表紙!D16<>"",表紙!D16,"") -> IFZ9000018 | M2: =IF(表紙!D17<>"",表紙!D17,"") -> K-WINC2連携用インボイスデータファイル
A4: 1 | B4: 代表IF基本情報
B5: ① | C5: 連携元
C6: プロトコル | H6: FTP
C7: ファイルフォーマット | R7: レコード長 | X7: 備考・特記事項
C8: 可変長(タブ区切り) | R8: -
B10: ② | C10: 連携先
C11: プロトコル | H11: FTP
C12: ファイルフォーマット | R12: レコード長 | X12: 備考・特記事項
C13: 可変長(タブ区切り) | R13: -
A15: 2 | B15: 代表IF単位での共通処理
B16: ① | C16: 実行タイミング
C17: 実行場所 | J17: 処理名 | Q17: 起動契機 | X17: 連携区分 | AE17: 再処理単位 | AL17: 備考・特記事項
C18: 連携元 | J18: ファイル送信 | Q18: 任意 | X18: 差分 | AE18: トランザクション
C19: データ連携基盤 | J19: ETL(抽出) | Q19: 時間指定 | X19: 全件 | AE19: トランザクション
C20: データ連携基盤 | J20: ETL(変換) | Q20: ジョブ連携 | X20: 全件 | AE20: トランザクション
C21: データ連携基盤 | J21: ETL(投入) | Q21: ジョブ連携 | X21: 全件 | AE21: トランザクション
B24: ② | C24: ファイル操作
C25: パターン：FTP → FTP
C26: ファイル種別 | L26: 説明 | AE26: 有無 | AG26: 複数世代 | AI26: 入出力 | AQ26: バックアップ | BC26: 削除 | BK26: リネーム：世代番号付与 | BS26: リネーム：FTP送達保証
AI27: 出力 | AM27: 入力 | AQ27: 事前(前回分) | AU27: 成功時 | AY27: 失敗時 | BC27: 成功時 | BG27: 失敗時 | BK27: 成功時 | BO27: 失敗時 | BS27: 成功時 | BW27: 失敗時
C28: IFファイル(連携元) | L28: FTP連携で、連携元システムがデータ連携基盤にPUTしたファイル。 | AE28: 有 | AG28: 無 | AI28: 連携元 | AM28: ETL(抽出) | AQ28: - | AU28: - | AY28: - | BC28: ETL(抽出) | BG28: - | BK28: - | BO28: - | BS28: - | BW28: -
C29: 変換前ファイル | L29: 抽出処理の出力、変換処理の入力ファイル。 | AE29: 有 | AG29: 有 | AI29: ETL(抽出) | AM29: ETL(変換) | AQ29: - | AU29: ETL(変換) | AY29: - | BC29: ETL(変換) | BG29: - | BK29: ETL(抽出) | BO29: - | BS29: - | BW29: -
C30: 変換後ファイル | L30: 変換処理の出力、投入処理の入力ファイル。 | AE30: 有 | AG30: 有 | AI30: ETL(変換) | AM30: ETL(投入) | AQ30: - | AU30: ETL(投入) | AY30: - | BC30: ETL(投入) | BG30: - | BK30: ETL(変換) | BO30: - | BS30: - | BW30: -
C31: IFファイル(連携先) | L31: FTP連携で、データ連携基盤が連携先システムにPUTするファイル。 | AE31: 有 | AG31: 無 | AI31: ETL(投入) | AM31: 連携先 | AQ31: - | AU31: - | AY31: - | BC31: - | BG31: - | BK31: - | BO31: - | BS31: ETL(投入) | BW31: -
C32: ※ 標準と異なるファイル操作を指定したい場合のみ、AE～BZ列の内容を変更してください。標準のファイル操作については、インターフェース開発方針「4.2. 連携方式概要」を参照。
B34: ③ | C34: 順序制御
C35: ・ | D35: FIFO（受信した順番に連携する） | O35: ※FIFOではない個別の並び替え要件がある場合には、ソートのキーとなる項目および昇順/降順、複数ある場合には優先順序を明記すること。
B37: ④ | C37: トランザクション制御
C38: ・ | D38: 処理の開始時に対象となる全データを１つのトランザクションとして処理する。
A42: 3 | B42: 総IF毎の個別処理
B43: ① | C43: 連携元
C44: プロトコル | H44: FTP
C45: No | E45: マージ版No | L45: 送信元情報 | T45: 送信先情報 | AA45: 抽出条件 | AL45: ファイル名 | AV45: 保管先パス | BD45: 文字コード | BI45: 改行コード | BN45: 括り文字 | BW45: 空ファイル生成 | BZ45: ヘッダ | CC45: 備考・特記事項
C47: 1 | E47: 9999 | L47: 北米ERP(S/4) | S47: ⇒ | T47: データ連携基盤 | AA47: なし | AV47: $home/inrecv/ | BD47: UTF-8 | BI47: CR+LF | BN47: なし | BW47: 無 | BZ47: 無
C48: 2
C49: 3
C50: 4
C51: 5
B53: ② | C53: 連携先
C54: プロトコル | H54: FTP
C55: No | E55: マージ版No | L55: 送信元情報 | T55: 送信先情報 | AA55: 抽出条件 | AL55: ファイル名 | AV55: 保管先パス | BD55: 文字コード | BI55: 改行コード | BN55: 括り文字 | BW55: 空ファイル生成 | BZ55: ヘッダ | CC55: 備考・特記事項
C57: 1 | E57: 9999 | L57: データ連携基盤 | S57: ⇒ | T57: マスタメンテシステム | AA57: なし | AV57: \\xxx\xxx | BD57: UTF-8 | BI57: CR+LF | BN57: なし | BW57: 無 | BZ57: 無
C58: 2
C59: 3
C60: 4
C61: 5
A63: 4 | B63: システムフロー（任意記載）

Sheet 対象IF一覧(BAPI)
A1: IFID | M1: インターフェース名称
A2: =IF(表紙!D16<>"",表紙!D16,"") -> IFZ9000018 | M2: =IF(表紙!D17<>"",表紙!D17,"") -> K-WINC2連携用インボイスデータファイル
A4: 1 | B4: 代表IF基本情報
B5: ① | C5: 連携元
C6: クライアントプログラム名 | X6: 備考・特記事項
B9: ② | C9: 連携先
C10: プロトコル | H10: RFC/BAPI
C11: RFC/BAPI名 | R11: 操作内容 | X11: 備考・特記事項
C12: BAPI_USER_GET_DETAIL | R12: 取得
A14: 2 | B14: 代表IF単位での共通処理
B15: ① | C15: 実行タイミング
C16: 実行場所 | J16: 処理名 | Q16: 起動契機 | X16: 連携区分 | AE16: 再処理単位 | AL16: 備考・特記事項
C17: 連携元(KIC) | J17: BAPI呼出 | Q17: 随時 | AE17: トランザクション
C18: 連携先(KIC) | J18: RFC/BAPI実行 | Q18: 随時 | X18: 差分 | AE18: トランザクション
B21: ② | C21: ファイル操作
C22: ・ | D22: なし
B24: ③ | C24: 順序制御
C25: ・ | D25: なし
B27: ④ | C27: トランザクション制御
C28: ・ | D28: １件のリクエストを１つのトランザクションとして処理する。
A32: 3 | B32: 総IF毎の個別処理
C34: プロトコル | H34: RFC/BAPI
C35: No | E35: マージ版No | L35: 送信元情報 | T35: 送信先情報 | AA35: コミット発行 | AH35: コミット完了待機 | AO35: コミット間隔 | AV35: 備考・特記事項
C37: 1 | E37: 9901 | L37: 調達ポータル | S37: ⇔ | T37: ERP(S/4) | AA37: 無 | AH37: 有 | AO37: なし
C38: 2
C39: 3
C40: 4
C41: 5
A43: 4 | B43: システムフロー（任意記載）
B57: ※ | C57: 直接連携（BAPI呼出）のインタフェースパターンでは、シート [項目マッピング][PWC設計] は不要。
B58: ※ | C58: 連携元/連携先側の処理については、「1.代表IF基本情報」欄に記載のPGMに対する基本設計書を参照。それ以外に参照すべきドキュメントがある場合は、以下に記載。

Sheet 対象IF一覧(SOAP→BAPI)
A1: IFID | M1: インターフェース名称
A2: =IF(表紙!D16<>"",表紙!D16,"") -> IFZ9000018 | M2: =IF(表紙!D17<>"",表紙!D17,"") -> K-WINC2連携用インボイスデータファイル
A4: 1 | B4: 代表IF基本情報
B5: ① | C5: 連携元
C6: クライアントプログラム名 | X6: 備考・特記事項
B9: ② | C9: ETL
C10: プロトコル | H10: SOAP
C11: WEBサービス名 | R11: 認証による保護 | X11: 備考・特記事項
C12: 《IFID》_WEB_《マージ版No》 | R12: 無
B14: ③ | C14: 連携先
C15: プロトコル | H15: RFC/BAPI
C16: RFC/BAPI名 | R16: 操作内容 | X16: 備考・特記事項
C17: BAPI_USER_GET_DETAIL | R17: 取得
A19: 2 | B19: 代表IF単位での共通処理
B20: ① | C20: 実行タイミング
C21: 実行場所 | J21: 処理名 | Q21: 起動契機 | X21: 連携区分 | AE21: 再処理単位 | AL21: 備考・特記事項
C22: 連携元 | J22: SOAP呼出 | Q22: 随時 | X22: 差分 | AE22: トランザクション
C23: データ連携基盤 | J23: ETL(WEB) | Q23: 随時 | X23: 全件 | AE23: トランザクション
C24: 連携先(KIC) | J24: RFC/BAPI実行 | Q24: 随時 | X24: 全件 | AE24: トランザクション
B26: ② | C26: ファイル操作
C27: ・ | D27: なし
B29: ③ | C29: 順序制御
C30: ・ | D30: なし
B32: ④ | C32: トランザクション制御
C33: ・ | D33: １件のリクエストを１つのトランザクションとして処理する。
A37: 3 | B37: 総IF毎の個別処理
B38: ① | C38: 連携元
C39: プロトコル | H39: SOAP
C40: No | E40: マージ版No | L40: 送信元情報 | T40: 送信先情報 | AA40: タイムアウト (秒) | AH40: アイドル時間 (秒) | AO40: 備考・特記事項
C42: 1 | E42: 8029 | L42: 堺工場 | S42: ⇔ | T42: データ連携基盤 | AA42: 60 | AH42: 180
C43: 2 | E43: 8480 | L43: 枚方工場 | S43: ⇔ | T43: データ連携基盤 | AA43: 60 | AH43: 180
C44: 3
C45: 4
C46: 5
B48: ② | C48: 連携先
C49: プロトコル | H49: RFC/BAPI
C50: No | E50: マージ版No | L50: 送信元情報 | T50: 送信先情報 | AA50: コミット発行 | AH50: コミット完了待機 | AO50: コミット間隔 | AV50: 備考・特記事項
C52: 1 | E52: 8029 | L52: データ連携基盤 | S52: ⇔ | T52: ERP(S/4) | AA52: 無 | AH52: 有 | AO52: 1000
C53: 2 | E53: 8480 | L53: データ連携基盤 | S53: ⇔ | T53: ERP(S/4) | AA53: 無 | AH53: 有 | AO53: 1000
C54: 3
C55: 4
C56: 5
A59: 4 | B59: システムフロー（任意記載）
B60: ※ | C60: SOAP要求→BAPI呼出、BAPI応答→SOAP応答の対で、「項目マッピング(要求)」「項目マッピング(応答)」の２シートを作成すること。

Sheet 対象IF一覧(IDOC→SOAP)
A1: IFID | M1: インターフェース名称
A2: =IF(表紙!D16<>"",表紙!D16,"") -> IFZ9000018 | M2: =IF(表紙!D17<>"",表紙!D17,"") -> K-WINC2連携用インボイスデータファイル
A4: 1 | B4: 代表IF基本情報
B5: ① | C5: 連携元
C6: プロトコル | H6: ALE/IDOC
C7: メッセージタイプ | N7: 基本タイプ.拡張タイプ | X7: 備考・特記事項
X8: SOAP呼出で取得したい値はブランクの状態でインタフェースする。 ブランク項目にSOAP呼出で取得した値を詰めて、同じメッセージタイプ/基本タイプのIDOCをSAPへ送り返す。 汎用検索Webサービスが返却する E生販システムorCode / E生販システムorMessage を格納する項目もブランクの状態でインタフェースする。
B10: ② | C10: 連携先
C11: プロトコル | H11: SOAP
C12: WEBサービス名 | R12: 認証による保護 | X12: 備考・特記事項
C13: ws_General-PurposeSearch | R13: 有 | X13: WebサービスURL： https://xxxxxxxxxxxxxxxxxxxxxxxxxxxxxxxxxxxxxx ライセンス情報、VIEW名、データ検索条件、項目名をパラメータに、条件に合致する値を検索する。APIに引渡すパラメータの詳細についてはシート[PWC設計]を参照。
A16: 2 | B16: 代表IF単位での共通処理
B17: ① | C17: 実行タイミング
C18: 実行場所 | J18: 処理名 | Q18: 起動契機 | X18: 連携区分 | AE18: 再処理単位 | AL18: 備考・特記事項
C19: 連携元(KIC) | J19: IDOC生成 | Q19: 時間指定 | X19: 差分 | AE19: トランザクション
C20: 連携元(KIC) | J20: IDOC送信 | Q20: ジョブ連携 | X20: 全件 | AE20: トランザクション
C21: データ連携基盤 | J21: ETL(抽出) | Q21: 随時 | X21: 全件 | AE21: トランザクション
C22: データ連携基盤 | J22: ETL(変換) | Q22: ファイル検知 | X22: 全件 | AE22: ALL | AL22: 汎用検索WebサービスのSOAP呼出を実行。
C23: データ連携基盤 | J23: ETL(投入) | Q23: ジョブ連携 | X23: 全件 | AE23: ALL
C24: 連携先(KIC) | J24: IDOC解析 | Q24: 時間指定 | X24: 全件 | AE24: トランザクション
C25: 連携先(KIC) | J25: データ格納 | Q25: 随時 | X25: 全件 | AE25: トランザクション
B28: ② | C28: ファイル操作
C29: パターン：IDOC ⇔ SOAP
C30: ファイル種別 | L30: 説明 | AE30: 有無 | AG30: 複数世代 | AI30: 入出力 | AQ30: バックアップ | BC30: 削除 | BK30: リネーム：世代番号付与 | BS30: リネーム：FTP送達保証
AI31: 出力 | AM31: 入力 | AQ31: 事前(前回分) | AU31: 成功時 | AY31: 失敗時 | BC31: 成功時 | BG31: 失敗時 | BK31: 成功時 | BO31: 失敗時 | BS31: 成功時 | BW31: 失敗時
C32: 変換前ファイル | L32: 共通処理の出力、変換処理の入力ファイル。IDOC形式。 | AE32: 有 | AG32: 有 | AI32: 共通処理 | AM32: ETL(変換) | AQ32: - | AU32: ETL(変換) | AY32: - | BC32: ETL(変換) | BG32: - | BK32: 共通処理 | BO32: - | BS32: - | BW32: -
C33: 変換後ファイル | L33: 変換処理の出力、投入処理の入力ファイル。IDOC形式。 | AE33: 有 | AG33: 有 | AI33: ETL(変換) | AM33: ETL(投入) | AQ33: - | AU33: ETL(投入) | AY33: - | BC33: ETL(投入) | BG33: - | BK33: ETL(変換) | BO33: - | BS33: - | BW33: -
C34: ※ 標準と異なるファイル操作を指定したい場合のみ、AE～BZ列の内容を変更してください。標準のファイル操作については、インターフェース開発方針「4.2. 連携方式概要」を参照。
B36: ③ | C36: 順序制御
C37: ・ | D37: FIFO（受信した順番に連携する） | O37: ※FIFOではない個別の並び替え要件がある場合には、ソートのキーとなる項目および昇順/降順、複数ある場合には優先順序を明記すること。
B39: ④ | C39: トランザクション制御
C40: ・ | D40: 処理の開始時に対象となる全データを１つのトランザクションとして処理する。
A44: 3 | B44: 総IF毎の個別処理
B45: ① | C45: 連携元
C46: プロトコル | H46: ALE/IDOC
C47: No | E47: マージ版No | L47: 送信元情報 | T47: 送信先情報 | AA47: 抽出条件 | AL47: 備考・特記事項
C49: 1 | E49: 9999 | L49: ERP(S/4) | S49: ⇔ | T49: データ連携基盤 | AA49: なし
C50: 2
C51: 3
B53: ② | C53: 連携先
C54: プロトコル | H54: SOAP
C55: No | E55: マージ版No | L55: クライアント | T55: サーバ | AA55: 抽出条件 | AL55: 備考・特記事項
C57: 1 | E57: 9999 | L57: データ連携基盤 | S57: ⇔ | T57: 汎用検索WEB | AA57: VIEW名 = 'XXXXXXXXXXX' | AL57: 汎用検索WEBサービスは「新会計(MLCW)」システムを参照する。
C58: 2
C59: 3
A62: 4 | B62: システムフロー（任意記載）
B63: ※ | C63: 送信IDOC→SOAP要求、SOAP応答→受信IDOCの対で、「項目マッピング(要求)」「項目マッピング(応答)」の２シートを作成すること。(認証部分は [PWC設計] シートに記載)
B64: ※ | C64: SOAP呼出/応答のリクエストやパラメータについて、項目マッピングシートに表現しにくい場合はPWC設計シートに詳細を記載し、項目マッピングシートには変換仕様欄に 「PWC設計シート参照」の旨を記載すること。
B65: ※ | C65: SOAPの呼出自体が失敗した場合は、データ連携基盤の「SOAP呼出(変換)」処理がエラーとなる。JP1ジョブの実行エラーとしてハンドリングする。
B66: ※ | C66: SOAPの呼出自体は成功で、E生販システムorCode / E生販システムorMessage が返却された場合、データ連携基盤の「SOAP呼出(変換)」処理はエラーにならない。業務エラーとしてSAP側で対処すること。

Sheet 対象IF一覧(IDOC→MQ)
A1: IFID | M1: インターフェース名称
A2: =IF(表紙!D16<>"",表紙!D16,"") -> IFZ9000018 | M2: =IF(表紙!D17<>"",表紙!D17,"") -> K-WINC2連携用インボイスデータファイル
A4: 1 | B4: 代表IF基本情報
B5: ① | C5: 連携元
C6: プロトコル | H6: ALE/IDOC
C7: メッセージタイプ | N7: 基本タイプ.拡張タイプ | X7: 備考・特記事項
B10: ② | C10: 連携先
C11: プロトコル | H11: IBMMQ
C12: メッセージフォーマット | R12: レコード長 | X12: 備考・特記事項
C13: 固定長 | R13: 10000
C15: プロトコル | H15: MSMQ
C16: メッセージフォーマット | R16: レコード長 | X16: 備考・特記事項
C17: XML | R17: ー | X17: [フォーマットに "XML" を選択する場合] XSD File： XXXXXXXXXXXXXXXXXXXXXXXXXX.xsd （または同等の情報が得られる資料へのリンクを明記）
A19: 2 | B19: 代表IF単位での共通処理
B20: ① | C20: 実行タイミング
C21: 実行場所 | J21: 処理名 | Q21: 起動契機 | X21: 連携区分 | AE21: 再処理単位 | AL21: 備考・特記事項
C22: 連携元(KIC) | J22: IDOC生成 | Q22: 時間指定 | X22: 差分 | AE22: トランザクション
C23: 連携元(KIC) | J23: IDOC送信 | Q23: ジョブ連携 | X23: 全件 | AE23: トランザクション
C24: データ連携基盤 | J24: ETL(抽出) | Q24: 随時 | X24: 全件 | AE24: トランザクション
C25: データ連携基盤 | J25: ETL(変換) | Q25: ファイル検知 | X25: 全件 | AE25: トランザクション
C26: データ連携基盤 | J26: ETL(投入) | Q26: ジョブ連携 | X26: 全件 | AE26: トランザクション
C27: 連携先 | J27: メッセージ取得 | Q27: 任意 | X27: 全件 | AE27: トランザクション
B30: ② | C30: ファイル操作
C31: パターン：IDOC → MQ
C32: ファイル種別 | L32: 説明 | AE32: 有無 | AG32: 複数世代 | AI32: 入出力 | AQ32: バックアップ | BC32: 削除 | BK32: リネーム：世代番号付与 | BS32: リネーム：FTP送達保証
AI33: 出力 | AM33: 入力 | AQ33: 事前(前回分) | AU33: 成功時 | AY33: 失敗時 | BC33: 成功時 | BG33: 失敗時 | BK33: 成功時 | BO33: 失敗時 | BS33: 成功時 | BW33: 失敗時
C34: 変換前ファイル | L34: 共通処理の出力、変換処理の入力ファイル。IDOC形式。 | AE34: 有 | AG34: 有 | AI34: 共通処理 | AM34: ETL(変換) | AQ34: - | AU34: ETL(変換) | AY34: - | BC34: ETL(変換) | BG34: - | BK34: 共通処理 | BO34: - | BS34: - | BW34: -
C35: 変換後ファイル | L35: 変換処理の出力、投入処理の入力ファイル。 | AE35: 有 | AG35: 有 | AI35: ETL(変換) | AM35: ETL(投入) | AQ35: - | AU35: ETL(投入) | AY35: - | BC35: ETL(投入) | BG35: - | BK35: ETL(変換) | BO35: - | BS35: - | BW35: -
C36: MQメッセージ(連携先) | L36: データ連携基盤が連携先向けのリモートキューにPUTしたメッセージ。 | AE36: 有 | AG36: 有 | AI36: ETL(投入) | AM36: 連携先 | AQ36: - | AU36: - | AY36: - | BC36: - | BG36: - | BK36: - | BO36: - | BS36: - | BW36: -
C37: ※ 標準と異なるファイル操作を指定したい場合のみ、AE～BZ列の内容を変更してください。標準のファイル操作については、インターフェース開発方針「4.2. 連携方式概要」を参照。
B39: ③ | C39: 順序制御
C40: ・ | D40: FIFO（受信した順番に連携する） | O40: ※FIFOではない個別の並び替え要件がある場合には、ソートのキーとなる項目および昇順/降順、複数ある場合には優先順序を明記すること。
B42: ④ | C42: トランザクション制御
C43: ・ | D43: 処理の開始時に対象となる全データを１つのトランザクションとして処理する。
A47: 3 | B47: 総IF毎の個別処理
B48: ① | C48: 連携元
C49: プロトコル | H49: ALE/IDOC
C50: No | E50: マージ版No | L50: 送信元情報 | T50: 送信先情報 | AA50: 抽出条件 | AL50: 備考・特記事項
C52: 1 | E52: 1000 | L52: ERP(S/4) | S52: ⇒ | T52: データ連携基盤 | AA52: なし | AL52: 堺工場向け
C53: 2 | E53: 2000 | L53: ERP(S/4) | S53: ⇒ | T53: データ連携基盤 | AA53: なし | AL53: 臨海工場向け
C54: 3 | E54: 3000 | L54: ERP(S/4) | S54: ⇒ | T54: データ連携基盤 | AA54: なし | AL54: 筑波工場向け
C55: 4 | E55: 4000 | L55: ERP(S/4) | S55: ⇒ | T55: データ連携基盤 | AA55: なし | AL55: 宇都宮工場向け
C56: 5 | E56: 5000 | L56: ERP(S/4) | S56: ⇒ | T56: データ連携基盤 | AA56: なし | AL56: 枚方工場向け
C57: 6 | E57: 6000 | L57: ERP(S/4) | S57: ⇒ | T57: データ連携基盤 | AA57: なし | AL57: クボ精工場向け
B59: ② | C59: 連携先
C60: プロトコル | H60: IBMMQ
C61: No | E61: マージ版No | L61: 送信元情報 | T61: 送信先情報 | AA61: キューマネージャ名 | AG61: キュー名 | AM61: 抽出条件 | AX61: 文字コード | BC61: 改行コード | BH61: 括り文字 | BQ61: ヘッダ | BT61: トレーラ | BW61: 0件時 送信 | BZ61: 備考・特記事項
C63: 1 | E63: XXXX | L63: データ連携基盤 | S63: ⇒ | T63: XXXX | AM63: なし | AX63: Shift-JIS | BC63: CR+LF | BH63: なし | BQ63: 無 | BT63: 無 | BW63: 無
C65: プロトコル | H65: MSMQ
C66: No | E66: マージ版No | L66: 送信元情報 | T66: 送信先情報 | AA66: キュー名 | AG66: ラベル | AM66: 抽出条件 | AX66: 文字コード | BC66: トランザクション | BH66: ジャーナル | BM66: 記憶域の最大サイズ | BU66: 認証 | BW66: 0件時 送信 | BZ66: 備考・特記事項
BM67: メッセージ | BQ67: ジャーナル
C68: 1 | E68: 1000 | L68: データ連携基盤 | S68: ⇒ | T68: Apriso MES(堺) | AA68: KIC.PWC.Queue | AM68: マージ版No | AX68: UTF-8 | BC68: 無効 | BH68: 無効 | BM68: 初期値 | BQ68: 初期値 | BU68: 無 | BW68: 無
C69: 2 | E69: 2000 | L69: データ連携基盤 | S69: ⇒ | T69: Apriso MES(臨海) | AA69: KIC.PWC.Queue | AM69: マージ版No | AX69: UTF-8 | BC69: 無効 | BH69: 無効 | BM69: 初期値 | BQ69: 初期値 | BU69: 無 | BW69: 無
C70: 3 | E70: 3000 | L70: データ連携基盤 | S70: ⇒ | T70: Apriso MES(筑波) | AA70: KIC.PWC.Queue | AM70: マージ版No | AX70: UTF-8 | BC70: 無効 | BH70: 無効 | BM70: 初期値 | BQ70: 初期値 | BU70: 無 | BW70: 無
C71: 4 | E71: 4000 | L71: データ連携基盤 | S71: ⇒ | T71: Apriso MES(宇都宮) | AA71: KIC.PWC.Queue | AM71: マージ版No | AX71: UTF-8 | BC71: 無効 | BH71: 無効 | BM71: 初期値 | BQ71: 初期値 | BU71: 無 | BW71: 無
C72: 5 | E72: 5000 | L72: データ連携基盤 | S72: ⇒ | T72: Apriso MES(枚方) | AA72: KIC.PWC.Queue | AM72: マージ版No | AX72: UTF-8 | BC72: 無効 | BH72: 無効 | BM72: 初期値 | BQ72: 初期値 | BU72: 無 | BW72: 無
C73: 6 | E73: 6000 | L73: データ連携基盤 | S73: ⇒ | T73: Apriso MES(クボ精) | AA73: KIC.PWC.Queue | AM73: マージ版No | AX73: UTF-8 | BC73: 無効 | BH73: 無効 | BM73: 初期値 | BQ73: 初期値 | BU73: 無 | BW73: 無
A75: 4 | B75: システムフロー（任意記載）
C77: ERP(S/4) | Z77: データ連携基盤 | AE77: Apriso MES(堺)
L78: 《ALE/IDOC》 | AB78: 《MSMQ》
AE81: Apriso MES(臨海)
AB82: 《MSMQ》
AE85: Apriso MES(XXX)
AB86: 《MSMQ》

Sheet 対象IF一覧(MQ→IDOC)
A1: IFID | M1: インターフェース名称
A2: =IF(表紙!D16<>"",表紙!D16,"") -> IFZ9000018 | M2: =IF(表紙!D17<>"",表紙!D17,"") -> K-WINC2連携用インボイスデータファイル
A4: 1 | B4: 代表IF基本情報
B5: ① | C5: 連携元
C6: プロトコル | H6: IBMMQ
C7: メッセージフォーマット | R7: レコード長 | X7: 備考・特記事項
C8: 固定長 | R8: 10000
C10: プロトコル | H10: MSMQ
C11: メッセージフォーマット | R11: レコード長 | X11: 備考・特記事項
C12: XML | R12: ー | X12: [フォーマットに "XML" を選択する場合] XSD File： XXXXXXXXXXXXXXXXXXXXXXXXXX.xsd （または同等の情報が得られる資料へのリンクを明記）
B14: ② | C14: 連携先
C15: プロトコル | H15: ALE/IDOC
C16: メッセージタイプ | N16: 基本タイプ.拡張タイプ | X16: 備考・特記事項
A19: 2 | B19: 代表IF単位での共通処理
B20: ① | C20: 実行タイミング
C21: 実行場所 | J21: 処理名 | Q21: 起動契機 | X21: 連携区分 | AE21: 再処理単位 | AL21: 備考・特記事項
C22: 連携元 | J22: メッセージ送信 | Q22: 任意 | X22: 差分 | AE22: トランザクション
C23: データ連携基盤 | J23: ETL(抽出) | Q23: 随時 | X23: 全件 | AE23: トランザクション
C24: データ連携基盤 | J24: ETL(変換) | Q24: ファイル検知 | X24: 全件 | AE24: トランザクション
C25: データ連携基盤 | J25: ETL(投入) | Q25: ジョブ連携 | X25: 全件 | AE25: トランザクション
C26: 連携先(KIC) | J26: IDOC解析 | Q26: 時間指定 | X26: 全件 | AE26: トランザクション
C27: 連携先(KIC) | J27: データ格納 | Q27: 随時 | X27: 全件 | AE27: トランザクション
B30: ② | C30: ファイル操作
C31: パターン：MQ → IDOC
C32: ファイル種別 | L32: 説明 | AE32: 有無 | AG32: 複数世代 | AI32: 入出力 | AQ32: バックアップ | BC32: 削除 | BK32: リネーム：世代番号付与 | BS32: リネーム：FTP送達保証
AI33: 出力 | AM33: 入力 | AQ33: 事前(前回分) | AU33: 成功時 | AY33: 失敗時 | BC33: 成功時 | BG33: 失敗時 | BK33: 成功時 | BO33: 失敗時 | BS33: 成功時 | BW33: 失敗時
C34: MQメッセージ(連携元) | L34: 連携元がデータ連携基盤向けのリモートキューにPUTしたメッセージ。 | AE34: 有 | AG34: 有 | AI34: 連携元 | AM34: ETL(抽出) | AQ34: - | AU34: - | AY34: - | BC34: ETL(抽出) | BG34: - | BK34: - | BO34: - | BS34: - | BW34: -
C35: 変換前ファイル | L35: 抽出処理の出力、変換処理の入力ファイル。 | AE35: 有 | AG35: 有 | AI35: ETL(抽出) | AM35: ETL(変換) | AQ35: - | AU35: ETL(変換) | AY35: - | BC35: ETL(変換) | BG35: - | BK35: ETL(抽出) | BO35: - | BS35: - | BW35: -
C36: 変換後ファイル | L36: 変換処理の出力、投入処理の入力ファイル。IDOC形式。 | AE36: 有 | AG36: 有 | AI36: ETL(変換) | AM36: ETL(投入) | AQ36: - | AU36: ETL(投入) | AY36: - | BC36: ETL(投入) | BG36: - | BK36: ETL(変換) | BO36: - | BS36: - | BW36: -
C37: ※ 標準と異なるファイル操作を指定したい場合のみ、AE～BZ列の内容を変更してください。標準のファイル操作については、インターフェース開発方針「4.2. 連携方式概要」を参照。
B39: ③ | C39: 順序制御
C40: ・ | D40: FIFO（受信した順番に連携する） | O40: ※FIFOではない個別の並び替え要件がある場合には、ソートのキーとなる項目および昇順/降順、複数ある場合には優先順序を明記すること。
B42: ④ | C42: トランザクション制御
C43: ・ | D43: IDOCの文書番号は、インタフェース対象となるメッセージ１件につき１つのユニークな番号を割り当てて連携を行う。
D44: ※ ERP(S/4)側の取り込み処理でコミットを発行する単位で文書番号を分けること。
A47: 3 | B47: 総IF毎の個別処理
B48: ① | C48: 連携元
C49: プロトコル | H49: MSMQ
C50: No | E50: マージ版No | L50: 送信元情報 | T50: 送信先情報 | AA50: キュー名 | AG50: ラベル | AM50: 抽出条件 | AX50: 文字コード | BC50: トランザクション | BH50: ジャーナル | BM50: 記憶域の最大サイズ | BU50: 認証 | BW50: 0件時 送信 | BZ50: 備考・特記事項
BM51: メッセージ | BQ51: ジャーナル
C52: 1 | E52: 1000 | L52: Apriso MES(堺) | S52: ⇒ | T52: データ連携基盤 | AA52: KIC.MES.Queue.01 | AM52: なし | AX52: UTF-8 | BC52: 無効 | BH52: 無効 | BM52: 初期値 | BQ52: 初期値 | BU52: 無 | BW52: 無
C53: 2 | E53: 2000 | L53: Apriso MES(臨海) | S53: ⇒ | T53: データ連携基盤 | AA53: KIC.MES.Queue.02 | AM53: なし | AX53: UTF-8 | BC53: 無効 | BH53: 無効 | BM53: 初期値 | BQ53: 初期値 | BU53: 無 | BW53: 無
C54: 3 | E54: 3000 | L54: Apriso MES(筑波) | S54: ⇒ | T54: データ連携基盤 | AA54: KIC.MES.Queue.03 | AM54: なし | AX54: UTF-8 | BC54: 無効 | BH54: 無効 | BM54: 初期値 | BQ54: 初期値 | BU54: 無 | BW54: 無
C55: 4 | E55: 4000 | L55: Apriso MES(宇都宮) | S55: ⇒ | T55: データ連携基盤 | AA55: KIC.MES.Queue.04 | AM55: なし | AX55: UTF-8 | BC55: 無効 | BH55: 無効 | BM55: 初期値 | BQ55: 初期値 | BU55: 無 | BW55: 無
C56: 5 | E56: 5000 | L56: Apriso MES(枚方) | S56: ⇒ | T56: データ連携基盤 | AA56: KIC.MES.Queue.05 | AM56: なし | AX56: UTF-8 | BC56: 無効 | BH56: 無効 | BM56: 初期値 | BQ56: 初期値 | BU56: 無 | BW56: 無
C57: 6 | E57: 6000 | L57: Apriso MES(クボ精) | S57: ⇒ | T57: データ連携基盤 | AA57: KIC.MES.Queue.06 | AM57: なし | AX57: UTF-8 | BC57: 無効 | BH57: 無効 | BM57: 初期値 | BQ57: 初期値 | BU57: 無 | BW57: 無
C59: プロトコル | H59: IBMMQ
C60: No | E60: マージ版No | L60: 送信元情報 | T60: 送信先情報 | AA60: キューマネージャ名 | AG60: キュー名 | AM60: 抽出条件 | AX60: 文字コード | BC60: 改行コード | BH60: 括り文字 | BQ60: ヘッダ | BT60: トレーラ | BW60: 0件時 送信 | BZ60: 備考・特記事項
C62: 1 | E62: XXXX | L62: XXXX | S62: ⇒ | T62: データ連携基盤 | AM62: なし | AX62: Shift-JIS | BC62: CR+LF | BH62: なし | BQ62: 無 | BT62: 無 | BW62: 無
B65: ② | C65: 連携先
C66: プロトコル | H66: ALE/IDOC
C67: No | E67: マージ版No | L67: 送信元情報 | T67: 送信先情報 | AA67: 抽出条件 | AL67: 備考・特記事項
C69: 1 | E69: 1000 | L69: データ連携基盤 | S69: ⇒ | T69: ERP(S/4) | AA69: なし
A72: 4 | B72: システムフロー（任意記載）
C74: Apriso MES(堺) | O74: データ連携基盤 | AG74: ERP(S/4)
L75: 《MSMQ》
C78: Apriso MES(臨海)
AC79: 《ALE/IDOC》
C82: Apriso MES(XXX)

Sheet 対象IF一覧(IDOC→ODBC)
A1: IFID | M1: インターフェース名称
A2: =IF(表紙!D16<>"",表紙!D16,"") -> IFZ9000018 | M2: =IF(表紙!D17<>"",表紙!D17,"") -> K-WINC2連携用インボイスデータファイル
A4: 1 | B4: 代表IF基本情報
B5: ① | C5: 連携元
C6: プロトコル | H6: ALE/IDOC
C7: メッセージタイプ | N7: 基本タイプ.拡張タイプ | X7: 備考・特記事項
B10: ② | C10: 連携先
C11: プロトコル | H11: ODBC
C12: テーブル名 | N12: IF用ワークTB | X12: 備考・特記事項
A16: 2 | B16: 代表IF単位での共通処理
B17: ① | C17: 実行タイミング
C18: 実行場所 | J18: 処理名 | Q18: 起動契機 | X18: 連携区分 | AE18: 再処理単位 | AL18: 備考・特記事項
C19: 連携元(KIC) | J19: IDOC生成 | Q19: 時間指定 | X19: 差分 | AE19: トランザクション
C20: 連携元(KIC) | J20: IDOC送信 | Q20: ジョブ連携 | X20: 全件 | AE20: トランザクション
C21: データ連携基盤 | J21: ETL(抽出) | Q21: 随時 | X21: 全件 | AE21: トランザクション
C22: データ連携基盤 | J22: ETL(変換) | Q22: ファイル検知 | X22: 全件 | AE22: トランザクション
C23: データ連携基盤 | J23: ETL(投入) | Q23: ジョブ連携 | X23: 差分 | AE23: トランザクション | AL23: IFワークTBのレコードを全件置換でインタフェースする。 完了後に、ワークTBとターゲットTBとマージして差分の反映を行う。
B26: ② | C26: ファイル操作
C27: パターン：IDOC → ODBC
C28: ファイル種別 | L28: 説明 | AE28: 有無 | AG28: 複数世代 | AI28: 入出力 | AQ28: バックアップ | BC28: 削除 | BK28: リネーム：世代番号付与 | BS28: リネーム：FTP送達保証
AI29: 出力 | AM29: 入力 | AQ29: 事前(前回分) | AU29: 成功時 | AY29: 失敗時 | BC29: 成功時 | BG29: 失敗時 | BK29: 成功時 | BO29: 失敗時 | BS29: 成功時 | BW29: 失敗時
C30: 変換前ファイル | L30: 共通処理の出力、変換処理の入力ファイル。IDOC形式。 | AE30: 有 | AG30: 有 | AI30: 共通処理 | AM30: ETL(変換) | AQ30: - | AU30: ETL(変換) | AY30: - | BC30: ETL(変換) | BG30: - | BK30: 共通処理 | BO30: - | BS30: - | BW30: -
C31: 変換後ファイル | L31: 変換処理の出力、投入処理の入力ファイル。 | AE31: 有 | AG31: 有 | AI31: ETL(変換) | AM31: ETL(投入) | AQ31: - | AU31: ETL(投入) | AY31: - | BC31: ETL(投入) | BG31: - | BK31: ETL(変換) | BO31: - | BS31: - | BW31: -
C32: ※ 標準と異なるファイル操作を指定したい場合のみ、AE～BZ列の内容を変更してください。標準のファイル操作については、インターフェース開発方針「4.2. 連携方式概要」を参照。
B34: ③ | C34: 順序制御
C35: ・ | D35: FIFO（受信した順番に連携する） | O35: ※FIFOではない個別の並び替え要件がある場合には、ソートのキーとなる項目および昇順/降順、複数ある場合には優先順序を明記すること。
B37: ④ | C37: トランザクション制御
C38: ・ | D38: 処理の開始時に対象となる着信済データ(未連携分)を１つのトランザクションとして一括で処理する。
A42: 3 | B42: 総IF毎の個別処理
B43: ① | C43: 連携元
C44: プロトコル | H44: ALE/IDOC
C45: No | E45: マージ版No | L45: 送信元情報 | T45: 送信先情報 | AA45: 抽出条件 | AL45: 備考・特記事項
C47: 1 | E47: XXXX | L47: ERP(S/4) | S47: ⇒ | T47: データ連携基盤 | AA47: なし
B50: ② | C50: 連携先
C51: プロトコル | H51: ODBC
C52: No | E52: マージ版No | L52: 送信元情報 | T52: 送信先情報 | AA52: 抽出条件 | AL52: DSN | AS52: データベース名 | AZ52: データベース別名 | BG52: スキーマ名 | BN52: 備考・特記事項
C54: 1 | E54: XXXX | L54: データ連携基盤 | S54: ⇒ | T54: 農機国内DWH | AA54: なし | AL54: 本番：APROS | BN54: 農機国内DWH経由で下記システムにデータを連携する。 ・K-SCM（生販計画） ・K-SCM（管理経理）
AL55: 統合：APROSPRE
AL56: 結合：APROSSE
AL57: 試験：DWHSE | AS57: EROUTE | AZ57: DWHSE | BG57: DWHSE
A59: 4 | B59: システムフロー
C60: ETL処理は、ERP(S/4)から着信したデータを農機国内DWHのIF用ワークTBに全件置換でLOADする。
C61: LOAD処理の成功後、メインターゲットとなるテーブルにマージする。（シート[IFレイアウト] のKey列でキーマッチを行い、UPDATEまたはINSERTを実行する）
C63: ERP(S/4) | O63: データ連携基盤 | AE63: 農機国内DWH | BG63: K-SCM（生販計画）
BD65: 《SQL:SELECT》
L68: 《ALE/IDOC》 | AB68: 《SQL:TRUNCATE-LOAD》
BG69: K-SCM（管理経理）
BD71: 《SQL:SELECT》
AB72: 《SQL:MERGE》

Sheet 対象IF一覧(DB連携)
A1: IFID | M1: インターフェース名称
A2: =IF(表紙!D16<>"",表紙!D16,"") -> IFZ9000018 | M2: =IF(表紙!D17<>"",表紙!D17,"") -> K-WINC2連携用インボイスデータファイル
A4: 1 | B4: DB連携の接続情報
C5: DBMS | K5: テーブルID | V5: テーブル名称 | AH5: 備考・特記事項
C6: Pure HANA | K6: ZG01IFT2xxx | V6: ○○テーブル | AH6: ＸＸＸＸＸＸＸＸＸＸＸＸＸＸＸＸ
A8: 2 | B8: 総IF毎の接続情報
C9: マージ版No | K9: 接続元システム名 | V9: 説明 | AH9: 備考・特記事項
C10: 9001 | K10: K-SCM（管理経理） | AH10: ＸＸＸＸＸＸＸＸＸＸＸＸＸＸＸＸ
C11: 9002 | K11: K-SCM（生販計画） | AH11: ＸＸＸＸＸＸＸＸＸＸＸＸＸＸＸＸ
C12: 9003 | K12: K-SCM（統合調達） | AH12: ＸＸＸＸＸＸＸＸＸＸＸＸＸＸＸＸ
A15: 3 | B15: システムフロー（任意記載）
B19: ※ | C19: DB連携のインタフェースパターンでは、シート [項目マッピング][PWC設計] は不要。
B20: ※ | C20: 接続先のDB情報については、「1.DB連携の接続情報」欄に記載のテーブルIDに対するテーブル定義書を参照。それ以外に参照すべきドキュメントがある場合は、以下に記載。

Sheet PwC設計
A1: IFID | C1: インターフェース名称
A2: =IF(表紙!D16<>"",表紙!D16,"") -> IFZ9000018 | C2: =IF(表紙!D17<>"",表紙!D17,"") -> K-WINC2連携用インボイスデータファイル
A3: 変換処理
A5: 処理No.01
A20: 処理No.02

Sheet FMT変更履歴
A1: フォーマット変更履歴 | F1: レビュー | I1: 承認
A2: No. | B2: 変更日 | C2: 変更者 | D2: 変更箇所 | E2: 変更内容 | F2: ABレビュー者 | G2: 開発管理レビュー者 | H2: KBT事務局レビュー者 | I2: KBT事務局承認 | J2: 承認日
A3: R1.00 | B3: 43819 | C3: 奥村 | D3: 全文書 | E3: 初版
A4: R1.10 | B4: 43845 | C4: 西山 | D4: 対象IF一覧 | E4: [3.総IF毎の個別処理] から [IF名称] [業務パターン] の列を削除。 → 理由：総IFで異なることは想定されない。
D5: 対象IF一覧 | E5: [3.総IF毎の個別処理] のプロトコル [ALE/IDOC] の列 [パートナ番号] を [抽出条件] ないし [抽出条件] に変更。 → 理由：パートナー番号を条件とするのは例外的なパターンとなる一方、抽出条件や抽出条件を明記する欄がなかったため。
D6: 対象IF一覧 | E6: [3.総IF毎の個別処理] の [②連携先] の列 [抽出条件] を [抽出条件] に変更。 → 理由：連携先にデータを渡す条件なので、[抽出]との表現は不適切。
D7: 対象IF一覧 | E7: [文字コード/改行コード/括り文字/0件時のフォーマット] の設定欄を [1.代表IF基本情報] から [3.総IF毎の個別処理] に移動。 → 理由：総IFで異なる可能性が指摘されたため。
D8: 対象IF一覧 | E8: 列 [0件時のフォーマット] を [ヘッダ][空ファイル生成] に分割。 → 理由：ヘッダの要否はデータの件数とは直接の関係がない。
D9: 対象IF一覧 | E9: [1.代表IF基本情報] の列 [基本タイプ/拡張タイプ/メッセージタイプ/拡張メッセージタイプ] を統合。 → 理由①：IDOCに [拡張メッセージタイプ] という概念はない。 → 理由②：原則をユーザIDOCに寄せる方針。拡張タイプを意識するのは例外となるため。
D10: 対象IF一覧 | E10: [起動契機] に関する情報を [1.代表IF基本情報] から [2.代表IF単位での共通処理] に移動。 → 理由：処理に関する情報で合って基本情報ではないし、フォーマットとは記載したい粒度が異なる情報であるため。
D11: 対象IF一覧 | E11: 列位置を微調整。
D12: 対象IF一覧 | E12: 連携方式の組み合わせでテンプレートシートを分離。 → 理由：MQ等のテンプレートを追加するにあたり情報量が増えたことで、何を残して何を削除するべきなのかがわかりにくくなると懸念されたため。
D13: 対象IF一覧(SOAP→BAPI) | E13: シート追加。
D14: 対象IF一覧(IDOC→MQ) | E14: シート追加。
D15: 対象IF一覧(MQ→IDOC) | E15: シート追加。
D16: 対象IF一覧(FTP→MQ) | E16: シート追加。
D17: 対象IF一覧(MQ→FTP) | E17: シート追加。
A18: R1.20 | B18: 43880 | C18: 西山 | D18: 対象IF一覧(*) | E18: 「④ トランザクション制御」の記入欄を追加。
A19: R1.30 | B19: 43881 | C19: 伊東 | D19: 項目マッピング | E19: 「Byte数」⇒「文字数」に変更。
A20: R1.40 | B20: 43922 | C20: 西山 | D20: 対象IF一覧(*MQ*) | E20: MSMQ用のレイアウトを追加。
A21: R1.50 | B21: 43944 | C21: 吉住 | D21: 対象IF一覧(DB連携) | E21: シート追加。
A22: R1.60 | B22: 43964 | C22: 西山 | D22: 全シート | E22: シート [リスト] を追加。各選択項目(データの入力規則)について整理。
D23: IFレイアウト | E23: 項目「属性」に「日時」を追加。「日時」を選択する際は「書式設定」も指定する必要がある旨をメモに追記。注意喚起の条件付き書式設定を追加。
E24: 項目「文字種別」に「混在」を選択する場合、固定長のフォーマットを選択しないようにメモに注意事項を追記。注意喚起の条件付き書式設定を追加。
E25: 項目「符号」の記載例が不適切な指定になっていた（数値以外の項目に符号を付与する体裁になっていた）ためサンプルを修正。
D26: 対象IF一覧(*) | E26: IF方針として非推奨と規定されたことを踏まえて、「文字コード」の選択肢から「EBCDIC」を削除。
B27: 43977 | C27: 村田 | D27: 項目マッピング | E27: P列以降に対向先セッション用の列を追加。
C28: 西山 | D28: 対象IF一覧(*) | E28: FTPで扱うファイルのフォーマットに「XML」を追加。
E29: FTP/IBMMQで扱うフォーマットで「固定長」以外を選択した場合に、「レコード長」の記入欄がグレーアウトされるように変更。
A30: R1.70 | B30: 44011 | C30: 西山 | D30: 対象IF一覧(*) | E30: 連携元/先で選択可能なプロトコルを追加。
A31: R1.71 | B31: 44077 | C31: 西山 | D31: 対象IF一覧(SFTP→*) 対象IF一覧(*→SFTP) | E31: ・RR連携用にシート追加。 ・「対象IF一覧(FTP→FTP)」のシートは削除。
D32: 対象IF一覧(MQ→*) 対象IF一覧(*→MQ) | E32: ・Apriso MESが工場ごとに別インスタンスとなるとのことからテンプレート変更。 ・「4.システムフロー」の記載例を追加。
D33: 対象IF一覧(*) | E33: ・記載例の誤字を修正。（「牧方」との誤表記(枚方の間違い)あり） ・「抽出条件」の記載例が実情に沿っていなかったのを修正。
D34: 対象IF一覧(FTP→FTP) | E34: ・RRの変換マスタ連携で需要があるとのことだったのでシート復活。
A35: R1.72 | B35: 44099 | C35: 西山 | D35: 対象IF一覧(IDOC→ODBC) | E35: ・過渡期DB連携用(農機DWH経由のK-SCMとの連携を想定)にシート追加。
A36: R1.73 | B36: 44258 | C36: 西山 | D36: 対象IF一覧(MQ→FTP) 対象IF一覧(MQ→IDOC) | E36: ・データ連携基盤側のキュー名をAprisoの工場インスタンスごとに変更。

Sheet リスト
A1: 表紙 | B1: IFフォーマット | J1: 対象IF一覧 | U1: 項目マッピング
A2: 連携方式 | B2: Key | C2: 属性 | D2: 文字種別 | E2: 有り無し | F2: 小数部 | G2: 必須 | H2: 文字埋 | I2: 符号 | J2: プロトコル | K2: フォーマット | L2: 操作内容 | M2: 起動契機 | N2: 連携区分 | O2: 再処理単位 | P2: 文字コード | Q2: 改行コード | R2: 括り文字 | S2: 空ファイル生成 | T2: 有無 | U2: 項目属性 | V2: 桁数表記
A3: ファイル連携 | C3: 文字 | D3: 半角 | E3: 有り | F3: 固定 | H3: 無し | I3: 無 | J3: ALE/IDOC | K3: 可変長(タブ区切り) | L3: 取得 | M3: ジョブ連携 | N3: 全件 | O3: ALL | P3: UTF-8 | Q3: CR+LF | R3: なし | S3: 無 | T3: 有 | U3: 文字(半角のみ) | V3: 文字数
A4: Webサービス連携 | B4: ● | C4: 数値 | D4: 全角 | E4: 無し | F4: 省略 | G4: 〇 | H4: 前ゼロ | I4: 前 | J4: RFC/BAPI | K4: 可変長(カンマ区切り) | L4: 登録・変更・削除 | M4: ファイル検知 | N4: 差分 | O4: トランザクション | P4: ASCII | Q4: CR | R4: ダブルクォーテーション | S4: 有(通常) | T4: 無 | U4: 文字(全角のみ) | V4: Byte数
A5: メッセージ連携 | C5: 日付 | D5: 混在 | H5: 前スペース | I5: 後 | J5: FTP | K5: 固定長 | L5: 登録専用 | M5: 時間指定 | O5: レコード | P5: Shift-JIS | Q5: LF | R5: シングルクォーテーション | S5: 有(0バイト) | U5: 文字(全角半角混在)
A6: SAP直接連携 | C6: 時刻 | H6: 後スペース | J6: SFTP | K6: XML | L6: 変更専用 | M6: 随時 | P6: EUC-JP | R6: その他(備考参照) | U6: 数値(符号付き)
A7: DB連携 | C7: 日付+時刻 | J7: IBMMQ | K7: その他(備考参照) | L7: 削除専用 | M7: 任意 | U7: 数値(符号なし)
J8: MSMQ | M8: 要検討 | U8: 日付
J9: ODBC | M9: その他(備考参照) | U9: 時刻
J10: SOAP | U10: 日付+時刻

Sheet 項目マッピング (02)
A1: IFID | C1: インターフェース名称 | P1: →印刷範囲外（対向先とのセッション時に利用）
A2: =IF(表紙!D16<>"",表紙!D16,"") -> IFZ9000018 | C2: =IF(表紙!D17<>"",表紙!D17,"") -> K-WINC2連携用インボイスデータファイル
A4: 連携元 | G4: 連携元№ | H4: 変換 | J4: 連携先 | Q4: (補足）対向先調整メモ
A5: 部品SAP | H5: 変換仕様 | I5: 現行編集仕様（参考情報） | J5: KWINC2 | Q5: 現行からの変更内容 | T5: 部品SAP再現不可情報 | V5: 備考
A6: № | B6: 項目名称 | C6: 構造 | D6: 技術名称 | E6: 文字数 | F6: 属性 | J6: № | K6: 項目名称 | L6: 構造 | M6: 技術名称 | N6: 文字数 | O6: 属性 | Q6: 桁数 | R6: コード体系 | S6: 補足・その他 | T6: No. | U6: 分類
A7: S010 | G7: S010 | H7: 固定値02 | I7: 02'(固定値) | J7: S010 | K7: データ種別 | M7: DATAID | N7: 2 | O7: 文字(半角のみ)
A8: S020 | B8: 外部荷役単位 ID | C8: VEKP | D8: EXIDV | E8: 20 | F8: CHAR | G8: S020 | H8: ケース№ | I8: パッキング台帳ヘッド：同名項目 | J8: S020 | K8: ケース№ | M8: BCAS | N8: 6 | O8: 文字(半角のみ)
A9: S030 | B9: 受注先 | C9: LIKP | D9: KUNAG | E9: 10 | F9: CHAR | G9: S030 | I9: パッキング台帳ヘッド：同名項目 | J9: S030 | K9: 得意先コード | M9: BTKU | N9: 6 | O9: 文字(半角のみ)
A10: S040 | B10: 計画在庫移動日付 | C10: LIKP | D10: WADAT | E10: 8 | F10: CHAR | G10: S040 | I10: パッキング台帳ヘッド：同名項目 | J10: S040 | K10: 出荷日付 | M10: DSYK | N10: 8 | O10: 文字(半角のみ)
A11: S050 | B11: 得意先グループ 2 | C11: VBAK | D11: KVGR2 | E11: 3 | F11: CHAR | G11: S050 | H11: 貿易区分 | I11: パッキング台帳ヘッド：同名項目 | J11: S050 | K11: 貿易区分 | M11: CBOE | N11: 1 | O11: 文字(半角のみ)
A12: S060 | B12: 出荷条件 | C12: LIKP | D12: VSBED | E12: 2 | F12: CHAR | G12: S060 | H12: 輸送便 | I12: パッキング台帳ヘッド：同名項目 | J12: S060 | K12: 輸送便区分 | M12: CYUS | N12: 1 | O12: 文字(半角のみ)
A13: S070 | G13: S070 | H13: 非標準 | I13: パッキング台帳ヘッド：同名項目 | J13: S070 | K13: 受注担当者コード | M13: BTTSJUC | N13: 3 | O13: 文字(半角のみ)
A14: S080 | G14: S080 | H14: 非標準 | I14: パッキング台帳ヘッド：同名項目 | J14: S080 | K14: 船積担当者コード | M14: BFZMTTS | N14: 3 | O14: 文字(半角のみ)
A15: S090 | G15: S090 | H15: どの国？受注先、出荷先、船積地、仕向地 | I15: パッキング台帳ヘッド：同名項目 | J15: S090 | K15: 国コード | M15: BCOT | N15: 3 | O15: 文字(半角のみ)
A16: S0100 | G16: S0100 | H16: 非標準 | I16: パッキング台帳ヘッド：同名項目 | J16: S0100 | K16: 照会受注区分 | M16: CRETJUC | N16: 1 | O16: 文字(半角のみ)
A17: S0110 | G17: S0110 | H17: 非標準 貴社注文番号(VBAK-BSTNK)とは違う？ | I17: パッキング台帳ヘッド：同名項目 | J17: S0110 | K17: ＫＢＴオーダー№ | M17: BKBTODR | N17: 8 | O17: 文字(半角のみ)
A18: S0120 | G18: S0120 | H18: 非標準 | I18: パッキング台帳ヘッド：同名項目 | J18: S0120 | K18: 契約№１ | M18: BKEI1 | N18: 15 | O18: 文字(半角のみ)
A19: S0130 | G19: S0130 | H19: 非標準 | I19: パッキング台帳ヘッド：同名項目 | J19: S0130 | K19: 契約№２ | M19: BKEI2 | N19: 15 | O19: 文字(半角のみ)
A20: S0140 | B20: 名称1＋名称2 | C20: ADRC ADRC | D20: NAME1 NAME2 | E20: 40 40 | F20: CHAR CHAR | G20: S0140 | H20: 受注先のBPマスタから取得、名称1と名称2の結合 | I20: パッキング台帳ヘッド：同名項目 | J20: S0140 | K20: 得意先名略称（漢字） | M20: NTKURAKKJ | N20: 20 | O20: 文字(全角のみ)
A21: S0150 | G21: S0150 | H21: S0850国コードの名称 ※SAPカスタマイズと同じか要確認 | I21: パッキング台帳ヘッド：同名項目 | J21: S0150 | K21: 国名 | M21: NCOT | N21: 15 | O21: 文字(半角のみ)
A22: S0160 | B22: 出荷単位内容のテキスト | C22: VEKP | D22: INHALT | E22: 40 | F22: CHAR | G22: S0160 | H22: カートン数(出荷単位内容のテキスト) | I22: パッキング台帳ヘッド：同名項目 (999編集) | J22: S0160 | K22: カートン数 | M22: SCTN | N22: 3 | O22: 文字(半角のみ)
A23: S0170 | G23: S0170 | H23: 非標準 | I23: パッキング台帳ヘッド：同名項目 (99999編集) | J23: S0170 | K23: ピース数（合計） | M23: SPCETTL | N23: 5 | O23: 文字(半角のみ)
A24: S0180 | G24: S0180 | H24: 非標準 | I24: パッキング台帳ヘッド：同名項目 (99999編集) | J24: S0180 | K24: セット数（合計） | M24: SSETTTL | N24: 5 | O24: 文字(半角のみ)
A25: S0190 | B25: 荷役単位の積載数量 | C25: VEKP | D25: NTGEW | E25: 15,3 | F25: QUAN | G25: S0190 | I25: パッキング台帳ヘッド：同名項目×1000 (999999999編集) | J25: S0190 | K25: 正味重量（合計） | M25: SSYMGYUTTL | N25: 9 | O25: 文字(半角のみ)
A26: S0200 | B26: 荷役単位の総重量 | C26: VEKP | D26: BRGEW | E26: 15,3 | F26: QUAN | G26: S0200 | I26: パッキング台帳ヘッド：同名項目×100 (9999999編集) | J26: S0200 | K26: 梱包重量 | M26: SKOPGYU | N26: 7 | O26: 文字(半角のみ)
A27: S0210 | B27: 荷役単位の総数量 | C27: VEKP | D27: BTVOL | E27: 15,3 | F27: QUAN | G27: S0210 | I27: パッキング台帳ヘッド：同名項目×1000 (999999編集) | J27: S0210 | K27: 容量 | M27: SYRO | N27: 6 | O27: 文字(半角のみ)
A28: S0220 | G28: S0220 | H28: ケースに梱包されている出荷明細から受注明細をたどり金額を合計？邦貨？外貨？ | I28: パッキング台帳ヘッド：同名項目×100 (9999999999999編集) | J28: S0220 | K28: 金額（合計） | M28: KKINTTL | N28: 13 | O28: 文字(半角のみ)
A29: S0230 | G29: S0230 | H29: ケースに梱包されている出荷明細から受注明細をたどり金額を合計？邦貨？外貨？ | I29: パッキング台帳ヘッド：同名項目 (99999999999編集) | J29: S0230 | K29: 金額２（合計） | M29: KKINTTL2 | N29: 11 | O29: 文字(半角のみ)
A30: S0240 | G30: S0240 | H30: 非標準 | I30: パッキング台帳ヘッド：同名項目 (99999編集) | J30: S0240 | K30: ピース数（日本製） | M30: SPCEMJP | N30: 5 | O30: 文字(半角のみ)
A31: S0250 | G31: S0250 | H31: 非標準 | I31: パッキング台帳ヘッド：同名項目 (99999編集) | J31: S0250 | K31: セット数（日本製） | M31: SSETMJP | N31: 5 | O31: 文字(半角のみ)
A32: S0260 | G32: S0260 | H32: 非標準 （日本製）（米国製）の違いは？ | I32: パッキング台帳ヘッド：同名項目×1000 (999999999編集) | J32: S0260 | K32: 正味重量（日本製） | M32: SSYMGYUMJP | N32: 9 | O32: 文字(半角のみ)
A33: S0270 | G33: S0270 | H33: 非標準 （日本製）（米国製）の違いは？ | I33: パッキング台帳ヘッド：同名項目×100 (9999999999999編集) | J33: S0270 | K33: 金額（日本製） | M33: KKINMJP | N33: 13 | O33: 文字(半角のみ)
A34: S0280 | G34: S0280 | H34: 非標準 | I34: パッキング台帳ヘッド：同名項目 (99999編集) | J34: S0280 | K34: ピース数（米国製） | M34: SPCEMUS | N34: 5 | O34: 文字(半角のみ)
A35: S0290 | G35: S0290 | H35: 非標準 | I35: パッキング台帳ヘッド：同名項目 (99999編集) | J35: S0290 | K35: セット数（米国製） | M35: SSETMUS | N35: 5 | O35: 文字(半角のみ)
A36: S0300 | G36: S0300 | H36: 非標準 （日本製）（米国製）の違いは？ | I36: パッキング台帳ヘッド：同名項目×1000 (999999999編集) | J36: S0300 | K36: 正味重量（米国製） | M36: SSYMGYUMUS | N36: 9 | O36: 文字(半角のみ)
A37: S0310 | G37: S0310 | H37: 非標準 （日本製）（米国製）の違いは？ | I37: パッキング台帳ヘッド：同名項目×100 (9999999999999編集) | J37: S0310 | K37: 金額（米国製） | M37: KKINMUS | N37: 13 | O37: 文字(半角のみ)
A38: S0320 | B38: 販売伝票通貨 | C38: VBAK | D38: WAERK | E38: 3 | F38: CUKY | G38: S0320 | H38: 出荷伝票→受注伝票と辿り受注伝票から取得 | I38: パッキング台帳ヘッド：同名項目 | J38: S0320 | K38: 通貨単位 | M38: CTUKTNI | N38: 3 | O38: 文字(半角のみ)
A39: S0330 | B39: 奥行 幅 高さ | C39: VEKP VEKP VEKP | D39: LAENG BREIT HOEHE | E39: 13,3 13,3 13,3 | F39: QUAN QUAN QUAN | G39: S0330 | H39: 奥行・幅・高さを"X"をセパレータにして結合して設定 | I39: パッキング台帳ヘッド：同名項目 | J39: S0330 | K39: ディメンション | M39: SDIM | N39: 20 | O39: 文字(半角のみ)
A40: S0340 | B40: 梱包材 | C40: VEKP | D40: VHILM | E40: 40 | F40: CHAR | G40: S0340 | H40: 梱包材の品目コードを荷姿コードに変換 | I40: パッキング台帳ヘッド：同名項目 | J40: S0340 | K40: 梱包荷姿 | M40: BKOPNSG | N40: 3 | O40: 文字(半角のみ)
A41: S0350 | G41: S0350 | H41: 非標準 請求用建値とは違う？ | I41: パッキング台帳ヘッド：同名項目 | J41: S0350 | K41: 建値 | M41: TTTE | N41: 20 | O41: 文字(半角のみ)
A42: S0360 | G42: S0360 | H42: 非標準 ■業務Ｔ検討中 | I42: パッキング台帳ヘッド：同名項目 | J42: S0360 | K42: ケースマーク№ | M42: BCAM | N42: 3 | O42: 文字(半角のみ)
A43: S0370 | G43: S0370 | H43: 非標準 | I43: パッキング台帳ヘッド：同名項目 | J43: S0370 | K43: 海外調達有無 | M43: CABRCTTYMU | N43: 1 | O43: 文字(半角のみ)
A44: S0380 | G44: S0380 | H44: 非標準 | I44: パッキング台帳ヘッド：同名項目 | J44: S0380 | K44: サイクルサイン | M44: CCYC | N44: 1 | O44: 文字(半角のみ)
A45: S0390 | G45: S0390 | H45: 非標準 SAPの出荷条件(VSBED)は輸送便として使用しているはずなので別項目？ | I45: パッキング台帳ヘッド：同名項目 | J45: S0390 | K45: 出荷条件 | M45: CSYKJOK | N45: 1 | O45: 文字(半角のみ)
A46: S0400 | G46: S0400 | H46: 非標準 | I46: パッキング台帳ヘッド：同名項目 | J46: S0400 | K46: 梱包条件 | M46: CKPOJOK | N46: 1 | O46: 文字(半角のみ)
A47: S0410 | G47: S0410 | H47: 非標準 | I47: パッキング台帳ヘッド：同名項目 | J47: S0410 | K47: キットありサイン | M47: CKITARI | N47: 1 | O47: 文字(半角のみ)
A48: S0420 | B48: 出荷タイプ | C48: VTTK | D48: VSART | E48: 2 | F48: CHAR | G48: S0420 | H48: 手配方法 | I48: パッキング台帳ヘッド：同名項目 | J48: S0420 | K48: 手配方法 | M48: CTEHMET | N48: 3 | O48: 文字(半角のみ)
A49: S0430 | G49: S0430 | H49: 非標準 | I49: パッキング台帳ヘッド：同名項目 | J49: S0430 | K49: Ｎ／Ｗなしサイン | M49: CNWNOT | N49: 1 | O49: 文字(半角のみ)
A50: S0440 | B50: 品目コード 品目分類：ベアリング区分 | C50: VEPO ZZ_LE_BEAR | D50: MATNR ZZ_BEARING_CATEGORY | E50: 40 1 | F50: CHAR CHAR | G50: S0440 | H50: 梱包対象品目いずれかの分類にベアリングサインが設定されていればフラグ設定でよいか？何故「２」なのか、「１」は無いのか？ | I50: パッキング台帳ヘッド：同名項目 | J50: S0440 | K50: ベアリングサイン２ | M50: CBEA2 | N50: 1 | O50: 文字(半角のみ)
A51: S0450 | G51: S0450 | H51: 非標準 | I51: パッキング台帳ヘッド：同名項目 | J51: S0450 | K51: ベアリングマスターなしサイン | M51: CBEAMASNOT | N51: 1 | O51: 文字(半角のみ)
A52: S0460 | B52: 品目コード 統計品目コード | C52: VEPO MARC | D52: MATNR STAWN | E52: 40 40 | F52: CHAR CHAR | G52: S0460 | H52: 梱包対象品目すべてに統計品目コード(HSコード)が設定されていなければフラグ設定でよいか？ | I52: パッキング台帳ヘッド：同名項目 | J52: S0460 | K52: ＨＳコードなしサイン | M52: CHSCODNOT | N52: 1 | O52: 文字(半角のみ)
A53: S0470 | B53: 品目コード 品目分類：危険物サイン | C53: VEPO ZZ_LE_DAG | D53: MATNR ZZ_DANGEROUSGOODS_SIGN | E53: 40 1 | F53: CHAR CHAR | G53: S0470 | H53: 梱包対象品目いずれかの分類に危険物サインが設定されていればフラグ設定でよいか？ | I53: パッキング台帳ヘッド：同名項目 | J53: S0470 | K53: 危険物ありサイン | M53: CKNBARI | N53: 1 | O53: 文字(半角のみ)
A54: S0480 | B54: シップメント伝票番号 | C54: VTTK | D54: TKNUM | E54: 10 | F54: CHAR | G54: S0480 | H54: インボイスNo | I54: パッキング台帳ヘッド：同名項目 | J54: S0480 | K54: インボイス№ | M54: BINV | N54: 10 | O54: 文字(半角のみ)
A55: S0490 | G55: S0490 | H55: 非標準 | I55: パッキング台帳ヘッド：同名項目 | J55: S0490 | K55: 請求№ | M55: BSEK | N55: 10 | O55: 文字(半角のみ)
A56: S0500 | B56: 計画終了日付 | C56: VTTK | D56: DTDIS | E56: 8 | F56: DATS | G56: S0500 | H56: INVOICE DATE | I56: パッキング台帳ヘッド：同名項目 | J56: S0500 | K56: 請求日付 | M56: DSEK | N56: 8 | O56: 文字(半角のみ)
A57: S0510 | G57: S0510 | H57: 非標準 | I57: パッキング台帳ヘッド：同名項目 | J57: S0510 | K57: パッキングデータ送信指示日付 | M57: DPKDTSDSZ | N57: 8 | O57: 文字(半角のみ)
A58: S0520 | B58: 得意先グループ 1 | C58: VBAK | D58: KVGR1 | E58: 3 | F58: CHAR | G58: S0520 | H58: 送金区分 | I58: パッキング台帳ヘッド：同名項目 | J58: S0520 | K58: 送金区分 | M58: CSKN | N58: 1 | O58: 文字(半角のみ)
A59: S0530 | G59: S0530 | H59: 非標準 | I59: パッキング台帳ヘッド：インボイスNoの上1桁＝'N'の時、全角ブランク編集、以外は、同名項目 | J59: S0530 | K59: 決済条件（漢字） | M59: XKTJKJ | N59: 60 | O59: 文字(全角のみ)
A60: S0540 | G60: S0540 | H60: 非標準 | I60: パッキング台帳ヘッド：インボイスNoの上1桁＝'N'の時、ブランク編集、以外は、同名項目 | J60: S0540 | K60: 決済条件（英語） | M60: XKTJEN | N60: 60 | O60: 文字(半角のみ)
A61: S0550 | G61: S0550 | H61: 非標準 | I61: パッキング台帳ヘッド：同名項目 | J61: S0550 | K61: 請求締め単位 | M61: BSEKSME | N61: 1 | O61: 文字(半角のみ)
A62: S0560 | G62: S0560 | H62: 非標準 | I62: パッキング台帳ヘッド：同名項目 (999編集) | J62: S0560 | K62: 入金期間日数 | M62: SNYUFTDNSU | N62: 3 | O62: 文字(半角のみ)
A63: S0570 | G63: S0570 | H63: 非標準 | I63: パッキング台帳ヘッド：同名項目 | J63: S0570 | K63: 請求起算区分 | M63: CSEKKIB | N63: 1 | O63: 文字(半角のみ)
A64: S0580 | B64: 取引先機能：請求先の得意先コード | C64: VBPA | D64: KUNNR | E64: 10 | F64: CHAR | G64: S0580 | H64: 出荷伝票→受注伝票と辿り受注伝票取引先から取得 | I64: パッキング台帳ヘッド：同名項目 | J64: S0580 | K64: 請求得意先コード | M64: BSEKTKU | N64: 6 | O64: 文字(半角のみ)
A65: S0590 | G65: S0590 | H65: 非標準 | I65: パッキング台帳ヘッド：同名項目 | J65: S0590 | K65: ＤＥＡＬＥＲ直送サイン | M65: CDIRCSO | N65: 1 | O65: 文字(半角のみ)
A66: S0600 | G66: S0600 | H66: S0150通貨単位の名称 ※SAPカスタマイズと同じか要確認 | I66: パッキング台帳ヘッド：同名項目 | J66: S0600 | K66: 通貨単位名称 | M66: NTUKTMI | N66: 3 | O66: 文字(半角のみ)
A67: S0610 | G67: S0610 | H67: 非標準 | I67: パッキング台帳ヘッド：同名項目 | J67: S0610 | K67: 代表得意先コード | M67: BDAITKU | N67: 6 | O67: 文字(半角のみ)
A68: S0620 | G68: S0620 | H68: ブランク | I68: ブランク | J68: S0620 | K68: ケースマーク内容１ | M68: XCAMNAY1 | N68: 40 | O68: 文字(半角のみ)
A69: S0630 | G69: S0630 | H69: ブランク | I69: ブランク | J69: S0630 | K69: ケースマーク内容２ | M69: XCAMNAY2 | N69: 40 | O69: 文字(半角のみ)
A70: S0640 | G70: S0640 | H70: ブランク | I70: ブランク | J70: S0640 | K70: ケースマーク内容３ | M70: XCAMNAY3 | N70: 40 | O70: 文字(半角のみ)
A71: S0650 | G71: S0650 | H71: ブランク | I71: ブランク | J71: S0650 | K71: ケースマーク内容４ | M71: XCAMNAY4 | N71: 40 | O71: 文字(半角のみ)
A72: S0660 | G72: S0660 | H72: ブランク | I72: ブランク | J72: S0660 | K72: ケースマーク内容５ | M72: XCAMNAY5 | N72: 40 | O72: 文字(半角のみ)
A73: S0670 | G73: S0670 | H73: ブランク | I73: ブランク | J73: S0670 | K73: ケースマーク内容６ | M73: XCAMNAY6 | N73: 40 | O73: 文字(半角のみ)
A74: S0680 | G74: S0680 | H74: ブランク | I74: ブランク | J74: S0680 | K74: ケースマーク内容７ | M74: XCAMNAY7 | N74: 40 | O74: 文字(半角のみ)
A75: S0690 | G75: S0690 | H75: ブランク | I75: ブランク | J75: S0690 | K75: ケースマーク内容８ | M75: XCAMNAY8 | N75: 40 | O75: 文字(半角のみ)

Sheet 項目マッピング (03)
A1: IFID | C1: インターフェース名称 | P1: →印刷範囲外（対向先とのセッション時に利用）
A2: =IF(表紙!D16<>"",表紙!D16,"") -> IFZ9000018 | C2: =IF(表紙!D17<>"",表紙!D17,"") -> K-WINC2連携用インボイスデータファイル
A4: 連携元 | G4: 連携元№ | H4: 変換 | J4: 連携先 | Q4: (補足）対向先調整メモ
A5: 部品SAP | H5: 変換仕様 | I5: 現行編集仕様（参考情報） | J5: KWINC2 | Q5: 現行からの変更内容 | T5: 部品SAP再現不可情報 | V5: 備考
A6: № | B6: 項目名称 | C6: 構造 | D6: 技術名称 | E6: 文字数 | F6: 属性 | J6: № | K6: 項目名称 | L6: 構造 | M6: 技術名称 | N6: 文字数 | O6: 属性 | Q6: 桁数 | R6: コード体系 | S6: 補足・その他 | T6: No. | U6: 分類
A7: S010 | G7: S010 | H7: 固定値03 | I7: 03'(固定値) | J7: S010 | K7: データ種別 | M7: DATAID | N7: 2 | O7: 文字(半角のみ)
A8: S020 | B8: 外部荷役単位 ID | C8: VEKP | D8: EXIDV | E8: 20 | F8: CHAR | G8: S020 | H8: ケース№ | I8: パッキング台帳ボディ：同名項目 | J8: S020 | K8: ケース№ | M8: BCAS | N8: 6 | O8: 文字(半角のみ)
A9: S030 | G9: S030 | H9: 非標準 貴社注文番号(VBAK-BSTNK)とは違う？ | I9: パッキング台帳ボディ：同名項目 | J9: S030 | K9: ＫＢＴオーダー№ | M9: BKBTODR | N9: 8 | O9: 文字(半角のみ)
A10: S040 | G10: S040 | H10: 非標準 出荷明細番号か梱包明細番号か何か別の項目？ | I10: パッキング台帳ボディ：同名項目 | J10: S040 | K10: アイテム№ | M10: BITM | N10: 4 | O10: 文字(半角のみ)
A11: S050 | G11: S050 | H11: 非標準 出荷明細番号か梱包明細番号か何か別の項目？ | I11: パッキング台帳ボディ：同名項目 | J11: S050 | K11: アイテム№枝番 | M11: BITMEDA | N11: 2 | O11: 文字(半角のみ)
A12: S060 | B12: 伝票日付 (受信日/送信日) | C12: VBAK | D12: AUDAT | E12: 8 | F12: DATS | G12: S060 | H12: 出荷伝票→受注伝票と辿り受注伝票から取得 | I12: パッキング台帳ボディ：同名項目 （YYYYMMDD編集) | J12: S060 | K12: 受注日付 | M12: DJUC | N12: 8 | O12: 文字(半角のみ)
A13: S070 | G13: S070 | H13: 非標準 | I13: パッキング台帳ボディ：同名項目 | J13: S070 | K13: 契約№１ | M13: BKEI1 | N13: 15 | O13: 文字(半角のみ)
A14: S080 | G14: S080 | H14: 非標準 | I14: パッキング台帳ボディ：同名項目 | J14: S080 | K14: 契約№２ | M14: BKEI2 | N14: 15 | O14: 文字(半角のみ)
A15: S090 | B15: 受注先 | C15: LIKP | D15: KUNAG | E15: 10 | F15: CHAR | G15: S090 | I15: パッキング台帳ボディ：同名項目 | J15: S090 | K15: 得意先コード | M15: BTKU | N15: 6 | O15: 文字(半角のみ)
A16: S0100 | B16: 名称1＋名称2 | C16: ADRC ADRC | D16: NAME1 NAME2 | E16: 40 40 | F16: CHAR CHAR | G16: S0100 | H16: 受注先のBPマスタから取得、名称1名称2の結合 | I16: パッキング台帳ボディ：同名項目 | J16: S0100 | K16: 得意先名略称（漢字） | M16: NTKURAKKJ | N16: 20 | O16: 文字(全角のみ)
A17: S0110 | G17: S0110 | H17: 受注伝票で代替品提案が行われた場合の最初に入力された品目？代替品が適用される場合のデータの見方を確認すること（設計時？） | I17: パッキング台帳ボディ：同名項目 | J17: S0110 | K17: 受注品番 | M17: BJUCHIN | N17: 13 | O17: 文字(半角のみ)
A18: S0120 | B18: 品目コード | C18: VEPO | D18: MATNR | E18: 40 | F18: CHAR | G18: S0120 | I18: パッキング台帳ボディ：同名項目 | J18: S0120 | K18: 手配品番 | M18: BTEHHIN | N18: 13 | O18: 文字(半角のみ)
A19: S0130 | B19: 品目テキスト | C19: MAKT | D19: MAKTX | E19: 40 | F19: CHAR | G19: S0130 | H19: 言語ENの品目テキスト | I19: パッキング台帳ボディ：同名項目 | J19: S0130 | K19: 品名（英語） | M19: NHINEJ | N19: 20 | O19: 文字(半角のみ)
A20: S0140 | B20: 製品部門 | C20: MARA | D20: SPART | E20: 2 | F20: CHAR | G20: S0140 | H20: 工場区分 | I20: パッキング台帳ボディ：同名項目 | J20: S0140 | K20: 工場区分 | M20: CKOJ | N20: 2 | O20: 文字(半角のみ)
A21: S0150 | G21: S0150 | H21: 非標準 | I21: パッキング台帳ボディ：同名項目 | J21: S0150 | K21: 調達区分 | M21: CCTT | N21: 1 | O21: 文字(半角のみ)
A22: S0160 | G22: S0160 | H22: 非標準 | I22: パッキング台帳ボディ：同名項目 | J22: S0160 | K22: ＳＥＴ／ＰＣＳ区分 | M22: CSPP | N22: 1 | O22: 文字(半角のみ)
A23: S0170 | B23: 梱包済数量 | C23: VEPO | D23: VEMNG | E23: 15,3 | F23: QUAN | G23: S0170 | I23: パッキング台帳ボディ：同名項目(合算) (99999編集) | J23: S0170 | K23: 梱包数 | M23: SKOP | N23: 5 | O23: 文字(半角のみ)
A24: S0180 | G24: S0180 | H24: 出荷伝票→受注伝票と辿り受注伝票明細価格情報から外貨の単価を取得？ | I24: パッキング台帳ボディ：同名項目×100 (99999999999編集) | J24: S0180 | K24: 単価（外貨） | M24: TTANABK | N24: 11 | O24: 文字(半角のみ)
A25: S0190 | G25: S0190 | H25: 出荷伝票→受注伝票と辿り受注伝票明細価格情報から外貨の金額を取得？ | I25: パッキング台帳ボディ：同名項目×100(合算) (9999999999999編集) | J25: S0190 | K25: 金額（外貨） | M25: KKINABK | N25: 13 | O25: 文字(半角のみ)
A26: S0200 | G26: S0200 | H26: 出荷伝票→受注伝票と辿り受注伝票明細価格情報から邦貨の単価を取得？ | I26: パッキング台帳ボディ：同名項目 (999999999編集) | J26: S0200 | K26: 単価（円貨） | M26: TTANYEN | N26: 9 | O26: 文字(半角のみ)
A27: S0210 | G27: S0210 | H27: 出荷伝票→受注伝票と辿り受注伝票明細価格情報から邦貨の金額を取得？ | I27: パッキング台帳ボディ：同名項目(合算) (99999999999編集) | J27: S0210 | K27: 金額（円貨） | M27: KKINYEN | N27: 11 | O27: 文字(半角のみ)
A28: S0220 | B28: 正味重量 | C28: MARA | D28: NTGEW | E28: 15,3 | F28: QUAN | G28: S0220 | I28: パッキング台帳ボディ：同名項目(合算) (999999999編集) | J28: S0220 | K28: 単重 | M28: STGY | N28: 9 | O28: 文字(半角のみ)
A29: S0230 | B29: 統計品目コード | C29: MARC | D29: STAWN | E29: 40 | F29: CHAR | G29: S0230 | H29: HSコード | I29: パッキング台帳ボディ：同名項目 | J29: S0230 | K29: ＨＳコード | M29: BHS | N29: 11 | O29: 文字(半角のみ)
A30: S0240 | G30: S0240 | H30: 非標準 | I30: パッキング台帳ボディ：同名項目 | J30: S0240 | K30: キットサイン | M30: CKIT | N30: 1 | O30: 文字(半角のみ)
A31: S0250 | G31: S0250 | H31: 非標準 | I31: パッキング台帳ボディ：同名項目 | J31: S0250 | K31: Ｎ／Ｗなしサイン | M31: CNWNOT | N31: 1 | O31: 文字(半角のみ)
A32: S0260 | B32: 品目分類：ベアリングサイン | C32: ZZ_LE_BEAR | D32: ZZ_BEARING_SIGN | G32: S0260 | I32: パッキング台帳ボディ：同名項目 | J32: S0260 | K32: ベアリングサイン | M32: CBEA | N32: 1 | O32: 文字(半角のみ)
A33: S0270 | G33: S0270 | H33: 非標準 | I33: パッキング台帳ボディ：同名項目 | J33: S0270 | K33: ベアリングマスターなしサイン | M33: CBEAMASNOT | N33: 1 | O33: 文字(半角のみ)
A34: S0280 | G34: S0280 | H34: S0230ＨＳコードで判断 | I34: パッキング台帳ボディ：同名項目 | J34: S0280 | K34: ＨＳコードなしサイン | M34: CHSCODNOT | N34: 1 | O34: 文字(半角のみ)
A35: S0290 | B35: 品目分類：危険物サイン | C35: ZZ_LE_DAG | D35: ZZ_DANGEROUSGOODS_SIGN | E35: 1 | F35: CHAR | G35: S0290 | I35: パッキング台帳ボディ：同名項目 | J35: S0290 | K35: 危険物サイン | M35: CKNB | N35: 1 | O35: 文字(半角のみ)
A36: S0300 | G36: S0300 | H36: S0180単価（外貨） S0200単価（円貨） のどちらか？ | I36: パッキング台帳ボディ：同名項目 (999999999編集) | J36: S0300 | K36: 輸出単価 | M36: TSYS | N36: 9 | O36: 文字(半角のみ)
A37: S0310 | G37: S0310 | H37: 非標準 | I37: パッキング台帳ボディ：同名項目 | J37: S0310 | K37: 受検対象サイン | M37: CJKNTIS | N37: 1 | O37: 文字(半角のみ)
A38: S0320 | B38: 下位レベル荷役単位 | C38: VEPO | D38: UNVEL | E38: 10 | F38: CHAR | G38: S0320 | I38: パッキング台帳ボディ：同名項目 | J38: S0320 | K38: 内装ケース№ | M38: BNAC | N38: 6 | O38: 文字(半角のみ)
A39: S0330 | G39: S0330 | H39: 固定値000 | I39: 0 (999編集) | J39: S0330 | K39: キット内数 | M39: SKITUSU | N39: 3 | O39: 文字(半角のみ)

Sheet 項目マッピング (04)
A1: IFID | C1: インターフェース名称 | P1: →印刷範囲外（対向先とのセッション時に利用）
A2: =IF(表紙!D16<>"",表紙!D16,"") -> IFZ9000018 | C2: =IF(表紙!D17<>"",表紙!D17,"") -> K-WINC2連携用インボイスデータファイル
A4: 連携元 | G4: 連携元№ | H4: 変換 | J4: 連携先 | Q4: (補足）対向先調整メモ
A5: 部品SAP | H5: 変換仕様 | I5: 現行編集仕様（参考情報） | J5: KWINC2 | Q5: 現行からの変更内容 | T5: 部品SAP再現不可情報 | V5: 備考
A6: № | B6: 項目名称 | C6: 構造 | D6: 技術名称 | E6: 文字数 | F6: 属性 | J6: № | K6: 項目名称 | L6: 構造 | M6: 技術名称 | N6: 文字数 | O6: 属性 | Q6: 桁数 | R6: コード体系 | S6: 補足・その他 | T6: No. | U6: 分類
A7: S010 | G7: S010 | H7: 固定値04 | I7: 04'(固定値) | J7: S010 | K7: データ種別 | M7: DATAID | N7: 2 | O7: 文字(半角のみ)
A8: S020 | B8: 外部荷役単位 ID | C8: VEKP | D8: EXIDV | E8: 20 | F8: CHAR | G8: S020 | I8: 原産国管理テーブル：同名項目 | J8: S020 | K8: ケース№ | M8: BCAS | N8: 6 | O8: 文字(半角のみ)
A9: S030 | G9: S030 | H9: 非標準 貴社注文番号(VBAK-BSTNK)とは違う？ | I9: 原産国管理テーブル：同名項目 | J9: S030 | K9: ＫＢＴオーダー№ | M9: BKBTODR | N9: 8 | O9: 文字(半角のみ)
A10: S040 | G10: S040 | H10: 非標準 出荷明細番号か梱包明細番号か何か別の項目？ | I10: 原産国管理テーブル：同名項目 | J10: S040 | K10: アイテム№ | M10: BITM | N10: 4 | O10: 文字(半角のみ)
A11: S050 | G11: S050 | H11: 非標準 出荷明細番号か梱包明細番号か何か別の項目？ | I11: 原産国管理テーブル：同名項目 | J11: S050 | K11: アイテム№枝番 | M11: BITMEDA | N11: 2 | O11: 文字(半角のみ)
A12: S060 | G12: S060 | H12: 非標準 | I12: 原産国管理テーブル：同名項目 (99編集) | J12: S060 | K12: 連番 | M12: BRBN | N12: 2 | O12: 文字(半角のみ)
A13: S070 | G13: S070 | H13: 非標準 ■業務Ｔ検討中 | I13: 原産国管理テーブル：同名項目 但し、原産国管理テーブル：原産国＝'999',ブランクの時は、'000'に編集する | J13: S070 | K13: 原産国 | M13: BGNS | N13: 3 | O13: 文字(半角のみ)
A14: S080 | B14: 梱包済数量 | C14: VEPO | D14: VEMNG | E14: 15,3 | F14: QUAN | G14: S080 | H14: ケース単位の梱包数なら左記だが、原産国だと違う？ | I14: 原産国管理テーブル：同名項目 (99999編集) | J14: S080 | K14: 梱包数 | M14: SKOP | N14: 5 | O14: 文字(半角のみ)
A15: S090 | G15: S090 | H15: 非標準 | I15: 原産国管理テーブル：同名項目 | J15: S090 | K15: 調達区分 | M15: CCTT | N15: 1 | O15: 文字(半角のみ)

Sheet 項目マッピング (05)
A1: IFID | C1: インターフェース名称 | P1: →印刷範囲外（対向先とのセッション時に利用）
A2: =IF(表紙!D16<>"",表紙!D16,"") -> IFZ9000018 | C2: =IF(表紙!D17<>"",表紙!D17,"") -> K-WINC2連携用インボイスデータファイル
A4: 連携元 | G4: 連携元№ | H4: 変換 | J4: 連携先 | Q4: (補足）対向先調整メモ
A5: 部品SAP | H5: 変換仕様 | I5: 現行編集仕様（参考情報） | J5: KWINC2 | Q5: 現行からの変更内容 | T5: 部品SAP再現不可情報 | V5: 備考
A6: № | B6: 項目名称 | C6: 構造 | D6: 技術名称 | E6: 文字数 | F6: 属性 | J6: № | K6: 項目名称 | L6: 構造 | M6: 技術名称 | N6: 文字数 | O6: 属性 | Q6: 桁数 | R6: コード体系 | S6: 補足・その他 | T6: No. | U6: 分類
A7: S010 | G7: S010 | H7: 固定値99 | I7: 99'(固定値) | J7: S010 | K7: データ種別 | M7: DATAID | N7: 2 | O7: 文字(半角のみ)

Sheet 関連テーブル
A1: シップメント伝票 | H1: 出荷伝票 | N1: 梱包情報 | U1: 受注伝票
A2: テーブル | B2: 技術名称 | C2: 項目名称 | D2: 設定値(輸出) | E2: 設定値(三国間) | H2: テーブル | I2: 技術名称 | J2: 項目名称 | K2: 設定値(輸出) | N2: テーブル | O2: 技術名称 | P2: 項目名称 | Q2: 設定値(輸出) | R2: 設定値(三国間) | U2: テーブル | V2: 技術名称 | W2: 項目名称 | X2: 設定値(輸出)
A3: VTTK | B3: TKNUM | C3: シップメント番号 | D3: インボイスNo | E3: 同左 | H3: LIKP | I3: VBELN | J3: 出荷伝票 | K3: 出荷伝票番号を一意に識別する番号。 | N3: VEKP | O3: VENUM | P3: 内部荷役単位番号 | Q3: 内部採番でユニークキー | R3: 同左 | U3: VBAK | V3: VBELN | W3: 販売伝票 | X3: 販売伝票を一意に識別する番号を自動提案(提案値変更不可) 各種受注起票時に採番される。
A4: VTTK | B4: VBTYP | C4: 販売管理伝票カテゴリ | D4: 8(シップメント)固定 | E4: 同左 | H4: LIKP | I4: VSTEL | J4: 出荷ポイント/入荷ポイント | K4: ピッキング・梱包LT、積載LTを決定するコード値。受注伝票の値が引き継がれる。 | N4: VEKP | O4: EXIDV | P4: 外部荷役単位 ID | Q4: 外装ケースNoまたは内装ケースNo | R4: 外装ケースNo | U4: VBAK | V4: ERDAT | W4: レコード登録日 | X4: レコード登録日付 システム日付を自動提案(提案値変更不可)
A5: VTTK | B5: SHTYP | C5: シップメント番号タイプ | D5: 部品（輸出）固定値 | E5: 部品（三国間）固定値 | H5: LIKP | I5: WADAT | J5: 計画在庫移動日付 | K5: 得意先へ品目を出荷する日付を指定する。 | N5: VEKP | O5: EXIDA | P5: 外部荷役単位 ID タイプ | Q5: B(得意先割当番号)固定 | R5: 同左 | U5: VBAK | V5: ERZET | W5: 登録時刻 | X5: 受注伝票を登録した時刻。受注伝票を登録した際のシステム時刻を自動設定。(提案値変更不可) HH:MM:SS
A6: VTTK | B6: TPLST | C6: 輸送計画ポイント | D6: 固定値 | E6: 同左 | H6: LIKP | I6: LDDAT | J6: 積載日付 | K6: 積載する日付。受注伝票から値が引き継がれる。 | N6: VEKP | O6: VSTEL | P6: 出荷ポイント/入荷ポイント | Q6: 出荷明細から自動設定 | R6: 受注明細から自動設定 | U6: VBAK | V6: ERNAM | W6: オブジェクト登録者名 | X6: 受注登録者 伝票登録ユーザを自動提案(提案値変更不可)
A7: VTTK | B7: ERDAT | C7: レコード登録日付 | D7: シップメント伝票登録日 | E7: 同左 | H7: LIKP | I7: TDDAT | J7: 輸送計画日付 | K7: 輸送計画する日付。受注伝票から値が引き継がれる。 | N7: VEKP | O7: BRGEW | P7: 荷役単位の総重量 | Q7: 外装ケースの総重量 | R7: 同左 | U7: VBAK | V7: AUDAT | W7: 伝票日付 (受信日/送信日) | X7: 受注の受付日付。伝票登録時のシステム日付が自動登録される。(提案値変更可)
A8: VTTK | B8: VSART | C8: 出荷タイプ | D8: 手配方法 | E8: 同左 | H8: LIKP | I8: LFDAT | J8: 納入日付 | K8: 納入先への着荷日を指定する。 | N8: VEKP | O8: NTGEW | P8: 荷役単位の積載数量 | Q8: 外装ケースの正味重量または内装ケースの正味数量 (品目マスタから正味重量を積み上げして設定) | R8: 同左 | U8: VBAK | V8: VBTYP | W8: 販売管理伝票カテゴリ | X8: 販売伝票の区別に使用 自動設定 固定値"C:受注"
A9: VTTK | B9: ROUTE | C9: シップメント経路 | D9: AIRの場合、 A + 得意先コード先頭5桁 + 揚げ地の接頭語1桁 SEAの場合 S + 得意先コード先頭5桁 + 揚げ地の接頭語1桁 | E9: 同左 | H9: LIKP | I9: KODAT | J9: ピッキング日付 | K9: ピッキングする日付。 受注伝票から値が引き継がれる。 | N9: VEKP | O9: GEWEI | P9: 重量単位 | Q9: 固定値KG | R9: 同左 | U9: VBAK | V9: AUART | W9: 販売伝票タイプ | X9: 登録する受注伝票の種別を表す受注伝票タイプ。 Z101
A10: VTTK | B10: EXTI1 | C10: 外部 ID 1 | D10: OCEAN B/L No. | H10: LIKP | I10: ROUTE | J10: 輸送経路 | K10: 出荷元から納所への輸送に要する日数を表す。受注伝票の値が引き継がれる。 | N10: VEKP | O10: BTVOL | P10: 荷役単位の総数量 | Q10: 外装ケースの総容積 | R10: 同左 | U10: VBAK | V10: LIFSK | W10: 出荷ブロック (伝票ヘッダ) | X10: 得意先単位に自動で出荷伝票を作成しない制限を設ける。マスタ－に設定された受注先を登録すると出荷ブロックが自動で提案される。出荷ブロックを解除する際は、受注伝票の変更画面から出荷ブロックを解除する。 Z1：前金未入金
A11: VTTK | B11: DTDIS | C11: 計画終了日付 | D11: INVOICE DATE | H11: LIKP | I11: VSBED | J11: 出荷条件 | K11: 仕入先から得意先へ出荷する場合の一般的な出荷基本方針。受注伝票から値が引き継がれる。 | N11: VEKP | O11: VHILM | P11: 梱包材 | Q11: 荷姿の品目コード | R11: 同左 | U11: VBAK | V11: NETWR | W11: 受注正味額 (伝票通貨) | X11: 伝票上の通貨で表示する販売伝票全明細の総額情報 自動計算
A12: VTTK | B12: STREG | C12: チェックインステータス | D12: 船積指図書出力 | H12: LIKP | I12: KUNNR | J12: 出荷先 | K12: 出荷先を表すコード。受注伝票の値が引き継がれる。 | N12: VEKP | O12: LAENG | P12: 長さ | Q12: ディメンションの長さ | R12: 同左 | U12: VBAK | V12: WAERK | W12: 販売伝票通貨 | X12: 伝票に対して適用される通貨。ヘッダ-受注管理の伝票通貨が自動提案される。 JPY 日本円 USD アメリカドル
A13: VTTK | B13: STLBG | C13: 積載開始のステータス | D13: インボイスデータ伝送 | H13: LIKP | I13: KUNAG | J13: 受注先 | K13: 受注先を表すコード。受注伝票の値が引き継がれる。 | N13: VEKP | O13: BREIT | P13: 幅 | Q13: ディメンションの幅 | R13: 同左 | U13: VBAK | V13: VKORG | W13: 販売組織 | X13: 受注する組織・法人を識別する全事業共通の規定販売組織を入力する。 P001：部品事業 P002：ソリューション事業 R003：関商
A14: VTTK | B14: TDLNR | C14: 海貨業者番号 | D14: 固定値 | H14: LIKP | I14: KDGRP | J14: 得意先グループ | K14: 販売ルート区分を識別するコード。受注伝票の値が引き継がれる。 | N14: VEKP | O14: HOEHE | P14: 高さ | Q14: ディメンションの高さ | R14: 同左 | U14: VBAK | V14: VTWEG | W14: 流通チャネル | X14: 得意先からのオ－ダ－種別を分類する全事業共通の規定流通チャネルを入力する。 P1：国内 P2：輸出
A15: VTTK | B15: FRKRL | C15: 運賃関連 | D15: 固定値 | H15: LIKP | I15: XABLN | J15: 入出庫票番号 | K15: K-WINCとの出荷情報連携のキーである「出荷連絡No」を登録する。 | N15: VEKP | O15: MEABM | P15: 容積単位 (長さ/幅/高さ) | Q15: CM固定 | R15: 同左 | U15: VBAK | V15: SPART | W15: 製品部門 | X15: 販売組織に対して、取り扱う商品群をグル－プ化する単位。 P0：共通 21：堺製造所 23：枚方製造所 26：宇都宮工場 28：筑波工場 29：堺臨海工場
A16: VTTK | B16: ADD01 | C16: 補足 1 | D16: SIZE(1) | E16: 未使用 | H16: LIKP | I16: WADAT_IST | J16: 実在庫移動日付 | K16: 実際に品目が出荷された日付を指定する。 | N16: VEKP | O16: MEINS | P16: 基本数量単位 | Q16: 荷姿の基本数量単位 | R16: 同左 | U16: VBAK | V16: KNUMV | W16: 伝票条件番号 | X16: 受注に適用する 条件を保存するときの内部番号となり、価格情報との結びつき番号になる。
A17: VTTK | B17: ADD02 | C17: 補足 2 | D17: SIZE(2) | E17: 未使用 | H17: LIPS | I17: VBELN | J17: 出荷伝票 | K17: 出荷伝票番号を一意に識別する番号。 | N17: VEKP | O17: VOLEH_MAX | P17: 容積単位 | Q17: M3固定 | R17: 同左 | U17: VBAK | V17: VDATU | W17: 指定納期 | X17: 得意先からの納入指定日をマニュアルで入力する。指定納期には日付での入力を必須とする。入力初期値はブランクとし、当日や特定の日付を初期値として提案しない。 YYYY/MM/DD
A18: VTTK | B18: ADD03 | C18: 補足 3 | D18: SIZE(3) | E18: 未使用 | H18: LIPS | I18: POSNR | J18: 出荷明細 | K18: 出荷伝票の明細番号。 | N18: VEKP | O18: GEWEI_MAX | P18: 重量単位 | Q18: KG固定 | R18: 同左 | U18: VBAK | V18: VSBED | W18: 出荷条件 | X18: 仕入先から得意先へ出荷する場合の一般的な出荷基本方針。共通で使用する出荷条件が自動提案される。 Z1：SEA(輸出) Z2：AIR(輸出)
A19: VTTK | B19: ADD04 | C19: 補足 4 | D19: SIZE(4) | E19: 未使用 | H19: LIPS | I19: MATNR | J19: 品目コード | K19: 出荷する品目コード。受注伝票の値が引き継がれる。 | N19: VEKP | O19: INHALT | P19: 出荷単位内容のテキスト | Q19: カートン数 | R19: 同左 | U19: VBAK | V19: BSTNK | W19: 得意先参照 | X19: 得意先に対する注文番号(貴社注文番号)。得意先から受領した納入指示番号、もしくは得意先からのオ－ダ－を一意に識別可能な番号を入力する。
A20: VTTK | B20: TEXT1 | C20: 追加テキスト 1 | D20: CONTAINER NO.(1) | E20: 未使用 | H20: LIPS | I20: WERKS | J20: プラント | K20: 品目を出荷するプラント。受注伝票の値が引き継がれる。 | N20: VEKP | O20: VPOBJ | P20: 梱包対象 | Q20: 01(出荷伝票)固定 | R20: 02(販売伝票)固定 | U20: VBAK | V20: BSARK | W20: 得意先購買発注タイプ | X20: 得意先から販売伝票 (引合伝票または受注伝票など) が届く媒体 ブランク マニュアル受注 DFUE デ－タ転送
A21: VTTK | B21: TEXT2 | C21: 追加テキスト 2 | D21: CONTAINER NO.(2) | E21: 未使用 | H21: LIPS | I21: LGORT | J21: 保管場所 | K21: 品目を出荷する保管場所。受注伝票の値が引き継がれる。 | N21: VEKP | O21: UEVEL | P21: 上位レベル明細用途 ID荷役単位 | Q21: 内装ケースの場合にその上位にあたる外装ケースの内部荷役単位番号 | U21: VBAK | V21: BSTDK | W21: 得意先参照日付 | X21: 得意先が購買発注を登録した日付。得意先からの発注日(クボタ受注登録日)を設定する。 自動提案される。
A22: VTTK | B22: TEXT3 | C22: 追加テキスト 3 | D22: CONTAINER NO.(3) | E22: 未使用 | H22: LIPS | I22: KDMAT | J22: 得意先品目 | K22: 得意先品目マスタに登録があれば、マスタから自動設定される。 | N22: VEPO | O22: VENUM | P22: 内部荷役単位番号 | Q22: 内部採番でユニークキー | R22: 同左 | U22: VBAK | V22: IHREZ | W22: 参照 | X22: 得意先から発注を受けた会社。EDI発注会社コードを受注EDIにて入力する。
A23: VTTK | B23: TEXT4 | C23: 追加テキスト 4 | D23: CONTAINER NO.(4) | E23: 未使用 | H23: LIPS | I23: LFIMG | J23: 出荷数量実績 (販売単位) | K23: 出荷伝票上で指定している単位に対する出荷数量。 | N23: VEPO | O23: VEPOS | P23: 荷役単位明細 | Q23: 内部採番でユニークキー(明細) | R23: 同左 | U23: VBAK | V23: KUNNR | W23: 受注先 | X23: 受注先を識別するコ－ド。マニュアルで入力する。事前にマスタ－デ－タに登録された顧客のみ使用可能。事業を横断して販売するケ－スが存在する。
A24: VTTK | B24: TNDR_TRKID | C24: 海貨業者追跡 ID | D24: COURIER/EMS TRACKING NO. | E24: 未使用 | H24: LIPS | I24: VRKME | J24: 販売単位 | K24: 販売単位。品目マスタの値が自動でセットされる。 | N24: VEPO | O24: VELIN | P24: 荷役単位明細内容タイプ | Q24: 品目の場合1(品目明細)、内装ケースの場合3(荷役単位) | R24: 固定値1(品目明細) | U24: VBAK | V24: AEDAT | W24: 最終変更日付 | X24: 伝票の最終更新日付を自動設定
A25: VTTP | B25: TKNUM | C25: シップメント番号 | D25: インボイスNo | E25: 同左 | H25: LIPS | I25: NTGEW | J25: 正味重量 | K25: 出荷伝票の全明細の全体正味重量。受注伝票から値が引き継がれる。 | N25: VEPO | O25: VBELN | P25: 出荷伝票 | Q25: 品目の場合は出荷伝票番号、内装ケースの場合はINITIAL | R25: 受注伝票番号 | U25: VBAK | V25: KVGR1 | W25: 得意先グループ 1 | X25: 送金区分
A26: VTTP | B26: TPNUM | C26: シップメント明細 | D26: インボイス明細番号 | E26: 同左 | F26: ※三国間は出荷との紐付け無し？ | H26: LIPS | I26: BRGEW | J26: 総重量 | K26: 全出荷明細の合計総重量を示す。総重量とは、正味重量と梱包材料の合計。受注伝票から値が引き継がれる。 | N26: VEPO | O26: POSNR | P26: 出荷明細 | Q26: 品目の場合は出荷伝票明細番号、内装ケースの場合はINITIAL | R26: 出荷伝票明細番号 | U26: VBAK | V26: KVGR2 | W26: 得意先グループ 2 | X26: 貿易区分
A27: VTTP | B27: VBELN | C27: 出荷伝票 | D27: 出荷伝票 | H27: LIPS | I27: LADGR | J27: 積載グループ | K27: 後付け作業に必要な日数を表す区分。品目マスタから値が自動提案される。 | N27: VEPO | O27: UNVEL | P27: 下位レベル荷役単位 | Q27: 品目の場合はINITIAL、内装ケースの場合その下位レベルの内部荷役単位番号 | U27: VBAK | V27: VGBEL | W27: 参照伝票番号 | X27: 受注伝票から受注伝票コピーした場合、元伝票番号が設定される。
A28: VTTP | B28: TPRFO | C28: 出荷明細の順序 | D28: 出荷明細の順序 | H28: LIPS | I28: KVGR1 | J28: 得意先グループ 1 | K28: 得意先を地域ごとにグル－ピングする。受注伝票から値が引き継がれる。 | N28: VEPO | O28: VEMNG | P28: 荷役単位明細での梱包済基本数量 | Q28: 品目の場合は品目の梱包数、内装ケースの場合はINITIAL | R28: 品目の梱包数 | U28: VBAK | V28: BUKRS_VF | W28: 請求対象の会社コード | X28: 独立した会計単位。販売組織に紐づく会社コ－ドが自動提案される。 1000 株式会社クボタ
A29: VTTS | B29: TKNUM | C29: シップメント番号 | D29: インボイスNo | E29: 同左 | H29: LIPS | I29: MVGR1 | J29: 品目グループ 1 | K29: 科目を識別するキ－を指定する。受注伝票から値が引き継がれる。 | N29: VEPO | O29: VEMEH | P29: 梱包予定数量の基本数量単位 (VEMNG) | Q29: 品目の場合は品目の基本数量単位、内装ケースの場合はINITIAL | R29: 品目の基本数量単位 | U29: VBAK | V29: TAXK1 | W29: 代替税分類 | X29: 消費税等の税種別、税率を決定するキー情報の一つ。 得意先マスタから自動提案される。 0:非課税 1:課税 2:免税
A30: VTTS | B30: TSNUM | C30: 輸送番号の段階 | D30: FROM/VIA/TO(1)/TO(2)の段階1～3 | E30: 同左 | H30: LIPS | I30: MVGR2 | J30: 品目グループ 2 | K30: 機種を識別するキ－が指定される。 受注伝票から値が引き継がれる。 | N30: VEPO | O30: MATNR | P30: 品目コード | Q30: 品目の場合は品目コード、内装ケースの場合はINITIAL | R30: 品目コード | U30: VBAK | V30: LAST_CHANGED_BY_USER | W30: ビジネス文書を最後に変更したユーザ | X30: 販売伝票を最後に更新したユーザ 自動提案(提案値変更不可)
A31: VTTS | B31: ROUTE | C31: シップメントステージの輸送経路 | D31: AIRの場合、 A + 得意先コード先頭5桁 + 揚げ地の接頭語1桁 SEAの場合 S + 得意先コード先頭5桁 + 揚げ地の接頭語1桁 | H31: LIPS | I31: /CWM/PIKMG | J31: ピッキング数量/受入数量 (パラレル数量単位) | K31: ピッキング数量。ハンディもしくは手動で出荷実績を登録した際の数量実績がセットされる。 | N31: VEPO | O31: WERKS | P31: プラント | Q31: 出荷伝票から導出 | R31: 受注伝票から導出 | U31: VBAK | V31: ABSTK | W31: 拒否ステータス (すべての明細) | X31: 販売伝票明細の拒否理由が設定されているかどうかでステータスが変わる A:いずれの明細にも拒否理由が未設定 B:一部の明細に拒否理由が設定 C:全明細に拒否理由が設定
A32: VTTS | B32: INCO1 | C32: インコタームズ: 印刷 | D32: 請求用建値 | H32: ADRC | I32: ADDRNUMBER | J32: アドレス番号 | K32: アドレス管理アドレス識別のための内部キー | N32: VEPO | O32: LGORT | P32: 保管場所 | Q32: 出荷伝票から導出 | R32: 受注伝票から導出 | U32: VBAK | V32: FKSAK | W32: 請求ステータス (受注関連請求伝票) | X32: 全請求ステータスは、受注伝票または出荷伝票が請求書に関係があるか、関係があるならば、請求がどのくらい行われたかを示す。
A33: VTTS | B33: KNOTA | C33: 船積地点 | D33: FROM/VIA/TO(1)の港コード ※段階1はかならずFROM | H33: ADRC | I33: NAME1 | J33: 名称 1 | K33: 名称（漢字/英数字）1 | N33: VEPO | O33: SOBKZ | P33: 特殊在庫区分 | Q33: 特殊在庫区分 | R33: 同左 | U33: VBAK | V33: FSSTK | W33: 請求ブロックステータス (すべての明細) | X33: 明細の請求ブロックステータス + 販売伝票請求ブロック + ユーザステータスヘッダ
A34: VTTS | B34: KUNNA | C34: 出荷ポイント: 得意先 | D34: FROM/VIA/TO(1)の港コードに対するBPコード | H34: ADRC | I34: NAME2 | J34: 名称 2 | K34: 名称（漢字/英数字）2 | U34: VBAK | V34: GBSTK | W34: 全処理ステータス (ヘッダ/すべての明細) | X34: 全処理が完了しているかのステ－タスを示す。 関連なし A 未処理 B 一部処理済 C 処理完了
A35: VTTS | B35: BELAD | C35: 船積地点: 追加情報 (積載ポイントなど) | D35: SHIPPED PER ※段階1にのみ設定 | H35: ADRC | I35: NAME3 | J35: 名称 3 | K35: 名称（半角カナ）1 | U35: VBAK | V35: LFGSK | W35: 全出荷ステータス (すべての明細) | X35: 受注伝票の全明細の出荷状況をステータスで管理する。
A36: VTTS | B36: KNOTZ | C36: 納入ポイント | D36: VIA/TO(1)/TO(2)の港コード | H36: ADRC | I36: NAME4 | J36: 名称 4 | K36: 名称（半角カナ）2 | U36: VBAK | V36: LFSTK | W36: 出荷ステータス (全明細) | X36: 受注伝票の全明細の出荷状況をステータスで管理する。
A37: VTTS | B37: KUNNZ | C37: 納入ポイントの得意先コード | D37: VIA/TO(1)/TO(2)の港コードに対するBPコード | H37: ADRC | I37: CITY1 | J37: 市区町村 | K37: 住所（漢字/英数字）2 | U37: VBAK | V37: LSSTK | W37: 全出荷ブロックステータス (すべての明細) | X37: 明細出荷ブロックステータス + 伝票ヘッダ出荷ブロック + ヘッダユーザステータス
A38: VTTS | B38: ABLAD | C38: 仕向地: 追加情報 (例: 荷渡ポイント) | D38: 揚げ地 ※段階1にのみ設定 | H38: ADRC | I38: POST_CODE1 | J38: 市区町村の郵便番号 | K38: 郵便番号 | U38: VBAK | V38: RFGSK | W38: 全参照ステータス (すべての明細) | X38: 販売伝票の参照状況ステータス
A39: VTTS | B39: TDLNR | C39: シップメントステージの海貨業者番号 | D39: 固定値 | H39: ADRC | I39: TRANSPZONE | J39: 商品の納入区域 | K39: 得意先の納入区域。 | U39: VBAK | V39: RFSTK | W39: 参照ステータス (すべての明細) | X39: １枚または複数の販売伝票がこの明細を部分的にか全体的に参照しているかどうか、またはまったく参照していないのかが、ステータスメッセージで表示される
A40: VTTS | B40: ADRKNZA | C40: 船積地点: 原産地区分 | D40: A(マスタの住所)固定 | H40: ADRC | I40: STREET | J40: 地名 | K40: 得意先の住所。得意先マスタで定義される地名が自動提案される。 | U40: VBAK | V40: SPSTG | W40: 全ブロックステータス (ヘッダ) | X40: 全ブロック系のステ－タスがたっているかどうかのステ－タス。 関連なし A 未処理 B 一部処理済 C 処理完了
A41: VTTS | B41: ADRKNZZ | C41: 仕向先: 原産地区分 | D41: A(マスタの住所)固定 | H41: ADRC | I41: COUNTRY | J41: 国コード | K41: 国を表すコード JP：日本 | U41: VBAK | V41: TRSTA | W41: 輸送計画ステータス (ヘッダ) | X41: 輸送計画の実行された範囲を表示す。
H42: ADRC | I42: REGION | J42: 地域 (都道府県) | K42: 得意先の住所。得意先マスタで定義される地名が自動提案される。 ワンタイム出荷先では入力が必要 | U42: VBAK | V42: UVALL | W42: 不完全ステータス (ヘッダ) | X42: 一般ヘッダ情報の不完全ステ－タス。一般情報にはビジネス、出荷、請求デ－タが含まれる。 関連なし A 未処理 B 一部処理済 C 処理完了
H43: ADRC | I43: SORT1 | J43: 検索語句 1 | K43: 得意先名称の半角カナテキスト | U43: VBAK | V43: UVALS | W43: 不完全ステータス (すべての明細) | X43: 一般明細情報の不完全ステ－タス。 関連なし A 未処理 B 一部処理済 C 処理完了
H44: ADRC | I44: TEL_NUMBER | J44: 第 1 電話番号: 局番 + 番号 | K44: 電話番号 | U44: VBAK | V44: UVFAK | W44: 請求不完全ステータス (ヘッダ) | X44: 請求関連ヘッダ情報の完了ステ－タス。 関連なし A 未処理 B 一部処理済 C 処理完了
H45: ADRC | I45: FAX_NUMBER | J45: 第 1 FAX 番号: 局番 + 番号 | K45: FAX番号 | U45: VBAK | V45: UVFAS | W45: 請求不完全ステータス (すべての明細) | X45: 請求関連明細情報の完了ステ－タス。 関連なし A 未処理 B 一部処理済 C 処理完了
U46: VBAK | V46: UVPRS | W46: 価格設定不完全ステータス (すべての明細) | X46: 販売伝票の価格設定ステータス
U47: VBAK | V47: UVVLK | W47: 出荷不完全ステータス (ヘッダ) | X47: 出荷関連ヘッダ情報の不完全ステ－タス。 関連なし A 未処理 B 一部処理済 C 処理完了
U48: VBAK | V48: UVVLS | W48: 出荷不完全ステータス (すべての明細) | X48: 出荷関連明細情報不完全ステ－タス。 関連なし A 未処理 B 一部処理済 C 処理完了
U49: VBAK | V49: WBSTK | W49: 在庫移動ステータス (すべての明細) | X49: 出荷品が自社の敷地から送られたかどうか、および出荷の処理状況を指定する
U50: VBAP | V50: MANDT | W50: クライアント | X50: システムクライアントを自動提案(提案値変更不可)
U51: VBAP | V51: VBELN | W51: 販売伝票 | X51: 販売伝票を一意に識別する番号を自動提案(提案値変更不可) 各種受注起票時に採番される。
U52: VBAP | V52: POSNR | W52: 販売伝票明細 | X52: 受注明細を一意に識別する番号。10から＋10単位に自動採番される。
U53: VBAP | V53: MATNR | W53: 品目コード | X53: 品目を一意に識別するコ－ド。受注した型式および品番を選択する。販売型式として登録がない製品や販売開始前、販売終了後の品目コ－ドは、入力不可とする。
U54: VBAP | V54: MATKL | W54: 品目グループ | X54: 同じ属性を持つ複数の 品目または、 サ－ビスをグル－プ化し、それを特定の品目グル－プに割り当てるために使用するキ－。品目マスタで設定された品目グル－プが自動提案される。
U55: VBAP | V55: ARKTX | W55: 受注明細のテキスト (短) | X55: 受注明細の品目名を示す。品目マスタで登録された品目コ－ドに結び付いた品目名が自動提案される。マニュアルでの変更も可能。
U56: VBAP | V56: PSTYV | W56: 明細カテゴリ (販売伝票) | X56: Z002：標準明細(海外) ZAPA：標準ソーシング Z006：個別購買発注(輸出) Z008：仕入先直送明細(輸出)
U57: VBAP | V57: LFREL | W57: 明細は出荷関連 | X57: テキストまたは値の明細が出荷処理に関連するかどうかを示す。
U58: VBAP | V58: FKREL | W58: 請求関連 | X58: 請求の基になる対象を示す。 請求の種類を表示 自動提案(提案値変更可) 例:A(出荷関連請求伝票)
U59: VBAP | V59: UEPOS | W59: BOM 構成の上位レベル明細
U60: VBAP | V60: ABGRU | W60: 販売伝票の拒否理由 | X60: 各種受注の取り消し、及び取り消し理由を管理する。
U61: VBAP | V61: PRODH | W61: 品目階層 | X61: 品目の分類を階層化、事業と紐づける
U62: VBAP | V62: MEINS | W62: 基本数量単位 | X62: 品目の 在庫を管理する数量単位。他の数量単位で入力した数量 (代替数量単位) は、全て基本数量単位に変換される。
U63: VBAP | V63: POSEX | W63: 元となる購買発注の明細番号 | X63: 得意先が明細を一意に識別するために使用する明細番号を指定する。 貴社注文番号明細を指定する。
U64: VBAP | V64: GRKOR | W64: 出荷グループ (明細一括出荷) | X64: 同時に出荷する明細の組合せをグル－ピングする番号。
U65: VBAP | V65: FMENG | W65: 数量固定 | X65: 確認済数量が取得できている伝票に対して、再日程にて確認済数量がとられないようにするためのフラグとして使用。
U66: VBAP | V66: SPART | W66: 製品部門 | X66: 販売組織に対して、取り扱う商品群をグル－プ化する単位。 P0：共通 21：堺製造所 23：枚方製造所 26：宇都宮工場 28：筑波工場 29：堺臨海工場
U67: VBAP | V67: NETWR | W67: 伝票通貨での受注明細正味額 | X67: 値引および追加料金を考慮した後の明細の正味額を示す。明細-条件の正味額が自動提案される。
U68: VBAP | V68: WAERK | W68: 販売伝票通貨 | X68: 伝票に対して適用される通貨。ヘッダ-受注管理の伝票通貨が自動提案される。 JPY 日本円 USD アメリカドル
U69: VBAP | V69: KWMENG | W69: 累積受注数量 (販売単位) | X69: 受注数量を整数で入力する。
U70: VBAP | V70: VRKME | W70: 販売単位 | X70: 品目販売上の販売単位。品目マスタの販売数量単位または基本数量単位が自動提案される。 PC 台
U71: VBAP | V71: UMVKZ | W71: 販売数量単位から基本数量単位への変換係数の分子 | X71: 販売単位と基本数量単位との変換をするための販売単位の数字(例の1) 例：1SET（販売単位）＝4PCS（基本数量単位）
... U205: OBJK | V205: SERNR | W205: シリアル番号 | X205: 品目シリアル化のシリアル番号を指定する。製品に割り当てられた機番を入力する。 建機、中古品の受注登録で記入が要求される。

Sheet 文書変更履歴
A1: 文書変更履歴 | F1: レビュー | I1: 承認
A2: No. | B2: 変更日 | C2: 変更者 | D2: 変更箇所 | E2: 変更内容 | F2: TISレビュー者 | G2: 開発管理レビュー者 | H2: KBTレビュー者 | I2: KBT承認 | J2: 承認日
A3: 0.01 | B3: 46013 | C3: TIS竹田 | D3: 全文書 | E3: 初版 | F3: TIS丸山
A4: 0.80 | B4: 46014 | C4: TIS奥川 | D4: ー | E4: 要件定義工程納品のためバージョンアップ
A5: 0.81 | B5: 46062 | C5: TIS齊藤 | D5: 表紙 | E5: IFID訂正：IF0018→IFZ9000018
A6: 0.81 | B6: 46062 | C6: TIS齊藤 | D6: 項目マッピング (01) | E6: S060連携元変更；KNA1-NAME3＋NAME4→ADRC-NAME1＋NAME2 S0100連携元変更：KNA1-NAME3＋NAME4→ADRC-NAME1＋NAME2 S0110連携元変更：KNA1-ORT01＋STRAS→ADRC-CITY1＋STREET
A7: 0.81 | B7: 46062 | C7: TIS齊藤 | D7: 項目マッピング (02) | E7: S0140連携元変更；KNA1-NAME3＋NAME4→ADRC-NAME1＋NAME2 S0440連携元変更；ZZ_BEARING_SIGN→ZZ_BEARING_CATEGORY
A8: 0.81 | B8: 46062 | C8: TIS齊藤 | D8: 項目マッピング (03) | E8: S0100連携元変更；KNA1-NAME3＋NAME4→ADRC-NAME1＋NAME2
